Workbook

Sheet Brownian Motion simulation
A1: GEOMETRIC BROWNIAN MOTION
A2: Initial Price | B2: 22828 | E2: Press F9 to generate new Zs
A3: Expected Return | B3: 0.08
A4: Annual Volatility | B4: 0.1939
A5: Time (In years) | B5: 1
A6: Steps per year (N) | B6: 252
A7: Delta | B7: =B5/B6 -> 0.003968254
A9: Step | B9: Random Z | C9: Simulated Price
A10: 0 | C10: =B2 -> 22828
A11: =A10+1 -> 1 | B11: =_xlfn.NORM.S.INV(RAND()) -> 0.22234656 | C11: =C10 * EXP((($B$3 - 0.5 * $B$4^2) * $B$7) + ($B$4 * SQRT($B$7) * B11)) -> 22895.642
A12: =A11+1 -> 2 | B12: =_xlfn.NORM.S.INV(RAND()) -> -0.055258016 | C12: =C11 * EXP((($B$3 - 0.5 * $B$4^2) * $B$7) + ($B$4 * SQRT($B$7) * B12)) -> 22885.751
A13: =A12+1 -> 3 | B13: =_xlfn.NORM.S.INV(RAND()) -> 0.72289923 | C13: =C12 * EXP((($B$3 - 0.5 * $B$4^2) * $B$7) + ($B$4 * SQRT($B$7) * B13)) -> 23094.333
A14: =A13+1 -> 4 | B14: =_xlfn.NORM.S.INV(RAND()) -> 0.18127595 | C14: =C13 * EXP((($B$3 - 0.5 * $B$4^2) * $B$7) + ($B$4 * SQRT($B$7) * B14)) -> 23151.147
A15: =A14+1 -> 5 | B15: =_xlfn.NORM.S.INV(RAND()) -> 0.32107224 | C15: =C14 * EXP((($B$3 - 0.5 * $B$4^2) * $B$7) + ($B$4 * SQRT($B$7) * B15)) -> 23247.763
A16: =A15+1 -> 6 | B16: =_xlfn.NORM.S.INV(RAND()) -> -1.1493093 | C16: =C15 * EXP((($B$3 - 0.5 * $B$4^2) * $B$7) + ($B$4 * SQRT($B$7) * B16)) -> 22929.252
A17: =A16+1 -> 7 | B17: =_xlfn.NORM.S.INV(RAND()) -> 0.19794035 | C17: =C16 * EXP((($B$3 - 0.5 * $B$4^2) * $B$7) + ($B$4 * SQRT($B$7) * B17)) -> 22990.339
A18: =A17+1 -> 8 | B18: =_xlfn.NORM.S.INV(RAND()) -> -0.22758303 | C18: =C17 * EXP((($B$3 - 0.5 * $B$4^2) * $B$7) + ($B$4 * SQRT($B$7) * B18)) -> 22932.088
A19: =A18+1 -> 9 | B19: =_xlfn.NORM.S.INV(RAND()) -> -0.14305628 | C19: =C18 * EXP((($B$3 - 0.5 * $B$4^2) * $B$7) + ($B$4 * SQRT($B$7) * B19)) -> 22897.612
A20: =A19+1 -> 10 | B20: =_xlfn.NORM.S.INV(RAND()) -> 1.4851243 | C20: =C19 * EXP((($B$3 - 0.5 * $B$4^2) * $B$7) + ($B$4 * SQRT($B$7) * B20)) -> 23322.432
A21: =A20+1 -> 11 | B21: =_xlfn.NORM.S.INV(RAND()) -> -0.59524732 | C21: =C20 * EXP((($B$3 - 0.5 * $B$4^2) * $B$7) + ($B$4 * SQRT($B$7) * B21)) -> 23159.1
A22: =A21+1 -> 12 | B22: =_xlfn.NORM.S.INV(RAND()) -> -1.0507203 | C22: =C21 * EXP((($B$3 - 0.5 * $B$4^2) * $B$7) + ($B$4 * SQRT($B$7) * B22)) -> 22869.327
... A262: =A261+1 -> 252 | B262: =_xlfn.NORM.S.INV(RAND()) -> -1.4154789 | C262: =C261 * EXP((($B$3 - 0.5 * $B$4^2) * $B$7) + ($B$4 * SQRT($B$7) * B262)) -> 22224.614

Sheet Black-Scholes
A2: Current Price (S) | B2: 22828 | D2: Metric | E2: Call | F2: Put
A3: Strike Price (K) | B3: 22900 | D3: Delta | E3: =_xlfn.NORM.S.DIST(B8, TRUE) -> 0.48743359 | F3: =_xlfn.NORM.S.DIST(B8, TRUE) - 1 -> -0.51256641
A4: Time to Maturity (T) | B4: 0.02466 | D4: Gamma | E4: =_xlfn.NORM.S.DIST(B8,FALSE)/(B2*B5*SQRT(B4)) -> 0.00057365704 | F4: =_xlfn.NORM.S.DIST(B8,FALSE)/(B2*B5*SQRT(B4)) -> 0.00057365704
A5: Volatility (Sigma) | B5: 0.1939 | D5: Theta | E5: =-(B2 * _xlfn.NORM.S.DIST(B8,FALSE) * B5) / (2 * SQRT(B4)) - B6 * B3 * EXP(-B6 * B4) * _xlfn.NORM.S.DIST(B9,TRUE) -> -6380.2987 | F5: =-(B2 * _xlfn.NORM.S.DIST(B8,FALSE) * B5) / (2 * SQRT(B4)) + B6 * B3 * EXP(-B6 * B4) * _xlfn.NORM.S.DIST(-B9,TRUE) -> -4780.0635
A6: Risk-free Rate (r) | B6: 0.07 | D6: Vega | E6: =B2 * _xlfn.NORM.S.DIST(B8,FALSE) * SQRT(B4) -> 1429.417 | F6: =B2 * _xlfn.NORM.S.DIST(B8,FALSE) * SQRT(B4) -> 1429.417
D7: Rho | E7: =B3 * B4 * EXP(-B6 * B4) * _xlfn.NORM.S.DIST(B9,TRUE) -> 267.94557 | F7: =-B3 * B4 * EXP(-B6 * B4) * _xlfn.NORM.S.DIST(-B9,TRUE) -> -295.79446
A8: d1 | B8: =(LN(B2/B3)+(B6+0.5*B5^2)*B4)/(B5*SQRT(B4)) -> -0.031504529
A9: d2 | B9: =B8 - B5*SQRT(B4) -> -0.06195362
A10: Call Price (C) | B10: =B2*_xlfn.NORM.S.DIST(B8,TRUE) - B3*EXP(-B6*B4)*_xlfn.NORM.S.DIST(B9,TRUE) -> 261.53906
A11: Put Price (P) | B11: =B3*EXP(-B6*B4)*_xlfn.NORM.S.DIST(-B9,TRUE) - B2*_xlfn.NORM.S.DIST(-B8,TRUE) -> 294.04318

Sheet Normal Distribution
D1: PRICE RANGE | E1: PDF VALUES
A2: Spot Price (S) | B2: 22828 | D2: =B2*EXP(-4*B5) -> 20210.282 | E2: =_xlfn.NORM.DIST(LN(D2/$B$2), 0, $B$5, FALSE)/D2 -> 2.1747407e-07
A3: Volatility (Sigma) | B3: 0.1939 | D3: =$D2*EXP(0.2*$B$5) -> 20333.734 | E3: =_xlfn.NORM.DIST(LN(D3/$B$2), 0, $B$5, FALSE)/D3 -> 4.7153335e-07
A4: Time to expiry (T) in years | B4: 0.02466 | D4: =$D3*EXP(0.2*$B$5) -> 20457.941 | E4: =_xlfn.NORM.DIST(LN(D4/$B$2), 0, $B$5, FALSE)/D4 -> 9.8230319e-07
A5: Std Dev of Log Returns | B5: =B3 * SQRT(B4) -> 0.030449092 | D5: =$D4*EXP(0.2*$B$5) -> 20582.906 | E5: =_xlfn.NORM.DIST(LN(D5/$B$2), 0, $B$5, FALSE)/D5 -> 1.966106e-06
D6: =$D5*EXP(0.2*$B$5) -> 20708.635 | E6: =_xlfn.NORM.DIST(LN(D6/$B$2), 0, $B$5, FALSE)/D6 -> 3.7809114e-06
A7: EXPECTED PRICE RANGE AT EXPIRY | D7: =$D6*EXP(0.2*$B$5) -> 20835.132 | E7: =_xlfn.NORM.DIST(LN(D7/$B$2), 0, $B$5, FALSE)/D7 -> 6.9857704e-06
A8: 1σ Upper | B8: =B2*EXP(B5) -> 23533.783 | D8: =$D7*EXP(0.2*$B$5) -> 20962.401 | E8: =_xlfn.NORM.DIST(LN(D8/$B$2), 0, $B$5, FALSE)/D8 -> 1.2401103e-05
A9: 1σ Lower | B9: =B2*EXP(-B5) -> 22143.384 | D9: =$D8*EXP(0.2*$B$5) -> 21090.448 | E9: =_xlfn.NORM.DIST(LN(D9/$B$2), 0, $B$5, FALSE)/D9 -> 2.1151179e-05
A10: 2σ Upper | B10: =B2*EXP(2*B5) -> 24261.386 | D10: =$D9*EXP(0.2*$B$5) -> 21219.276 | E10: =_xlfn.NORM.DIST(LN(D10/$B$2), 0, $B$5, FALSE)/D10 -> 3.4660677e-05
A11: 2σ Lower | B11: =B2*EXP(-2*B5) -> 21479.3 | D11: =$D10*EXP(0.2*$B$5) -> 21348.892 | E11: =_xlfn.NORM.DIST(LN(D11/$B$2), 0, $B$5, FALSE)/D11 -> 5.4571731e-05
A12: 3σ Upper | B12: =B2*EXP(3*B5) -> 25011.485 | D12: =$D11*EXP(0.2*$B$5) -> 21479.3 | E12: =_xlfn.NORM.DIST(LN(D12/$B$2), 0, $B$5, FALSE)/D12 -> 8.2551817e-05
A13: 3σ Lower | B13: =B2*EXP(-3*B5) -> 20835.132 | D13: =$D12*EXP(0.2*$B$5) -> 21610.504 | E13: =_xlfn.NORM.DIST(LN(D13/$B$2), 0, $B$5, FALSE)/D13 -> 0.00011998136
D14: =$D13*EXP(0.2*$B$5) -> 21742.509 | E14: =_xlfn.NORM.DIST(LN(D14/$B$2), 0, $B$5, FALSE)/D14 -> 0.00016754409
D15: =$D14*EXP(0.2*$B$5) -> 21875.321 | E15: =_xlfn.NORM.DIST(LN(D15/$B$2), 0, $B$5, FALSE)/D15 -> 0.00022478777
D16: =$D15*EXP(0.2*$B$5) -> 22008.945 | E16: =_xlfn.NORM.DIST(LN(D16/$B$2), 0, $B$5, FALSE)/D16 -> 0.00028976403
D17: =$D16*EXP(0.2*$B$5) -> 22143.384 | E17: =_xlfn.NORM.DIST(LN(D17/$B$2), 0, $B$5, FALSE)/D17 -> 0.00035887606
D18: =$D17*EXP(0.2*$B$5) -> 22278.645 | E18: =_xlfn.NORM.DIST(LN(D18/$B$2), 0, $B$5, FALSE)/D18 -> 0.00042704409
D19: =$D18*EXP(0.2*$B$5) -> 22414.731 | E19: =_xlfn.NORM.DIST(LN(D19/$B$2), 0, $B$5, FALSE)/D19 -> 0.0004882353
D20: =$D19*EXP(0.2*$B$5) -> 22551.65 | E20: =_xlfn.NORM.DIST(LN(D20/$B$2), 0, $B$5, FALSE)/D20 -> 0.00053630747 | O20: `
D21: =$D20*EXP(0.2*$B$5) -> 22689.404 | E21: =_xlfn.NORM.DIST(LN(D21/$B$2), 0, $B$5, FALSE)/D21 -> 0.00056601344
D22: =$D21*EXP(0.2*$B$5) -> 22828 | E22: =_xlfn.NORM.DIST(LN(D22/$B$2), 0, $B$5, FALSE)/D22 -> 0.0005739418
D23: =$D22*EXP(0.2*$B$5) -> 22967.443 | E23: =_xlfn.NORM.DIST(LN(D23/$B$2), 0, $B$5, FALSE)/D23 -> 0.00055916141
D24: =$D23*EXP(0.2*$B$5) -> 23107.737 | E24: =_xlfn.NORM.DIST(LN(D24/$B$2), 0, $B$5, FALSE)/D24 -> 0.00052340124
D25: =$D24*EXP(0.2*$B$5) -> 23248.888 | E25: =_xlfn.NORM.DIST(LN(D25/$B$2), 0, $B$5, FALSE)/D25 -> 0.0004707177
D26: =$D25*EXP(0.2*$B$5) -> 23390.902 | E26: =_xlfn.NORM.DIST(LN(D26/$B$2), 0, $B$5, FALSE)/D26 -> 0.00040673779
D27: =$D26*EXP(0.2*$B$5) -> 23533.783 | E27: =_xlfn.NORM.DIST(LN(D27/$B$2), 0, $B$5, FALSE)/D27 -> 0.00033767332
D28: =$D27*EXP(0.2*$B$5) -> 23677.536 | E28: =_xlfn.NORM.DIST(LN(D28/$B$2), 0, $B$5, FALSE)/D28 -> 0.00026934392
D29: =$D28*EXP(0.2*$B$5) -> 23822.168 | E29: =_xlfn.NORM.DIST(LN(D29/$B$2), 0, $B$5, FALSE)/D29 -> 0.00020641718
D30: =$D29*EXP(0.2*$B$5) -> 23967.683 | E30: =_xlfn.NORM.DIST(LN(D30/$B$2), 0, $B$5, FALSE)/D30 -> 0.0001519892
D31: =$D30*EXP(0.2*$B$5) -> 24114.088 | E31: =_xlfn.NORM.DIST(LN(D31/$B$2), 0, $B$5, FALSE)/D31 -> 0.0001075246
D32: =$D31*EXP(0.2*$B$5) -> 24261.386 | E32: =_xlfn.NORM.DIST(LN(D32/$B$2), 0, $B$5, FALSE)/D32 -> 7.3085487e-05
... D64: =$D63*EXP(0.2*$B$5) -> 29481.42 | E64: =_xlfn.NORM.DIST(LN(D64/$B$2), 0, $B$5, FALSE)/D64 -> 2.1177662e-19

Sheet Monte Carlo Simulation
A1: Spot Price (S) | B1: 22828
A2: Strike Price (K) | B2: 22900
A3: Risk-Free Rate (r) | B3: 0.07
A4: Volatility (Sigma) | B4: 0.1939
A5: Time to Expiry (T) | B5: 0.02466
A6: No. of Simulations | B6: 5000
A8: CONSTANTS
A9: Drift Component (μ - ½σ²) | B9: =B3 - 0.5*B4^2 -> 0.051201395
A10: Diffusion Component (σ√T) | B10: =B4*SQRT(B5) -> 0.030449092
A11: MONTE CARLO TABLE
A12: Sim # | B12: Random Normal Z | C12: Simulated Price | D12: Payoff (Call) | E12: Potential Loss
A13: 1 | B13: =_xlfn.NORM.S.INV(RAND()) -> 0.82760344 | C13: =B$1*EXP(B$9*B$5 + $B$10*B13) -> 23440.147 | D13: =MAX(C13 - B$2, 0) -> 540.14738 | E13: =$D$5014-D13 -> -281.51326
A14: =A13+1 -> 2 | B14: =_xlfn.NORM.S.INV(RAND()) -> -0.24330682 | C14: =B$1*EXP(B$9*B$5 + $B$10*B14) -> 22688.133 | D14: =MAX(C14 - B$2, 0) -> 0 | E14: =$D$5014-D14 -> 258.63412
A15: =A14+1 -> 3 | B15: =_xlfn.NORM.S.INV(RAND()) -> -1.4514064 | C15: =B$1*EXP(B$9*B$5 + $B$10*B15) -> 21868.702 | D15: =MAX(C15 - B$2, 0) -> 0 | E15: =$D$5014-D15 -> 258.63412
A16: =A15+1 -> 4 | B16: =_xlfn.NORM.S.INV(RAND()) -> 0.31702989 | C16: =B$1*EXP(B$9*B$5 + $B$10*B16) -> 23078.553 | D16: =MAX(C16 - B$2, 0) -> 178.55315 | E16: =$D$5014-D16 -> 80.080969
A17: =A16+1 -> 5 | B17: =_xlfn.NORM.S.INV(RAND()) -> -1.7419604 | C17: =B$1*EXP(B$9*B$5 + $B$10*B17) -> 21676.08 | D17: =MAX(C17 - B$2, 0) -> 0 | E17: =$D$5014-D17 -> 258.63412
A18: =A17+1 -> 6 | B18: =_xlfn.NORM.S.INV(RAND()) -> -0.95760827 | C18: =B$1*EXP(B$9*B$5 + $B$10*B18) -> 22199.998 | D18: =MAX(C18 - B$2, 0) -> 0 | E18: =$D$5014-D18 -> 258.63412
A19: =A18+1 -> 7 | B19: =_xlfn.NORM.S.INV(RAND()) -> -0.77523441 | C19: =B$1*EXP(B$9*B$5 + $B$10*B19) -> 22323.62 | D19: =MAX(C19 - B$2, 0) -> 0 | E19: =$D$5014-D19 -> 258.63412
A20: =A19+1 -> 8 | B20: =_xlfn.NORM.S.INV(RAND()) -> -0.55647012 | C20: =B$1*EXP(B$9*B$5 + $B$10*B20) -> 22472.818 | D20: =MAX(C20 - B$2, 0) -> 0 | E20: =$D$5014-D20 -> 258.63412
A21: =A20+1 -> 9 | B21: =_xlfn.NORM.S.INV(RAND()) -> -0.75141548 | C21: =B$1*EXP(B$9*B$5 + $B$10*B21) -> 22339.816 | D21: =MAX(C21 - B$2, 0) -> 0 | E21: =$D$5014-D21 -> 258.63412
A22: =A21+1 -> 10 | B22: =_xlfn.NORM.S.INV(RAND()) -> 0.9814684 | C22: =B$1*EXP(B$9*B$5 + $B$10*B22) -> 23550.223 | D22: =MAX(C22 - B$2, 0) -> 650.22326 | E22: =$D$5014-D22 -> -391.58913
A23: =A22+1 -> 11 | B23: =_xlfn.NORM.S.INV(RAND()) -> -1.1761373 | C23: =B$1*EXP(B$9*B$5 + $B$10*B23) -> 22052.769 | D23: =MAX(C23 - B$2, 0) -> 0 | E23: =$D$5014-D23 -> 258.63412
A24: =A23+1 -> 12 | B24: =_xlfn.NORM.S.INV(RAND()) -> -0.85280044 | C24: =B$1*EXP(B$9*B$5 + $B$10*B24) -> 22270.958 | D24: =MAX(C24 - B$2, 0) -> 0 | E24: =$D$5014-D24 -> 258.63412
A25: =A24+1 -> 13 | B25: =_xlfn.NORM.S.INV(RAND()) -> 2.9876952 | C25: =B$1*EXP(B$9*B$5 + $B$10*B25) -> 25033.704 | D25: =MAX(C25 - B$2, 0) -> 2133.7042 | E25: =$D$5014-D25 -> -1875.07
... A5012: =A5011+1 -> 5000 | B5012: =_xlfn.NORM.S.INV(RAND()) -> -0.30543323 | C5012: =B$1*EXP(B$9*B$5 + $B$10*B5012) -> 22645.254 | D5012: =MAX(C5012 - B$2, 0) -> 0 | E5012: =$D$5014-D5012 -> 258.63412
C5014: Average Payoff | D5014: =AVERAGE(D13:D5012) -> 258.63412
C5015: Present value of avg payoff (Monte Caro Estimated Option Price) | D5015: =D5014*EXP(-B3*B5) -> 258.18805
A5018: Probability of Expiring ITM | B5018: =COUNTIF(D13:D5012,">0")/5000 -> 0.4566
A5019: Probability of Profit | B5019: =COUNTIF(D13:D5012, ">" & D5014) / 5000 -> 0.3254
A5020: Probability of Loss | B5020: =COUNTIF(D13:D5012, "<" & D5014) / 5000 -> 0.6746
A5021: Probability of Option Expiring Worthless (Payoff = 0) | B5021: =COUNTIF(D13:D5012, "=0") / 5000 -> 0.5434
A5023: RISK EVALUATION
A5024: Std Dev of Payoffs (Risk spread) | B5024: =_xlfn.STDEV.P(D13:D5012) -> 405.73073
A5025: Worst Case Payoff (Minimum) | B5025: =MIN(D13:D5012) -> 0
A5026: Best Case Payoff (Maximum) | B5026: =MAX(D13:D5012) -> 3245.6771
A5027: Value at Risk (VaR @ 5%) | B5027: =_xlfn.PERCENTILE.INC(E13:E5012, 0.05) -> -891.84846

Sheet NIFTY 50_HistoricalData
A1: Date | B1: Close | C1: Open | D1: Daily % Change | E1: Jump > 2%? | F1: Total Days | G1: =COUNTA(D3:D1245) -> 1243
A2: 45764 | B2: 23851.65 | C2: 23401.85 | D2: =(C2-B3)/B3 -> -0.001508286 | F2: Jump Days | G2: =SUM(G6:G7) -> 16
A3: 45763 | B3: 23437.2 | C3: 23344.1 | D3: =(C3-B4)/B4 -> 0.00066656522 | E3: =IF(ABS(D3)>2%,1,0) -> 0 | F3: % Days with change of 2% | G3: =G2/G1 -> 0.012872084
A4: 45762 | B4: 23328.55 | C4: 23368.35 | D4: =(C4-B5)/B5 -> 0.023645829 | E4: =IF(ABS(D4)>2%,1,0) -> 1
A5: 45758 | B5: 22828.55 | C5: 22695.4 | D5: =(C5-B6)/B6 -> 0.013225948 | E5: =IF(ABS(D5)>2%,1,0) -> 0
A6: 45756 | B6: 22399.15 | C6: 22460.3 | D6: =(C6-B7)/B7 -> -0.0033524362 | E6: =IF(ABS(D6)>2%,1,0) -> 0 | F6: No. of days with 2% Jump | G6: =COUNTIF(D:D, ">0.02") -> 6 | H6: % Days with positive 2% jump | I6: =G6/G1 -> 0.0048270314
A7: 45755 | B7: 22535.85 | C7: 22446.75 | D7: =(C7-B8)/B8 -> 0.012866851 | E7: =IF(ABS(D7)>2%,1,0) -> 0 | F7: No. of days with 2% Fall | G7: =COUNTIF(D:D, "<-0.02") -> 10 | H7: % Days with negative 2% jump | I7: =G7/G1 -> 0.0080450523
A8: 45754 | B8: 22161.6 | C8: 21758.4 | D8: =(C8-B9)/B9 -> -0.050036128 | E8: =IF(ABS(D8)>2%,1,0) -> 1 | F8: Normal Days (Less than 2% Movement) | G8: =G1-G2 -> 1227 | H8: % of Normal Days | I8: =G8/G1 -> 0.98712792
A9: 45751 | B9: 22904.45 | C9: 23190.4 | D9: =(C9-B10)/B10 -> -0.0025677309 | E9: =IF(ABS(D9)>2%,1,0) -> 0
A10: 45750 | B10: 23250.1 | C10: 23150.3 | D10: =(C10-B11)/B11 -> -0.0078024717 | E10: =IF(ABS(D10)>2%,1,0) -> 0
A11: 45749 | B11: 23332.35 | C11: 23192.6 | D11: =(C11-B12)/B12 -> 0.0011611995 | E11: =IF(ABS(D11)>2%,1,0) -> 0
A12: 45748 | B12: 23165.7 | C12: 23341.1 | D12: =(C12-B13)/B13 -> -0.0075788659 | E12: =IF(ABS(D12)>2%,1,0) -> 0
A13: 45744 | B13: 23519.35 | C13: 23600.4 | D13: =(C13-B14)/B14 -> 0.00035817302 | E13: =IF(ABS(D13)>2%,1,0) -> 0
A14: 45743 | B14: 23591.95 | C14: 23433.95 | D14: =(C14-B15)/B15 -> -0.0022523242 | E14: =IF(ABS(D14)>2%,1,0) -> 0
A15: 45742 | B15: 23486.85 | C15: 23700.95 | D15: =(C15-B16)/B16 -> 0.0013646744 | E15: =IF(ABS(D15)>2%,1,0) -> 0
A16: 45741 | B16: 23668.65 | C16: 23751.5 | D16: =(C16-B17)/B17 -> 0.0039372991 | E16: =IF(ABS(D16)>2%,1,0) -> 0
A17: 45740 | B17: 23658.35 | C17: 23515.4 | D17: =(C17-B18)/B18 -> 0.0070662601 | E17: =IF(ABS(D17)>2%,1,0) -> 0
A18: 45737 | B18: 23350.4 | C18: 23168.25 | D18: =(C18-B19)/B19 -> -0.00096590652 | E18: =IF(ABS(D18)>2%,1,0) -> 0
A19: 45736 | B19: 23190.65 | C19: 23036.6 | D19: =(C19-B20)/B20 -> 0.0056313189 | E19: =IF(ABS(D19)>2%,1,0) -> 0
A20: 45735 | B20: 22907.6 | C20: 22874.95 | D20: =(C20-B21)/B21 -> 0.0017802166 | E20: =IF(ABS(D20)>2%,1,0) -> 0
... A1245: 43938 | B1245: 9266.75 | C1245: 9323.45 | D1245: =(C1245-B1246)/B1246 -> #DIV/0! | E1245: =IF(ABS(D1245)>2%,1,0) -> #DIV/0!

Sheet News
A1: Date | B1: Close | C1: Open | D1: Daily % Change | E1: News
A2: 45762 | B2: 23328.55 | C2: 23368.35 | D2: 0.023645829 | E2: Trump Tariff exemptions
A3: 45446 | B3: 23263.9 | C3: 23337.9 | D3: 0.035826672 | E3: Exit Polls
A4: 44630 | B4: 16594.9 | C4: 16757.1 | D4: 0.025190651 | E4: Assembly Election results
A5: 43998 | B5: 9914 | C5: 10014.8 | D5: 0.020491762 | E5: India China tensions in Ladakh
A6: 43964 | B6: 9383.55 | C6: 9584.2 | D6: 0.042151676 | E6: Modi Stimulus boost
A7: 43951 | B7: 9859.9 | C7: 9753.5 | D7: 0.020950766 | E7: Encouraging COVID 19 treatment trial

Sheet NIFTY movement on Thursdays 
A1: Date | B1: Open | C1: High | D1: Low | E1: Close | F1: Weekday | G1: Market move on Thursday | H1: Intraday range on Thursday | I1: How Thursday opened compared to Wednesday's close | J1: Thursday Direction | K1: High Movement | L1: News
A2: 45764 | B2: 23401.85 | C2: 23872.35 | D2: 23298.55 | E2: 23851.65 | F2: =TEXT(A2, "dddd") -> Thursday | G2: =(E2 - B2)/B2 -> 0.019220703 | H2: =(C2 - D2)/B2 -> 0.024519429 | I2: =(B2-E3)/E3 -> -0.001508286 | J2: =IF(F2="Thursday", IF(G2>0,"Positive","Negative"), "") -> Positive | K2: =IF(F2="Thursday", IF(ABS(G2)>1%, "High Move", ""), "") -> High Move | L2: FII Inflows, Strengthening Rupee against USD
A3: 45763 | B3: 23344.1 | C3: 23452.2 | D3: 23273.05 | E3: 23437.2 | F3: =TEXT(A3, "dddd") -> Wednesday | G3: =(E3 - B3)/B3 -> 0.0039881597 | H3: =(C3 - D3)/B3 -> 0.007674316 | I3: =(B3-E4)/E4 -> 0.00066656522 | J3: =IF(F3="Thursday", IF(G3>0,"Positive","Negative"), "") | K3: =IF(F3="Thursday", IF(ABS(G3)>1%, "High Move", ""), "")
A4: 45762 | B4: 23368.35 | C4: 23368.35 | D4: 23207 | E4: 23328.55 | F4: =TEXT(A4, "dddd") -> Tuesday | G4: =(E4 - B4)/B4 -> -0.0017031583 | H4: =(C4 - D4)/B4 -> 0.0069046381 | I4: =(B4-E5)/E5 -> 0.023645829 | J4: =IF(F4="Thursday", IF(G4>0,"Positive","Negative"), "") | K4: =IF(F4="Thursday", IF(ABS(G4)>1%, "High Move", ""), "")
A5: 45758 | B5: 22695.4 | C5: 22923.9 | D5: 22695.4 | E5: 22828.55 | F5: =TEXT(A5, "dddd") -> Friday | G5: =(E5 - B5)/B5 -> 0.0058668276 | H5: =(C5 - D5)/B5 -> 0.01006812 | I5: =(B5-E6)/E6 -> 0.013225948 | J5: =IF(F5="Thursday", IF(G5>0,"Positive","Negative"), "") | K5: =IF(F5="Thursday", IF(ABS(G5)>1%, "High Move", ""), "")
A6: 45756 | B6: 22460.3 | C6: 22468.7 | D6: 22353.25 | E6: 22399.15 | F6: =TEXT(A6, "dddd") -> Wednesday | G6: =(E6 - B6)/B6 -> -0.0027225816 | H6: =(C6 - D6)/B6 -> 0.0051401807 | I6: =(B6-E7)/E7 -> -0.0033524362 | J6: =IF(F6="Thursday", IF(G6>0,"Positive","Negative"), "") | K6: =IF(F6="Thursday", IF(ABS(G6)>1%, "High Move", ""), "")
A7: 45755 | B7: 22446.75 | C7: 22697.2 | D7: 22270.85 | E7: 22535.85 | F7: =TEXT(A7, "dddd") -> Tuesday | G7: =(E7 - B7)/B7 -> 0.0039693942 | H7: =(C7 - D7)/B7 -> 0.018993841 | I7: =(B7-E8)/E8 -> 0.012866851 | J7: =IF(F7="Thursday", IF(G7>0,"Positive","Negative"), "") | K7: =IF(F7="Thursday", IF(ABS(G7)>1%, "High Move", ""), "")
A8: 45754 | B8: 21758.4 | C8: 22254 | D8: 21743.65 | E8: 22161.6 | F8: =TEXT(A8, "dddd") -> Monday | G8: =(E8 - B8)/B8 -> 0.018530774 | H8: =(C8 - D8)/B8 -> 0.023455309 | I8: =(B8-E9)/E9 -> -0.050036128 | J8: =IF(F8="Thursday", IF(G8>0,"Positive","Negative"), "") | K8: =IF(F8="Thursday", IF(ABS(G8)>1%, "High Move", ""), "")
A9: 45751 | B9: 23190.4 | C9: 23214.7 | D9: 22857.45 | E9: 22904.45 | F9: =TEXT(A9, "dddd") -> Friday | G9: =(E9 - B9)/B9 -> -0.012330533 | H9: =(C9 - D9)/B9 -> 0.015405081 | I9: =(B9-E10)/E10 -> -0.0025677309 | J9: =IF(F9="Thursday", IF(G9>0,"Positive","Negative"), "") | K9: =IF(F9="Thursday", IF(ABS(G9)>1%, "High Move", ""), "")
A10: 45750 | B10: 23150.3 | C10: 23306.5 | D10: 23145.8 | E10: 23250.1 | F10: =TEXT(A10, "dddd") -> Thursday | G10: =(E10 - B10)/B10 -> 0.0043109593 | H10: =(C10 - D10)/B10 -> 0.0069415947 | I10: =(B10-E11)/E11 -> -0.0078024717 | J10: =IF(F10="Thursday", IF(G10>0,"Positive","Negative"), "") -> Positive | K10: =IF(F10="Thursday", IF(ABS(G10)>1%, "High Move", ""), "")
A11: 45749 | B11: 23192.6 | C11: 23350 | D11: 23158.45 | E11: 23332.35 | F11: =TEXT(A11, "dddd") -> Wednesday | G11: =(E11 - B11)/B11 -> 0.0060256289 | H11: =(C11 - D11)/B11 -> 0.0082590999 | I11: =(B11-E12)/E12 -> 0.0011611995 | J11: =IF(F11="Thursday", IF(G11>0,"Positive","Negative"), "") | K11: =IF(F11="Thursday", IF(ABS(G11)>1%, "High Move", ""), "")
A12: 45748 | B12: 23341.1 | C12: 23565.15 | D12: 23136.4 | E12: 23165.7 | F12: =TEXT(A12, "dddd") -> Tuesday | G12: =(E12 - B12)/B12 -> -0.0075146416 | H12: =(C12 - D12)/B12 -> 0.018368886 | I12: =(B12-E13)/E13 -> -0.0075788659 | J12: =IF(F12="Thursday", IF(G12>0,"Positive","Negative"), "") | K12: =IF(F12="Thursday", IF(ABS(G12)>1%, "High Move", ""), "")
A13: 45744 | B13: 23600.4 | C13: 23649.2 | D13: 23450.2 | E13: 23519.35 | F13: =TEXT(A13, "dddd") -> Friday | G13: =(E13 - B13)/B13 -> -0.0034342638 | H13: =(C13 - D13)/B13 -> 0.0084320605 | I13: =(B13-E14)/E14 -> 0.00035817302 | J13: =IF(F13="Thursday", IF(G13>0,"Positive","Negative"), "") | K13: =IF(F13="Thursday", IF(ABS(G13)>1%, "High Move", ""), "")
A14: 45743 | B14: 23433.95 | C14: 23646.45 | D14: 23412.2 | E14: 23591.95 | F14: =TEXT(A14, "dddd") -> Thursday | G14: =(E14 - B14)/B14 -> 0.0067423546 | H14: =(C14 - D14)/B14 -> 0.0099961808 | I14: =(B14-E15)/E15 -> -0.0022523242 | J14: =IF(F14="Thursday", IF(G14>0,"Positive","Negative"), "") -> Positive | K14: =IF(F14="Thursday", IF(ABS(G14)>1%, "High Move", ""), "")
... A1245: 43938 | B1245: 9323.45 | C1245: 9324 | D1245: 9091.35 | E1245: 9266.75 | F1245: =TEXT(A1245, "dddd") -> Friday | G1245: =(E1245 - B1245)/B1245 -> -0.0060814398 | H1245: =(C1245 - D1245)/B1245 -> 0.024953209 | I1245: =(B1245-E1246)/E1246 -> #DIV/0! | J1245: =IF(F1245="Thursday", IF(G1245>0,"Positive","Negative"), "") | K1245: =IF(F1245="Thursday", IF(ABS(G1245)>1%, "High Move", ""), "")

Sheet Data Metrics
A2: Avg Return on Thursdays | B2: =AVERAGE('NIFTY movement on Thursdays '!G2:G1245) -> -0.0005136049
A3: Std Dev of Returns | B3: =_xlfn.STDEV.P('NIFTY movement on Thursdays '!G2:G1245) -> 0.0078702762
A4: Positive Thursdays Count | B4: =COUNTIF('NIFTY movement on Thursdays '!G2:G1245, ">0") -> 611
A5: Negative Thursdays Count | B5: =COUNTIF('NIFTY movement on Thursdays '!G2:G1245, "<0") -> 633
A6: Max Thursdays Return | B6: =MAX('NIFTY movement on Thursdays '!G2:G1245) -> 0.044835227
A7: Min Thursdays Return | B7: =MIN('NIFTY movement on Thursdays '!G2:G1245) -> -0.055868332

Sheet 3rd Day Trading Pattern
A1: Date | B1: Close | C1: Daily Returns | D1: Up/Down | E1: 2-Day Down Streak | F1: 3rd Day Return | G1: Was 3rd Day Up?
A2: 43938 | B2: 9266.75 | F2: =IF(E1="Yes", C1, "") | G2: =IF(E2="Yes", IF(F2>0, "Yes", "No"), "")
A3: 43941 | B3: 9261.85 | C3: =(B3-B2)/B2 -> -0.00052877222 | D3: =IF(C3>0, "Up", IF(C3<0, "Down", "Flat")) -> Down | F3: =IF(E2="Yes", C2, "") | G3: =IF(E3="Yes", IF(F3>0, "Yes", "No"), "")
A4: 43942 | B4: 8981.45 | C4: =(B4-B3)/B3 -> -0.030274729 | D4: =IF(C4>0, "Up", IF(C4<0, "Down", "Flat")) -> Down | E4: =IF(AND(D2="Down", D3="Down"), "Yes", "No") -> No | F4: =IF(E3="Yes", C3, "") | G4: =IF(E4="Yes", IF(F4>0, "Yes", "No"), "")
A5: 43943 | B5: 9187.3 | C5: =(B5-B4)/B4 -> 0.022919462 | D5: =IF(C5>0, "Up", IF(C5<0, "Down", "Flat")) -> Up | E5: =IF(AND(D3="Down", D4="Down"), "Yes", "No") -> Yes | F5: =IF(E5="Yes", C5, "") -> 0.022919462 | G5: =IF(E5="Yes", IF(F5>0, "Yes", "No"), "") -> Yes
A6: 43944 | B6: 9313.9 | C6: =(B6-B5)/B5 -> 0.013779892 | D6: =IF(C6>0, "Up", IF(C6<0, "Down", "Flat")) -> Up | E6: =IF(AND(D4="Down", D5="Down"), "Yes", "No") -> No | F6: =IF(E6="Yes", C6, "") | G6: =IF(E6="Yes", IF(F6>0, "Yes", "No"), "")
A7: 43945 | B7: 9154.4 | C7: =(B7-B6)/B6 -> -0.017124942 | D7: =IF(C7>0, "Up", IF(C7<0, "Down", "Flat")) -> Down | E7: =IF(AND(D5="Down", D6="Down"), "Yes", "No") -> No | F7: =IF(E7="Yes", C7, "") | G7: =IF(E7="Yes", IF(F7>0, "Yes", "No"), "") | M7: Count of 2-Day Down | N7: =COUNTIF(E:E, "Yes") -> 279
A8: 43948 | B8: 9282.3 | C8: =(B8-B7)/B7 -> 0.013971424 | D8: =IF(C8>0, "Up", IF(C8<0, "Down", "Flat")) -> Up | E8: =IF(AND(D6="Down", D7="Down"), "Yes", "No") -> No | F8: =IF(E8="Yes", C8, "") | G8: =IF(E8="Yes", IF(F8>0, "Yes", "No"), "") | M8: Count of 3rd Day up | N8: =COUNTIF(G:G, "Yes") -> 134
A9: 43949 | B9: 9380.9 | C9: =(B9-B8)/B8 -> 0.010622367 | D9: =IF(C9>0, "Up", IF(C9<0, "Down", "Flat")) -> Up | E9: =IF(AND(D7="Down", D8="Down"), "Yes", "No") -> No | F9: =IF(E9="Yes", C9, "") | G9: =IF(E9="Yes", IF(F9>0, "Yes", "No"), "") | M9: % of times | N9: =N8/N7 -> 0.48028674
A10: 43950 | B10: 9553.35 | C10: =(B10-B9)/B9 -> 0.018383098 | D10: =IF(C10>0, "Up", IF(C10<0, "Down", "Flat")) -> Up | E10: =IF(AND(D8="Down", D9="Down"), "Yes", "No") -> No | F10: =IF(E10="Yes", C10, "") | G10: =IF(E10="Yes", IF(F10>0, "Yes", "No"), "") | M10: Average Return on 3rd Day (When Up) | N10: =AVERAGEIFS(F:F, G:G, "Yes") -> 0.0083781095
A11: 43951 | B11: 9859.9 | C11: =(B11-B10)/B10 -> 0.03208822 | D11: =IF(C11>0, "Up", IF(C11<0, "Down", "Flat")) -> Up | E11: =IF(AND(D9="Down", D10="Down"), "Yes", "No") -> No | F11: =IF(E11="Yes", C11, "") | G11: =IF(E11="Yes", IF(F11>0, "Yes", "No"), "") | M11: Average Return on All 3rd Days (Even if Down) | N11: =AVERAGEIF(E:E, "Yes", F:F) -> -0.00031428461
A12: 43955 | B12: 9293.5 | C12: =(B12-B11)/B11 -> -0.057444802 | D12: =IF(C12>0, "Up", IF(C12<0, "Down", "Flat")) -> Down | E12: =IF(AND(D10="Down", D11="Down"), "Yes", "No") -> No | F12: =IF(E12="Yes", C12, "") | G12: =IF(E12="Yes", IF(F12>0, "Yes", "No"), "")
A13: 43956 | B13: 9205.6 | C13: =(B13-B12)/B12 -> -0.0094582235 | D13: =IF(C13>0, "Up", IF(C13<0, "Down", "Flat")) -> Down | E13: =IF(AND(D11="Down", D12="Down"), "Yes", "No") -> No | F13: =IF(E13="Yes", C13, "") | G13: =IF(E13="Yes", IF(F13>0, "Yes", "No"), "") | M13: Up | N13: =COUNTIF(G:G, "Yes") -> 134
A14: 43957 | B14: 9270.9 | C14: =(B14-B13)/B13 -> 0.0070935083 | D14: =IF(C14>0, "Up", IF(C14<0, "Down", "Flat")) -> Up | E14: =IF(AND(D12="Down", D13="Down"), "Yes", "No") -> Yes | F14: =IF(E14="Yes", C14, "") -> 0.0070935083 | G14: =IF(E14="Yes", IF(F14>0, "Yes", "No"), "") -> Yes | M14: Down | N14: =COUNTIF(G:G, "No") -> 145
A15: 43958 | B15: 9199.05 | C15: =(B15-B14)/B14 -> -0.0077500566 | D15: =IF(C15>0, "Up", IF(C15<0, "Down", "Flat")) -> Down | E15: =IF(AND(D13="Down", D14="Down"), "Yes", "No") -> No | F15: =IF(E15="Yes", C15, "") | G15: =IF(E15="Yes", IF(F15>0, "Yes", "No"), "")
A16: 43959 | B16: 9251.5 | C16: =(B16-B15)/B15 -> 0.0057016757 | D16: =IF(C16>0, "Up", IF(C16<0, "Down", "Flat")) -> Up | E16: =IF(AND(D14="Down", D15="Down"), "Yes", "No") -> No | F16: =IF(E16="Yes", C16, "") | G16: =IF(E16="Yes", IF(F16>0, "Yes", "No"), "")
A17: 43962 | B17: 9239.2 | C17: =(B17-B16)/B16 -> -0.0013295141 | D17: =IF(C17>0, "Up", IF(C17<0, "Down", "Flat")) -> Down | E17: =IF(AND(D15="Down", D16="Down"), "Yes", "No") -> No | F17: =IF(E17="Yes", C17, "") | G17: =IF(E17="Yes", IF(F17>0, "Yes", "No"), "")
A18: 43963 | B18: 9196.55 | C18: =(B18-B17)/B17 -> -0.0046162005 | D18: =IF(C18>0, "Up", IF(C18<0, "Down", "Flat")) -> Down | E18: =IF(AND(D16="Down", D17="Down"), "Yes", "No") -> No | F18: =IF(E18="Yes", C18, "") | G18: =IF(E18="Yes", IF(F18>0, "Yes", "No"), "")
A19: 43964 | B19: 9383.55 | C19: =(B19-B18)/B18 -> 0.020333712 | D19: =IF(C19>0, "Up", IF(C19<0, "Down", "Flat")) -> Up | E19: =IF(AND(D17="Down", D18="Down"), "Yes", "No") -> Yes | F19: =IF(E19="Yes", C19, "") -> 0.020333712 | G19: =IF(E19="Yes", IF(F19>0, "Yes", "No"), "") -> Yes
A20: 43965 | B20: 9142.75 | C20: =(B20-B19)/B19 -> -0.02566193 | D20: =IF(C20>0, "Up", IF(C20<0, "Down", "Flat")) -> Down | E20: =IF(AND(D18="Down", D19="Down"), "Yes", "No") -> No | F20: =IF(E20="Yes", C20, "") | G20: =IF(E20="Yes", IF(F20>0, "Yes", "No"), "")
A21: 43966 | B21: 9136.85 | C21: =(B21-B20)/B20 -> -0.00064532006 | D21: =IF(C21>0, "Up", IF(C21<0, "Down", "Flat")) -> Down | E21: =IF(AND(D19="Down", D20="Down"), "Yes", "No") -> No | F21: =IF(E21="Yes", C21, "") | G21: =IF(E21="Yes", IF(F21>0, "Yes", "No"), "")
A22: 43969 | B22: 8823.25 | C22: =(B22-B21)/B21 -> -0.034322551 | D22: =IF(C22>0, "Up", IF(C22<0, "Down", "Flat")) -> Down | E22: =IF(AND(D20="Down", D21="Down"), "Yes", "No") -> Yes | F22: =IF(E22="Yes", C22, "") -> -0.034322551 | G22: =IF(E22="Yes", IF(F22>0, "Yes", "No"), "") -> No
A23: 43970 | B23: 8879.1 | C23: =(B23-B22)/B22 -> 0.0063298671 | D23: =IF(C23>0, "Up", IF(C23<0, "Down", "Flat")) -> Up | E23: =IF(AND(D21="Down", D22="Down"), "Yes", "No") -> Yes | F23: =IF(E23="Yes", C23, "") -> 0.0063298671 | G23: =IF(E23="Yes", IF(F23>0, "Yes", "No"), "") -> Yes
A24: 43971 | B24: 9066.55 | C24: =(B24-B23)/B23 -> 0.021111374 | D24: =IF(C24>0, "Up", IF(C24<0, "Down", "Flat")) -> Up | E24: =IF(AND(D22="Down", D23="Down"), "Yes", "No") -> No | F24: =IF(E24="Yes", C24, "") | G24: =IF(E24="Yes", IF(F24>0, "Yes", "No"), "")
A25: 43972 | B25: 9106.25 | C25: =(B25-B24)/B24 -> 0.0043787328 | D25: =IF(C25>0, "Up", IF(C25<0, "Down", "Flat")) -> Up | E25: =IF(AND(D23="Down", D24="Down"), "Yes", "No") -> No | F25: =IF(E25="Yes", C25, "") | G25: =IF(E25="Yes", IF(F25>0, "Yes", "No"), "")
A26: 43973 | B26: 9039.25 | C26: =(B26-B25)/B25 -> -0.0073575841 | D26: =IF(C26>0, "Up", IF(C26<0, "Down", "Flat")) -> Down | E26: =IF(AND(D24="Down", D25="Down"), "Yes", "No") -> No | F26: =IF(E26="Yes", C26, "") | G26: =IF(E26="Yes", IF(F26>0, "Yes", "No"), "")
... A1245: 45764 | B1245: 23851.65 | C1245: =(B1245-B1244)/B1244 -> 0.017683426 | D1245: =IF(C1245>0, "Up", IF(C1245<0, "Down", "Flat")) -> Up | E1245: =IF(AND(D1243="Down", D1244="Down"), "Yes", "No") -> No | F1245: =IF(E1245="Yes", C1245, "") | G1245: =IF(E1245="Yes", IF(F1245>0, "Yes", "No"), "")

Sheet 4th day Trading Pattern
A1: Date | B1: Close | C1: Daily Returns | D1: Up/Down | E1: 3-Day Down Streak | F1: 4th Day Return | G1: Was 4th Day Up?
A2: 43938 | B2: 9266.75 | G2: =IF(E2="Yes", IF(F2>0, "Yes", "No"), "")
A3: 43941 | B3: 9261.85 | C3: =(B3-B2)/B2 -> -0.00052877222 | D3: =IF(C3>0, "Up", IF(C3<0, "Down", "Flat")) -> Down | G3: =IF(E3="Yes", IF(F3>0, "Yes", "No"), "")
A4: 43942 | B4: 8981.45 | C4: =(B4-B3)/B3 -> -0.030274729 | D4: =IF(C4>0, "Up", IF(C4<0, "Down", "Flat")) -> Down | G4: =IF(E4="Yes", IF(F4>0, "Yes", "No"), "")
A5: 43943 | B5: 9187.3 | C5: =(B5-B4)/B4 -> 0.022919462 | D5: =IF(C5>0, "Up", IF(C5<0, "Down", "Flat")) -> Up | E5: =IF(AND(D2="Down", D3="Down", D4="Down"), "Yes", "No") -> No | F5: =IF(E5="Yes", C5, "") | G5: =IF(E5="Yes", IF(F5>0, "Yes", "No"), "")
A6: 43944 | B6: 9313.9 | C6: =(B6-B5)/B5 -> 0.013779892 | D6: =IF(C6>0, "Up", IF(C6<0, "Down", "Flat")) -> Up | E6: =IF(AND(D3="Down", D4="Down", D5="Down"), "Yes", "No") -> No | F6: =IF(E6="Yes", C6, "") | G6: =IF(E6="Yes", IF(F6>0, "Yes", "No"), "") | M6: Count of 3-Day Down | N6: =COUNTIF(E:E, "Yes") -> 144
A7: 43945 | B7: 9154.4 | C7: =(B7-B6)/B6 -> -0.017124942 | D7: =IF(C7>0, "Up", IF(C7<0, "Down", "Flat")) -> Down | E7: =IF(AND(D4="Down", D5="Down", D6="Down"), "Yes", "No") -> No | F7: =IF(E7="Yes", C7, "") | G7: =IF(E7="Yes", IF(F7>0, "Yes", "No"), "") | M7: Count of 4th Day up | N7: =COUNTIF(G:G, "Yes") -> 65
A8: 43948 | B8: 9282.3 | C8: =(B8-B7)/B7 -> 0.013971424 | D8: =IF(C8>0, "Up", IF(C8<0, "Down", "Flat")) -> Up | E8: =IF(AND(D5="Down", D6="Down", D7="Down"), "Yes", "No") -> No | F8: =IF(E8="Yes", C8, "") | G8: =IF(E8="Yes", IF(F8>0, "Yes", "No"), "") | M8: % of times | N8: =N7/N6 -> 0.45138889
A9: 43949 | B9: 9380.9 | C9: =(B9-B8)/B8 -> 0.010622367 | D9: =IF(C9>0, "Up", IF(C9<0, "Down", "Flat")) -> Up | E9: =IF(AND(D6="Down", D7="Down", D8="Down"), "Yes", "No") -> No | F9: =IF(E9="Yes", C9, "") | G9: =IF(E9="Yes", IF(F9>0, "Yes", "No"), "") | M9: Average Return on 4th Day (When Up) | N9: =AVERAGEIFS(F:F, G:G, "Yes") -> 0.0080536395
A10: 43950 | B10: 9553.35 | C10: =(B10-B9)/B9 -> 0.018383098 | D10: =IF(C10>0, "Up", IF(C10<0, "Down", "Flat")) -> Up | E10: =IF(AND(D7="Down", D8="Down", D9="Down"), "Yes", "No") -> No | F10: =IF(E10="Yes", C10, "") | G10: =IF(E10="Yes", IF(F10>0, "Yes", "No"), "") | M10: Average Return on All 4th Days (Even if Down) | N10: =AVERAGEIF(E:E, "Yes", F:F) -> -0.0014694971
A11: 43951 | B11: 9859.9 | C11: =(B11-B10)/B10 -> 0.03208822 | D11: =IF(C11>0, "Up", IF(C11<0, "Down", "Flat")) -> Up | E11: =IF(AND(D8="Down", D9="Down", D10="Down"), "Yes", "No") -> No | F11: =IF(E11="Yes", C11, "") | G11: =IF(E11="Yes", IF(F11>0, "Yes", "No"), "")
A12: 43955 | B12: 9293.5 | C12: =(B12-B11)/B11 -> -0.057444802 | D12: =IF(C12>0, "Up", IF(C12<0, "Down", "Flat")) -> Down | E12: =IF(AND(D9="Down", D10="Down", D11="Down"), "Yes", "No") -> No | F12: =IF(E12="Yes", C12, "") | G12: =IF(E12="Yes", IF(F12>0, "Yes", "No"), "") | M12: Up | N12: =COUNTIF(G:G, "Yes") -> 65
A13: 43956 | B13: 9205.6 | C13: =(B13-B12)/B12 -> -0.0094582235 | D13: =IF(C13>0, "Up", IF(C13<0, "Down", "Flat")) -> Down | E13: =IF(AND(D10="Down", D11="Down", D12="Down"), "Yes", "No") -> No | F13: =IF(E13="Yes", C13, "") | G13: =IF(E13="Yes", IF(F13>0, "Yes", "No"), "") | M13: Down | N13: =COUNTIF(G:G, "No") -> 79
A14: 43957 | B14: 9270.9 | C14: =(B14-B13)/B13 -> 0.0070935083 | D14: =IF(C14>0, "Up", IF(C14<0, "Down", "Flat")) -> Up | E14: =IF(AND(D11="Down", D12="Down", D13="Down"), "Yes", "No") -> No | F14: =IF(E14="Yes", C14, "") | G14: =IF(E14="Yes", IF(F14>0, "Yes", "No"), "")
A15: 43958 | B15: 9199.05 | C15: =(B15-B14)/B14 -> -0.0077500566 | D15: =IF(C15>0, "Up", IF(C15<0, "Down", "Flat")) -> Down | E15: =IF(AND(D12="Down", D13="Down", D14="Down"), "Yes", "No") -> No | F15: =IF(E15="Yes", C15, "") | G15: =IF(E15="Yes", IF(F15>0, "Yes", "No"), "")
A16: 43959 | B16: 9251.5 | C16: =(B16-B15)/B15 -> 0.0057016757 | D16: =IF(C16>0, "Up", IF(C16<0, "Down", "Flat")) -> Up | E16: =IF(AND(D13="Down", D14="Down", D15="Down"), "Yes", "No") -> No | F16: =IF(E16="Yes", C16, "") | G16: =IF(E16="Yes", IF(F16>0, "Yes", "No"), "")
A17: 43962 | B17: 9239.2 | C17: =(B17-B16)/B16 -> -0.0013295141 | D17: =IF(C17>0, "Up", IF(C17<0, "Down", "Flat")) -> Down | E17: =IF(AND(D14="Down", D15="Down", D16="Down"), "Yes", "No") -> No | F17: =IF(E17="Yes", C17, "") | G17: =IF(E17="Yes", IF(F17>0, "Yes", "No"), "")
A18: 43963 | B18: 9196.55 | C18: =(B18-B17)/B17 -> -0.0046162005 | D18: =IF(C18>0, "Up", IF(C18<0, "Down", "Flat")) -> Down | E18: =IF(AND(D15="Down", D16="Down", D17="Down"), "Yes", "No") -> No | F18: =IF(E18="Yes", C18, "") | G18: =IF(E18="Yes", IF(F18>0, "Yes", "No"), "")
A19: 43964 | B19: 9383.55 | C19: =(B19-B18)/B18 -> 0.020333712 | D19: =IF(C19>0, "Up", IF(C19<0, "Down", "Flat")) -> Up | E19: =IF(AND(D16="Down", D17="Down", D18="Down"), "Yes", "No") -> No | F19: =IF(E19="Yes", C19, "") | G19: =IF(E19="Yes", IF(F19>0, "Yes", "No"), "")
A20: 43965 | B20: 9142.75 | C20: =(B20-B19)/B19 -> -0.02566193 | D20: =IF(C20>0, "Up", IF(C20<0, "Down", "Flat")) -> Down | E20: =IF(AND(D17="Down", D18="Down", D19="Down"), "Yes", "No") -> No | F20: =IF(E20="Yes", C20, "") | G20: =IF(E20="Yes", IF(F20>0, "Yes", "No"), "")
A21: 43966 | B21: 9136.85 | C21: =(B21-B20)/B20 -> -0.00064532006 | D21: =IF(C21>0, "Up", IF(C21<0, "Down", "Flat")) -> Down | E21: =IF(AND(D18="Down", D19="Down", D20="Down"), "Yes", "No") -> No | F21: =IF(E21="Yes", C21, "") | G21: =IF(E21="Yes", IF(F21>0, "Yes", "No"), "")
A22: 43969 | B22: 8823.25 | C22: =(B22-B21)/B21 -> -0.034322551 | D22: =IF(C22>0, "Up", IF(C22<0, "Down", "Flat")) -> Down | E22: =IF(AND(D19="Down", D20="Down", D21="Down"), "Yes", "No") -> No | F22: =IF(E22="Yes", C22, "") | G22: =IF(E22="Yes", IF(F22>0, "Yes", "No"), "")
A23: 43970 | B23: 8879.1 | C23: =(B23-B22)/B22 -> 0.0063298671 | D23: =IF(C23>0, "Up", IF(C23<0, "Down", "Flat")) -> Up | E23: =IF(AND(D20="Down", D21="Down", D22="Down"), "Yes", "No") -> Yes | F23: =IF(E23="Yes", C23, "") -> 0.0063298671 | G23: =IF(E23="Yes", IF(F23>0, "Yes", "No"), "") -> Yes
A24: 43971 | B24: 9066.55 | C24: =(B24-B23)/B23 -> 0.021111374 | D24: =IF(C24>0, "Up", IF(C24<0, "Down", "Flat")) -> Up | E24: =IF(AND(D21="Down", D22="Down", D23="Down"), "Yes", "No") -> No | F24: =IF(E24="Yes", C24, "") | G24: =IF(E24="Yes", IF(F24>0, "Yes", "No"), "")
A25: 43972 | B25: 9106.25 | C25: =(B25-B24)/B24 -> 0.0043787328 | D25: =IF(C25>0, "Up", IF(C25<0, "Down", "Flat")) -> Up | E25: =IF(AND(D22="Down", D23="Down", D24="Down"), "Yes", "No") -> No | F25: =IF(E25="Yes", C25, "") | G25: =IF(E25="Yes", IF(F25>0, "Yes", "No"), "")
... A1245: 45764 | B1245: 23851.65 | C1245: =(B1245-B1244)/B1244 -> 0.017683426 | D1245: =IF(C1245>0, "Up", IF(C1245<0, "Down", "Flat")) -> Up | E1245: =IF(AND(D1242="Down", D1243="Down", D1244="Down"), "Yes", "No") -> No | F1245: =IF(E1245="Yes", C1245, "") | G1245: =IF(E1245="Yes", IF(F1245>0, "Yes", "No"), "")

Sheet 5th Day Trading Pattern
A1: Date | B1: Close | C1: Daily Returns | D1: Up/Down | E1: 4-Day Down Streak | F1: 5th Day Return | G1: Was 5th Day Up?
A2: 43938 | B2: 9266.75 | G2: =IF(E2="4-Day Down Streak", IF(F2>0, "Yes", "No"), "")
A3: 43941 | B3: 9261.85 | C3: =(B3-B2)/B2 -> -0.00052877222 | D3: =IF(C3>0, "Up", IF(C3<0, "Down", "Flat")) -> Down | G3: =IF(E3="4-Day Down Streak", IF(F3>0, "Yes", "No"), "")
A4: 43942 | B4: 8981.45 | C4: =(B4-B3)/B3 -> -0.030274729 | D4: =IF(C4>0, "Up", IF(C4<0, "Down", "Flat")) -> Down | G4: =IF(E4="4-Day Down Streak", IF(F4>0, "Yes", "No"), "")
A5: 43943 | B5: 9187.3 | C5: =(B5-B4)/B4 -> 0.022919462 | D5: =IF(C5>0, "Up", IF(C5<0, "Down", "Flat")) -> Up | E5: =IF(AND(D2="Down", D3="Down", D4="Down", D5="Down"), "4-Day Down Streak", "") | F5: =IF(E5="4-Day Down Streak", C5, "") | G5: =IF(E5="4-Day Down Streak", IF(F5>0, "Yes", "No"), "")
A6: 43944 | B6: 9313.9 | C6: =(B6-B5)/B5 -> 0.013779892 | D6: =IF(C6>0, "Up", IF(C6<0, "Down", "Flat")) -> Up | E6: =IF(AND(D3="Down", D4="Down", D5="Down", D6="Down"), "4-Day Down Streak", "") | F6: =IF(E6="4-Day Down Streak", C6, "") | G6: =IF(E6="4-Day Down Streak", IF(F6>0, "Yes", "No"), "")
A7: 43945 | B7: 9154.4 | C7: =(B7-B6)/B6 -> -0.017124942 | D7: =IF(C7>0, "Up", IF(C7<0, "Down", "Flat")) -> Down | E7: =IF(AND(D3="Down", D4="Down", D5="Down", D6="Down"), "4-Day Down Streak", "") | F7: =IF(E7="4-Day Down Streak", C7, "") | G7: =IF(E7="4-Day Down Streak", IF(F7>0, "Yes", "No"), "") | K7: Count of 4-Day Down | L7: =COUNTIF(E:E, "4-Day Down STreak") -> 79
A8: 43948 | B8: 9282.3 | C8: =(B8-B7)/B7 -> 0.013971424 | D8: =IF(C8>0, "Up", IF(C8<0, "Down", "Flat")) -> Up | E8: =IF(AND(D4="Down", D5="Down", D6="Down", D7="Down"), "4-Day Down Streak", "") | F8: =IF(E8="4-Day Down Streak", C8, "") | G8: =IF(E8="4-Day Down Streak", IF(F8>0, "Yes", "No"), "") | K8: Count of 5th Day up | L8: =COUNTIF(G:G, "Yes") -> 34
A9: 43949 | B9: 9380.9 | C9: =(B9-B8)/B8 -> 0.010622367 | D9: =IF(C9>0, "Up", IF(C9<0, "Down", "Flat")) -> Up | E9: =IF(AND(D5="Down", D6="Down", D7="Down", D8="Down"), "4-Day Down Streak", "") | F9: =IF(E9="4-Day Down Streak", C9, "") | G9: =IF(E9="4-Day Down Streak", IF(F9>0, "Yes", "No"), "") | K9: % of times | L9: =L8/L7 -> 0.43037975
A10: 43950 | B10: 9553.35 | C10: =(B10-B9)/B9 -> 0.018383098 | D10: =IF(C10>0, "Up", IF(C10<0, "Down", "Flat")) -> Up | E10: =IF(AND(D6="Down", D7="Down", D8="Down", D9="Down"), "4-Day Down Streak", "") | F10: =IF(E10="4-Day Down Streak", C10, "") | G10: =IF(E10="4-Day Down Streak", IF(F10>0, "Yes", "No"), "") | K10: Average Return on 5th Day (When Up) | L10: =AVERAGEIFS(F:F, G:G, "Yes") -> 0.0092038209
A11: 43951 | B11: 9859.9 | C11: =(B11-B10)/B10 -> 0.03208822 | D11: =IF(C11>0, "Up", IF(C11<0, "Down", "Flat")) -> Up | E11: =IF(AND(D7="Down", D8="Down", D9="Down", D10="Down"), "4-Day Down Streak", "") | F11: =IF(E11="4-Day Down Streak", C11, "") | G11: =IF(E11="4-Day Down Streak", IF(F11>0, "Yes", "No"), "") | K11: Average Return on All 5th Days (Even if Down) | L11: =AVERAGEIF(E:E, "4-Day Down Streak", F:F) -> -0.0011771837
A12: 43955 | B12: 9293.5 | C12: =(B12-B11)/B11 -> -0.057444802 | D12: =IF(C12>0, "Up", IF(C12<0, "Down", "Flat")) -> Down | E12: =IF(AND(D8="Down", D9="Down", D10="Down", D11="Down"), "4-Day Down Streak", "") | F12: =IF(E12="4-Day Down Streak", C12, "") | G12: =IF(E12="4-Day Down Streak", IF(F12>0, "Yes", "No"), "")
A13: 43956 | B13: 9205.6 | C13: =(B13-B12)/B12 -> -0.0094582235 | D13: =IF(C13>0, "Up", IF(C13<0, "Down", "Flat")) -> Down | E13: =IF(AND(D9="Down", D10="Down", D11="Down", D12="Down"), "4-Day Down Streak", "") | F13: =IF(E13="4-Day Down Streak", C13, "") | G13: =IF(E13="4-Day Down Streak", IF(F13>0, "Yes", "No"), "") | K13: Up | L13: =COUNTIF(G:G, "Yes") -> 34
A14: 43957 | B14: 9270.9 | C14: =(B14-B13)/B13 -> 0.0070935083 | D14: =IF(C14>0, "Up", IF(C14<0, "Down", "Flat")) -> Up | E14: =IF(AND(D10="Down", D11="Down", D12="Down", D13="Down"), "4-Day Down Streak", "") | F14: =IF(E14="4-Day Down Streak", C14, "") | G14: =IF(E14="4-Day Down Streak", IF(F14>0, "Yes", "No"), "") | K14: Down | L14: =COUNTIF(G:G, "No") -> 44
A15: 43958 | B15: 9199.05 | C15: =(B15-B14)/B14 -> -0.0077500566 | D15: =IF(C15>0, "Up", IF(C15<0, "Down", "Flat")) -> Down | E15: =IF(AND(D11="Down", D12="Down", D13="Down", D14="Down"), "4-Day Down Streak", "") | F15: =IF(E15="4-Day Down Streak", C15, "") | G15: =IF(E15="4-Day Down Streak", IF(F15>0, "Yes", "No"), "")
A16: 43959 | B16: 9251.5 | C16: =(B16-B15)/B15 -> 0.0057016757 | D16: =IF(C16>0, "Up", IF(C16<0, "Down", "Flat")) -> Up | E16: =IF(AND(D12="Down", D13="Down", D14="Down", D15="Down"), "4-Day Down Streak", "") | F16: =IF(E16="4-Day Down Streak", C16, "") | G16: =IF(E16="4-Day Down Streak", IF(F16>0, "Yes", "No"), "")
A17: 43962 | B17: 9239.2 | C17: =(B17-B16)/B16 -> -0.0013295141 | D17: =IF(C17>0, "Up", IF(C17<0, "Down", "Flat")) -> Down | E17: =IF(AND(D13="Down", D14="Down", D15="Down", D16="Down"), "4-Day Down Streak", "") | F17: =IF(E17="4-Day Down Streak", C17, "") | G17: =IF(E17="4-Day Down Streak", IF(F17>0, "Yes", "No"), "")
A18: 43963 | B18: 9196.55 | C18: =(B18-B17)/B17 -> -0.0046162005 | D18: =IF(C18>0, "Up", IF(C18<0, "Down", "Flat")) -> Down | E18: =IF(AND(D14="Down", D15="Down", D16="Down", D17="Down"), "4-Day Down Streak", "") | F18: =IF(E18="4-Day Down Streak", C18, "") | G18: =IF(E18="4-Day Down Streak", IF(F18>0, "Yes", "No"), "")
A19: 43964 | B19: 9383.55 | C19: =(B19-B18)/B18 -> 0.020333712 | D19: =IF(C19>0, "Up", IF(C19<0, "Down", "Flat")) -> Up | E19: =IF(AND(D15="Down", D16="Down", D17="Down", D18="Down"), "4-Day Down Streak", "") | F19: =IF(E19="4-Day Down Streak", C19, "") | G19: =IF(E19="4-Day Down Streak", IF(F19>0, "Yes", "No"), "")
A20: 43965 | B20: 9142.75 | C20: =(B20-B19)/B19 -> -0.02566193 | D20: =IF(C20>0, "Up", IF(C20<0, "Down", "Flat")) -> Down | E20: =IF(AND(D16="Down", D17="Down", D18="Down", D19="Down"), "4-Day Down Streak", "") | F20: =IF(E20="4-Day Down Streak", C20, "") | G20: =IF(E20="4-Day Down Streak", IF(F20>0, "Yes", "No"), "")
A21: 43966 | B21: 9136.85 | C21: =(B21-B20)/B20 -> -0.00064532006 | D21: =IF(C21>0, "Up", IF(C21<0, "Down", "Flat")) -> Down | E21: =IF(AND(D17="Down", D18="Down", D19="Down", D20="Down"), "4-Day Down Streak", "") | F21: =IF(E21="4-Day Down Streak", C21, "") | G21: =IF(E21="4-Day Down Streak", IF(F21>0, "Yes", "No"), "")
A22: 43969 | B22: 8823.25 | C22: =(B22-B21)/B21 -> -0.034322551 | D22: =IF(C22>0, "Up", IF(C22<0, "Down", "Flat")) -> Down | E22: =IF(AND(D18="Down", D19="Down", D20="Down", D21="Down"), "4-Day Down Streak", "") | F22: =IF(E22="4-Day Down Streak", C22, "") | G22: =IF(E22="4-Day Down Streak", IF(F22>0, "Yes", "No"), "")
A23: 43970 | B23: 8879.1 | C23: =(B23-B22)/B22 -> 0.0063298671 | D23: =IF(C23>0, "Up", IF(C23<0, "Down", "Flat")) -> Up | E23: =IF(AND(D19="Down", D20="Down", D21="Down", D22="Down"), "4-Day Down Streak", "") | F23: =IF(E23="4-Day Down Streak", C23, "") | G23: =IF(E23="4-Day Down Streak", IF(F23>0, "Yes", "No"), "")
A24: 43971 | B24: 9066.55 | C24: =(B24-B23)/B23 -> 0.021111374 | D24: =IF(C24>0, "Up", IF(C24<0, "Down", "Flat")) -> Up | E24: =IF(AND(D20="Down", D21="Down", D22="Down", D23="Down"), "4-Day Down Streak", "") | F24: =IF(E24="4-Day Down Streak", C24, "") | G24: =IF(E24="4-Day Down Streak", IF(F24>0, "Yes", "No"), "")
A25: 43972 | B25: 9106.25 | C25: =(B25-B24)/B24 -> 0.0043787328 | D25: =IF(C25>0, "Up", IF(C25<0, "Down", "Flat")) -> Up | E25: =IF(AND(D21="Down", D22="Down", D23="Down", D24="Down"), "4-Day Down Streak", "") | F25: =IF(E25="4-Day Down Streak", C25, "") | G25: =IF(E25="4-Day Down Streak", IF(F25>0, "Yes", "No"), "")
A26: 43973 | B26: 9039.25 | C26: =(B26-B25)/B25 -> -0.0073575841 | D26: =IF(C26>0, "Up", IF(C26<0, "Down", "Flat")) -> Down | E26: =IF(AND(D22="Down", D23="Down", D24="Down", D25="Down"), "4-Day Down Streak", "") | F26: =IF(E26="4-Day Down Streak", C26, "") | G26: =IF(E26="4-Day Down Streak", IF(F26>0, "Yes", "No"), "")
... A1245: 45764 | B1245: 23851.65 | C1245: =(B1245-B1244)/B1244 -> 0.017683426 | D1245: =IF(C1245>0, "Up", IF(C1245<0, "Down", "Flat")) -> Up | E1245: =IF(AND(D1241="Down", D1242="Down", D1243="Down", D1244="Down"), "4-Day Down Streak", "") | F1245: =IF(E1245="4-Day Down Streak", C1245, "") | G1245: =IF(E1245="4-Day Down Streak", IF(F1245>0, "Yes", "No"), "")

Sheet 6th Day Trading Pattern
A1: Date | B1: Close | C1: Daily Returns | D1: Up/Down | E1: 5-Day Down Streak | F1: 6th Day Return | G1: Was 6th Day Up?
A2: 43938 | B2: 9266.75 | F2: =IF(E2="5-Day Down Streak", C2, "") | G2: =IF(E2="5-Day Down Streak", IF(F2>0, "Yes", "No"), "")
A3: 43941 | B3: 9261.85 | C3: =(B3-B2)/B2 -> -0.00052877222 | D3: =IF(C3>0, "Up", IF(C3<0, "Down", "Flat")) -> Down | F3: =IF(E3="5-Day Down Streak", C3, "") | G3: =IF(E3="5-Day Down Streak", IF(F3>0, "Yes", "No"), "")
A4: 43942 | B4: 8981.45 | C4: =(B4-B3)/B3 -> -0.030274729 | D4: =IF(C4>0, "Up", IF(C4<0, "Down", "Flat")) -> Down | F4: =IF(E4="5-Day Down Streak", C4, "") | G4: =IF(E4="5-Day Down Streak", IF(F4>0, "Yes", "No"), "")
A5: 43943 | B5: 9187.3 | C5: =(B5-B4)/B4 -> 0.022919462 | D5: =IF(C5>0, "Up", IF(C5<0, "Down", "Flat")) -> Up | F5: =IF(E5="5-Day Down Streak", C5, "") | G5: =IF(E5="5-Day Down Streak", IF(F5>0, "Yes", "No"), "")
A6: 43944 | B6: 9313.9 | C6: =(B6-B5)/B5 -> 0.013779892 | D6: =IF(C6>0, "Up", IF(C6<0, "Down", "Flat")) -> Up | F6: =IF(E6="5-Day Down Streak", C6, "") | G6: =IF(E6="5-Day Down Streak", IF(F6>0, "Yes", "No"), "")
A7: 43945 | B7: 9154.4 | C7: =(B7-B6)/B6 -> -0.017124942 | D7: =IF(C7>0, "Up", IF(C7<0, "Down", "Flat")) -> Down | E7: =IF(AND(D2="Down", D3="Down", D4="Down", D5="Down", D6="Down"), "5-Day Down Streak", "") | F7: =IF(E7="5-Day Down Streak", C7, "") | G7: =IF(E7="5-Day Down Streak", IF(F7>0, "Yes", "No"), "") | M7: Count of 5-Day Down | N7: =COUNTIF(E:E, "5-Day Down STreak") -> 45
A8: 43948 | B8: 9282.3 | C8: =(B8-B7)/B7 -> 0.013971424 | D8: =IF(C8>0, "Up", IF(C8<0, "Down", "Flat")) -> Up | E8: =IF(AND(D3="Down", D4="Down", D5="Down", D6="Down", D7="Down"), "5-Day Down Streak", "") | F8: =IF(E8="5-Day Down Streak", C8, "") | G8: =IF(E8="5-Day Down Streak", IF(F8>0, "Yes", "No"), "") | M8: Count of 6th Day up | N8: =COUNTIF(G:G, "Yes") -> 21
A9: 43949 | B9: 9380.9 | C9: =(B9-B8)/B8 -> 0.010622367 | D9: =IF(C9>0, "Up", IF(C9<0, "Down", "Flat")) -> Up | E9: =IF(AND(D4="Down", D5="Down", D6="Down", D7="Down", D8="Down"), "5-Day Down Streak", "") | F9: =IF(E9="5-Day Down Streak", C9, "") | G9: =IF(E9="5-Day Down Streak", IF(F9>0, "Yes", "No"), "") | M9: % of times | N9: =N8/N7 -> 0.46666667
A10: 43950 | B10: 9553.35 | C10: =(B10-B9)/B9 -> 0.018383098 | D10: =IF(C10>0, "Up", IF(C10<0, "Down", "Flat")) -> Up | E10: =IF(AND(D5="Down", D6="Down", D7="Down", D8="Down", D9="Down"), "5-Day Down Streak", "") | F10: =IF(E10="5-Day Down Streak", C10, "") | G10: =IF(E10="5-Day Down Streak", IF(F10>0, "Yes", "No"), "") | M10: Average Return on 6th Day (When Up) | N10: =AVERAGEIFS(F:F, G:G, "Yes") -> 0.010905188
A11: 43951 | B11: 9859.9 | C11: =(B11-B10)/B10 -> 0.03208822 | D11: =IF(C11>0, "Up", IF(C11<0, "Down", "Flat")) -> Up | E11: =IF(AND(D6="Down", D7="Down", D8="Down", D9="Down", D10="Down"), "5-Day Down Streak", "") | F11: =IF(E11="5-Day Down Streak", C11, "") | G11: =IF(E11="5-Day Down Streak", IF(F11>0, "Yes", "No"), "") | M11: Average Return on All 6th Days (Even if Down) | N11: =AVERAGEIF(E:E, "5-Day Down Streak", F:F) -> 0.0012220179
A12: 43955 | B12: 9293.5 | C12: =(B12-B11)/B11 -> -0.057444802 | D12: =IF(C12>0, "Up", IF(C12<0, "Down", "Flat")) -> Down | E12: =IF(AND(D7="Down", D8="Down", D9="Down", D10="Down", D11="Down"), "5-Day Down Streak", "") | F12: =IF(E12="5-Day Down Streak", C12, "") | G12: =IF(E12="5-Day Down Streak", IF(F12>0, "Yes", "No"), "")
A13: 43956 | B13: 9205.6 | C13: =(B13-B12)/B12 -> -0.0094582235 | D13: =IF(C13>0, "Up", IF(C13<0, "Down", "Flat")) -> Down | E13: =IF(AND(D8="Down", D9="Down", D10="Down", D11="Down", D12="Down"), "5-Day Down Streak", "") | F13: =IF(E13="5-Day Down Streak", C13, "") | G13: =IF(E13="5-Day Down Streak", IF(F13>0, "Yes", "No"), "") | M13: Up | N13: =COUNTIF(G:G, "Yes") -> 21
A14: 43957 | B14: 9270.9 | C14: =(B14-B13)/B13 -> 0.0070935083 | D14: =IF(C14>0, "Up", IF(C14<0, "Down", "Flat")) -> Up | E14: =IF(AND(D9="Down", D10="Down", D11="Down", D12="Down", D13="Down"), "5-Day Down Streak", "") | F14: =IF(E14="5-Day Down Streak", C14, "") | G14: =IF(E14="5-Day Down Streak", IF(F14>0, "Yes", "No"), "") | M14: Down | N14: =COUNTIF(G:G, "No") -> 23
A15: 43958 | B15: 9199.05 | C15: =(B15-B14)/B14 -> -0.0077500566 | D15: =IF(C15>0, "Up", IF(C15<0, "Down", "Flat")) -> Down | E15: =IF(AND(D10="Down", D11="Down", D12="Down", D13="Down", D14="Down"), "5-Day Down Streak", "") | F15: =IF(E15="5-Day Down Streak", C15, "") | G15: =IF(E15="5-Day Down Streak", IF(F15>0, "Yes", "No"), "")
A16: 43959 | B16: 9251.5 | C16: =(B16-B15)/B15 -> 0.0057016757 | D16: =IF(C16>0, "Up", IF(C16<0, "Down", "Flat")) -> Up | E16: =IF(AND(D11="Down", D12="Down", D13="Down", D14="Down", D15="Down"), "5-Day Down Streak", "") | F16: =IF(E16="5-Day Down Streak", C16, "") | G16: =IF(E16="5-Day Down Streak", IF(F16>0, "Yes", "No"), "")
A17: 43962 | B17: 9239.2 | C17: =(B17-B16)/B16 -> -0.0013295141 | D17: =IF(C17>0, "Up", IF(C17<0, "Down", "Flat")) -> Down | E17: =IF(AND(D12="Down", D13="Down", D14="Down", D15="Down", D16="Down"), "5-Day Down Streak", "") | F17: =IF(E17="5-Day Down Streak", C17, "") | G17: =IF(E17="5-Day Down Streak", IF(F17>0, "Yes", "No"), "")
A18: 43963 | B18: 9196.55 | C18: =(B18-B17)/B17 -> -0.0046162005 | D18: =IF(C18>0, "Up", IF(C18<0, "Down", "Flat")) -> Down | E18: =IF(AND(D13="Down", D14="Down", D15="Down", D16="Down", D17="Down"), "5-Day Down Streak", "") | F18: =IF(E18="5-Day Down Streak", C18, "") | G18: =IF(E18="5-Day Down Streak", IF(F18>0, "Yes", "No"), "")
A19: 43964 | B19: 9383.55 | C19: =(B19-B18)/B18 -> 0.020333712 | D19: =IF(C19>0, "Up", IF(C19<0, "Down", "Flat")) -> Up | E19: =IF(AND(D14="Down", D15="Down", D16="Down", D17="Down", D18="Down"), "5-Day Down Streak", "") | F19: =IF(E19="5-Day Down Streak", C19, "") | G19: =IF(E19="5-Day Down Streak", IF(F19>0, "Yes", "No"), "")
A20: 43965 | B20: 9142.75 | C20: =(B20-B19)/B19 -> -0.02566193 | D20: =IF(C20>0, "Up", IF(C20<0, "Down", "Flat")) -> Down | E20: =IF(AND(D15="Down", D16="Down", D17="Down", D18="Down", D19="Down"), "5-Day Down Streak", "") | F20: =IF(E20="5-Day Down Streak", C20, "") | G20: =IF(E20="5-Day Down Streak", IF(F20>0, "Yes", "No"), "")
A21: 43966 | B21: 9136.85 | C21: =(B21-B20)/B20 -> -0.00064532006 | D21: =IF(C21>0, "Up", IF(C21<0, "Down", "Flat")) -> Down | E21: =IF(AND(D16="Down", D17="Down", D18="Down", D19="Down", D20="Down"), "5-Day Down Streak", "") | F21: =IF(E21="5-Day Down Streak", C21, "") | G21: =IF(E21="5-Day Down Streak", IF(F21>0, "Yes", "No"), "")
A22: 43969 | B22: 8823.25 | C22: =(B22-B21)/B21 -> -0.034322551 | D22: =IF(C22>0, "Up", IF(C22<0, "Down", "Flat")) -> Down | E22: =IF(AND(D17="Down", D18="Down", D19="Down", D20="Down", D21="Down"), "5-Day Down Streak", "") | F22: =IF(E22="5-Day Down Streak", C22, "") | G22: =IF(E22="5-Day Down Streak", IF(F22>0, "Yes", "No"), "")
A23: 43970 | B23: 8879.1 | C23: =(B23-B22)/B22 -> 0.0063298671 | D23: =IF(C23>0, "Up", IF(C23<0, "Down", "Flat")) -> Up | E23: =IF(AND(D18="Down", D19="Down", D20="Down", D21="Down", D22="Down"), "5-Day Down Streak", "") | F23: =IF(E23="5-Day Down Streak", C23, "") | G23: =IF(E23="5-Day Down Streak", IF(F23>0, "Yes", "No"), "")
A24: 43971 | B24: 9066.55 | C24: =(B24-B23)/B23 -> 0.021111374 | D24: =IF(C24>0, "Up", IF(C24<0, "Down", "Flat")) -> Up | E24: =IF(AND(D19="Down", D20="Down", D21="Down", D22="Down", D23="Down"), "5-Day Down Streak", "") | F24: =IF(E24="5-Day Down Streak", C24, "") | G24: =IF(E24="5-Day Down Streak", IF(F24>0, "Yes", "No"), "")
A25: 43972 | B25: 9106.25 | C25: =(B25-B24)/B24 -> 0.0043787328 | D25: =IF(C25>0, "Up", IF(C25<0, "Down", "Flat")) -> Up | E25: =IF(AND(D20="Down", D21="Down", D22="Down", D23="Down", D24="Down"), "5-Day Down Streak", "") | F25: =IF(E25="5-Day Down Streak", C25, "") | G25: =IF(E25="5-Day Down Streak", IF(F25>0, "Yes", "No"), "")
A26: 43973 | B26: 9039.25 | C26: =(B26-B25)/B25 -> -0.0073575841 | D26: =IF(C26>0, "Up", IF(C26<0, "Down", "Flat")) -> Down | E26: =IF(AND(D21="Down", D22="Down", D23="Down", D24="Down", D25="Down"), "5-Day Down Streak", "") | F26: =IF(E26="5-Day Down Streak", C26, "") | G26: =IF(E26="5-Day Down Streak", IF(F26>0, "Yes", "No"), "")
... A1245: 45764 | B1245: 23851.65 | C1245: =(B1245-B1244)/B1244 -> 0.017683426 | D1245: =IF(C1245>0, "Up", IF(C1245<0, "Down", "Flat")) -> Up | E1245: =IF(AND(D1240="Down", D1241="Down", D1242="Down", D1243="Down", D1244="Down"), "5-Day Down Streak", "") | F1245: =IF(E1245="5-Day Down Streak", C1245, "") | G1245: =IF(E1245="5-Day Down Streak", IF(F1245>0, "Yes", "No"), "")

Sheet 7th Day Trading Pattern
A1: Date | B1: Close | C1: Daily Returns | D1: Up/Down | E1: 6-Day Down Streak | F1: 7th Day Return | G1: Was 7th Day Up?
A2: 43938 | B2: 9266.75 | F2: =IF(E2="6-Day Down Streak", C2, "") | G2: =IF(E2="6-Day Down Streak", IF(F2>0, "Yes", "No"), "")
A3: 43941 | B3: 9261.85 | C3: =(B3-B2)/B2 -> -0.00052877222 | D3: =IF(C3>0, "Up", IF(C3<0, "Down", "Flat")) -> Down | F3: =IF(E3="6-Day Down Streak", C3, "") | G3: =IF(E3="6-Day Down Streak", IF(F3>0, "Yes", "No"), "")
A4: 43942 | B4: 8981.45 | C4: =(B4-B3)/B3 -> -0.030274729 | D4: =IF(C4>0, "Up", IF(C4<0, "Down", "Flat")) -> Down | F4: =IF(E4="6-Day Down Streak", C4, "") | G4: =IF(E4="6-Day Down Streak", IF(F4>0, "Yes", "No"), "")
A5: 43943 | B5: 9187.3 | C5: =(B5-B4)/B4 -> 0.022919462 | D5: =IF(C5>0, "Up", IF(C5<0, "Down", "Flat")) -> Up | F5: =IF(E5="6-Day Down Streak", C5, "") | G5: =IF(E5="6-Day Down Streak", IF(F5>0, "Yes", "No"), "")
A6: 43944 | B6: 9313.9 | C6: =(B6-B5)/B5 -> 0.013779892 | D6: =IF(C6>0, "Up", IF(C6<0, "Down", "Flat")) -> Up | F6: =IF(E6="6-Day Down Streak", C6, "") | G6: =IF(E6="6-Day Down Streak", IF(F6>0, "Yes", "No"), "")
A7: 43945 | B7: 9154.4 | C7: =(B7-B6)/B6 -> -0.017124942 | D7: =IF(C7>0, "Up", IF(C7<0, "Down", "Flat")) -> Down | F7: =IF(E7="6-Day Down Streak", C7, "") | G7: =IF(E7="6-Day Down Streak", IF(F7>0, "Yes", "No"), "")
A8: 43948 | B8: 9282.3 | C8: =(B8-B7)/B7 -> 0.013971424 | D8: =IF(C8>0, "Up", IF(C8<0, "Down", "Flat")) -> Up | F8: =IF(E8="6-Day Down Streak", C8, "") | G8: =IF(E8="6-Day Down Streak", IF(F8>0, "Yes", "No"), "") | L8: Count of 6-Day Down | M8: =COUNTIF(E:E, "6-Day Down STreak") -> 24
A9: 43949 | B9: 9380.9 | C9: =(B9-B8)/B8 -> 0.010622367 | D9: =IF(C9>0, "Up", IF(C9<0, "Down", "Flat")) -> Up | E9: =IF(AND(D3="Down", D4="Down", D5="Down", D6="Down", D7="Down", D8="Down"), "6-Day Down Streak", "") | F9: =IF(E9="6-Day Down Streak", C9, "") | G9: =IF(E9="6-Day Down Streak", IF(F9>0, "Yes", "No"), "") | L9: Count of 7th Day up | M9: =COUNTIF(G:G, "Yes") -> 12
A10: 43950 | B10: 9553.35 | C10: =(B10-B9)/B9 -> 0.018383098 | D10: =IF(C10>0, "Up", IF(C10<0, "Down", "Flat")) -> Up | E10: =IF(AND(D4="Down", D5="Down", D6="Down", D7="Down", D8="Down", D9="Down"), "6-Day Down Streak", "") | F10: =IF(E10="6-Day Down Streak", C10, "") | G10: =IF(E10="6-Day Down Streak", IF(F10>0, "Yes", "No"), "") | L10: % of times | M10: =M9/M8 -> 0.5
A11: 43951 | B11: 9859.9 | C11: =(B11-B10)/B10 -> 0.03208822 | D11: =IF(C11>0, "Up", IF(C11<0, "Down", "Flat")) -> Up | E11: =IF(AND(D5="Down", D6="Down", D7="Down", D8="Down", D9="Down", D10="Down"), "6-Day Down Streak", "") | F11: =IF(E11="6-Day Down Streak", C11, "") | G11: =IF(E11="6-Day Down Streak", IF(F11>0, "Yes", "No"), "") | L11: Average Return on 7th Day (When Up) | M11: =AVERAGEIFS(F:F, G:G, "Yes") -> 0.013518106
A12: 43955 | B12: 9293.5 | C12: =(B12-B11)/B11 -> -0.057444802 | D12: =IF(C12>0, "Up", IF(C12<0, "Down", "Flat")) -> Down | E12: =IF(AND(D6="Down", D7="Down", D8="Down", D9="Down", D10="Down", D11="Down"), "6-Day Down Streak", "") | F12: =IF(E12="6-Day Down Streak", C12, "") | G12: =IF(E12="6-Day Down Streak", IF(F12>0, "Yes", "No"), "") | L12: Average Return on All 7th Days (Even if Down) | M12: =AVERAGEIF(E:E, "6-Day Down Streak", F:F) -> 0.0032043509
A13: 43956 | B13: 9205.6 | C13: =(B13-B12)/B12 -> -0.0094582235 | D13: =IF(C13>0, "Up", IF(C13<0, "Down", "Flat")) -> Down | E13: =IF(AND(D7="Down", D8="Down", D9="Down", D10="Down", D11="Down", D12="Down"), "6-Day Down Streak", "") | F13: =IF(E13="6-Day Down Streak", C13, "") | G13: =IF(E13="6-Day Down Streak", IF(F13>0, "Yes", "No"), "")
A14: 43957 | B14: 9270.9 | C14: =(B14-B13)/B13 -> 0.0070935083 | D14: =IF(C14>0, "Up", IF(C14<0, "Down", "Flat")) -> Up | E14: =IF(AND(D8="Down", D9="Down", D10="Down", D11="Down", D12="Down", D13="Down"), "6-Day Down Streak", "") | F14: =IF(E14="6-Day Down Streak", C14, "") | G14: =IF(E14="6-Day Down Streak", IF(F14>0, "Yes", "No"), "") | L14: Up | M14: =COUNTIF(G:G, "Yes") -> 12
A15: 43958 | B15: 9199.05 | C15: =(B15-B14)/B14 -> -0.0077500566 | D15: =IF(C15>0, "Up", IF(C15<0, "Down", "Flat")) -> Down | E15: =IF(AND(D9="Down", D10="Down", D11="Down", D12="Down", D13="Down", D14="Down"), "6-Day Down Streak", "") | F15: =IF(E15="6-Day Down Streak", C15, "") | G15: =IF(E15="6-Day Down Streak", IF(F15>0, "Yes", "No"), "") | L15: Down | M15: =COUNTIF(G:G, "No") -> 11
A16: 43959 | B16: 9251.5 | C16: =(B16-B15)/B15 -> 0.0057016757 | D16: =IF(C16>0, "Up", IF(C16<0, "Down", "Flat")) -> Up | E16: =IF(AND(D10="Down", D11="Down", D12="Down", D13="Down", D14="Down", D15="Down"), "6-Day Down Streak", "") | F16: =IF(E16="6-Day Down Streak", C16, "") | G16: =IF(E16="6-Day Down Streak", IF(F16>0, "Yes", "No"), "")
A17: 43962 | B17: 9239.2 | C17: =(B17-B16)/B16 -> -0.0013295141 | D17: =IF(C17>0, "Up", IF(C17<0, "Down", "Flat")) -> Down | E17: =IF(AND(D11="Down", D12="Down", D13="Down", D14="Down", D15="Down", D16="Down"), "6-Day Down Streak", "") | F17: =IF(E17="6-Day Down Streak", C17, "") | G17: =IF(E17="6-Day Down Streak", IF(F17>0, "Yes", "No"), "")
A18: 43963 | B18: 9196.55 | C18: =(B18-B17)/B17 -> -0.0046162005 | D18: =IF(C18>0, "Up", IF(C18<0, "Down", "Flat")) -> Down | E18: =IF(AND(D12="Down", D13="Down", D14="Down", D15="Down", D16="Down", D17="Down"), "6-Day Down Streak", "") | F18: =IF(E18="6-Day Down Streak", C18, "") | G18: =IF(E18="6-Day Down Streak", IF(F18>0, "Yes", "No"), "")
A19: 43964 | B19: 9383.55 | C19: =(B19-B18)/B18 -> 0.020333712 | D19: =IF(C19>0, "Up", IF(C19<0, "Down", "Flat")) -> Up | E19: =IF(AND(D13="Down", D14="Down", D15="Down", D16="Down", D17="Down", D18="Down"), "6-Day Down Streak", "") | F19: =IF(E19="6-Day Down Streak", C19, "") | G19: =IF(E19="6-Day Down Streak", IF(F19>0, "Yes", "No"), "")
A20: 43965 | B20: 9142.75 | C20: =(B20-B19)/B19 -> -0.02566193 | D20: =IF(C20>0, "Up", IF(C20<0, "Down", "Flat")) -> Down | E20: =IF(AND(D14="Down", D15="Down", D16="Down", D17="Down", D18="Down", D19="Down"), "6-Day Down Streak", "") | F20: =IF(E20="6-Day Down Streak", C20, "") | G20: =IF(E20="6-Day Down Streak", IF(F20>0, "Yes", "No"), "")
A21: 43966 | B21: 9136.85 | C21: =(B21-B20)/B20 -> -0.00064532006 | D21: =IF(C21>0, "Up", IF(C21<0, "Down", "Flat")) -> Down | E21: =IF(AND(D15="Down", D16="Down", D17="Down", D18="Down", D19="Down", D20="Down"), "6-Day Down Streak", "") | F21: =IF(E21="6-Day Down Streak", C21, "") | G21: =IF(E21="6-Day Down Streak", IF(F21>0, "Yes", "No"), "")
A22: 43969 | B22: 8823.25 | C22: =(B22-B21)/B21 -> -0.034322551 | D22: =IF(C22>0, "Up", IF(C22<0, "Down", "Flat")) -> Down | E22: =IF(AND(D16="Down", D17="Down", D18="Down", D19="Down", D20="Down", D21="Down"), "6-Day Down Streak", "") | F22: =IF(E22="6-Day Down Streak", C22, "") | G22: =IF(E22="6-Day Down Streak", IF(F22>0, "Yes", "No"), "")
A23: 43970 | B23: 8879.1 | C23: =(B23-B22)/B22 -> 0.0063298671 | D23: =IF(C23>0, "Up", IF(C23<0, "Down", "Flat")) -> Up | E23: =IF(AND(D17="Down", D18="Down", D19="Down", D20="Down", D21="Down", D22="Down"), "6-Day Down Streak", "") | F23: =IF(E23="6-Day Down Streak", C23, "") | G23: =IF(E23="6-Day Down Streak", IF(F23>0, "Yes", "No"), "")
A24: 43971 | B24: 9066.55 | C24: =(B24-B23)/B23 -> 0.021111374 | D24: =IF(C24>0, "Up", IF(C24<0, "Down", "Flat")) -> Up | E24: =IF(AND(D18="Down", D19="Down", D20="Down", D21="Down", D22="Down", D23="Down"), "6-Day Down Streak", "") | F24: =IF(E24="6-Day Down Streak", C24, "") | G24: =IF(E24="6-Day Down Streak", IF(F24>0, "Yes", "No"), "")
A25: 43972 | B25: 9106.25 | C25: =(B25-B24)/B24 -> 0.0043787328 | D25: =IF(C25>0, "Up", IF(C25<0, "Down", "Flat")) -> Up | E25: =IF(AND(D19="Down", D20="Down", D21="Down", D22="Down", D23="Down", D24="Down"), "6-Day Down Streak", "") | F25: =IF(E25="6-Day Down Streak", C25, "") | G25: =IF(E25="6-Day Down Streak", IF(F25>0, "Yes", "No"), "")
A26: 43973 | B26: 9039.25 | C26: =(B26-B25)/B25 -> -0.0073575841 | D26: =IF(C26>0, "Up", IF(C26<0, "Down", "Flat")) -> Down | E26: =IF(AND(D20="Down", D21="Down", D22="Down", D23="Down", D24="Down", D25="Down"), "6-Day Down Streak", "") | F26: =IF(E26="6-Day Down Streak", C26, "") | G26: =IF(E26="6-Day Down Streak", IF(F26>0, "Yes", "No"), "")
A27: 43977 | B27: 9029.05 | C27: =(B27-B26)/B26 -> -0.0011284122 | D27: =IF(C27>0, "Up", IF(C27<0, "Down", "Flat")) -> Down | E27: =IF(AND(D21="Down", D22="Down", D23="Down", D24="Down", D25="Down", D26="Down"), "6-Day Down Streak", "") | F27: =IF(E27="6-Day Down Streak", C27, "") | G27: =IF(E27="6-Day Down Streak", IF(F27>0, "Yes", "No"), "")
... A1245: 45764 | B1245: 23851.65 | C1245: =(B1245-B1244)/B1244 -> 0.017683426 | D1245: =IF(C1245>0, "Up", IF(C1245<0, "Down", "Flat")) -> Up | E1245: =IF(AND(D1239="Down", D1240="Down", D1241="Down", D1242="Down", D1243="Down", D1244="Down"), "6-Day Down Streak", "") | F1245: =IF(E1245="6-Day Down Streak", C1245, "") | G1245: =IF(E1245="6-Day Down Streak", IF(F1245>0, "Yes", "No"), "")

Sheet 8th Day Trading Pattern
A1: Date | B1: Close | C1: Daily Returns | D1: Up/Down | E1: 7-Day Down Streak | F1: 8th Day Return | G1: Was 8th Day Up?
A2: 43938 | B2: 9266.75 | F2: =IF(E2="7-Day Down Streak", C2, "") | G2: =IF(E2="7-Day Down Streak", IF(F2>0, "Yes", "No"), "")
A3: 43941 | B3: 9261.85 | C3: =(B3-B2)/B2 -> -0.00052877222 | D3: =IF(C3>0, "Up", IF(C3<0, "Down", "Flat")) -> Down | F3: =IF(E3="7-Day Down Streak", C3, "") | G3: =IF(E3="7-Day Down Streak", IF(F3>0, "Yes", "No"), "")
A4: 43942 | B4: 8981.45 | C4: =(B4-B3)/B3 -> -0.030274729 | D4: =IF(C4>0, "Up", IF(C4<0, "Down", "Flat")) -> Down | F4: =IF(E4="7-Day Down Streak", C4, "") | G4: =IF(E4="7-Day Down Streak", IF(F4>0, "Yes", "No"), "")
A5: 43943 | B5: 9187.3 | C5: =(B5-B4)/B4 -> 0.022919462 | D5: =IF(C5>0, "Up", IF(C5<0, "Down", "Flat")) -> Up | F5: =IF(E5="7-Day Down Streak", C5, "") | G5: =IF(E5="7-Day Down Streak", IF(F5>0, "Yes", "No"), "")
A6: 43944 | B6: 9313.9 | C6: =(B6-B5)/B5 -> 0.013779892 | D6: =IF(C6>0, "Up", IF(C6<0, "Down", "Flat")) -> Up | F6: =IF(E6="7-Day Down Streak", C6, "") | G6: =IF(E6="7-Day Down Streak", IF(F6>0, "Yes", "No"), "")
A7: 43945 | B7: 9154.4 | C7: =(B7-B6)/B6 -> -0.017124942 | D7: =IF(C7>0, "Up", IF(C7<0, "Down", "Flat")) -> Down | F7: =IF(E7="7-Day Down Streak", C7, "") | G7: =IF(E7="7-Day Down Streak", IF(F7>0, "Yes", "No"), "")
A8: 43948 | B8: 9282.3 | C8: =(B8-B7)/B7 -> 0.013971424 | D8: =IF(C8>0, "Up", IF(C8<0, "Down", "Flat")) -> Up | F8: =IF(E8="7-Day Down Streak", C8, "") | G8: =IF(E8="7-Day Down Streak", IF(F8>0, "Yes", "No"), "") | K8: Count of 7-Day Down | L8: =COUNTIF(E:E, "7-Day Down STreak") -> 12
A9: 43949 | B9: 9380.9 | C9: =(B9-B8)/B8 -> 0.010622367 | D9: =IF(C9>0, "Up", IF(C9<0, "Down", "Flat")) -> Up | F9: =IF(E9="7-Day Down Streak", C9, "") | G9: =IF(E9="7-Day Down Streak", IF(F9>0, "Yes", "No"), "") | K9: Count of 8th Day up | L9: =COUNTIF(G:G, "Yes") -> 6
A10: 43950 | B10: 9553.35 | C10: =(B10-B9)/B9 -> 0.018383098 | D10: =IF(C10>0, "Up", IF(C10<0, "Down", "Flat")) -> Up | E10: =IF(AND(D3="Down", D4="Down", D5="Down", D6="Down", D7="Down", D8="Down", D9="Down"), "7-Day Down Streak", "") | F10: =IF(E10="7-Day Down Streak", C10, "") | G10: =IF(E10="7-Day Down Streak", IF(F10>0, "Yes", "No"), "") | K10: % of times | L10: =L9/L8 -> 0.5
A11: 43951 | B11: 9859.9 | C11: =(B11-B10)/B10 -> 0.03208822 | D11: =IF(C11>0, "Up", IF(C11<0, "Down", "Flat")) -> Up | E11: =IF(AND(D4="Down", D5="Down", D6="Down", D7="Down", D8="Down", D9="Down", D10="Down"), "7-Day Down Streak", "") | F11: =IF(E11="7-Day Down Streak", C11, "") | G11: =IF(E11="7-Day Down Streak", IF(F11>0, "Yes", "No"), "") | K11: Average Return on 8th Day (When Up) | L11: =AVERAGEIFS(F:F, G:G, "Yes") -> 0.010964875
A12: 43955 | B12: 9293.5 | C12: =(B12-B11)/B11 -> -0.057444802 | D12: =IF(C12>0, "Up", IF(C12<0, "Down", "Flat")) -> Down | E12: =IF(AND(D5="Down", D6="Down", D7="Down", D8="Down", D9="Down", D10="Down", D11="Down"), "7-Day Down Streak", "") | F12: =IF(E12="7-Day Down Streak", C12, "") | G12: =IF(E12="7-Day Down Streak", IF(F12>0, "Yes", "No"), "") | K12: Average Return on All 8th Days (Even if Down) | L12: =AVERAGEIF(E:E, "7-Day Down Streak", F:F) -> 0.0032459456
A13: 43956 | B13: 9205.6 | C13: =(B13-B12)/B12 -> -0.0094582235 | D13: =IF(C13>0, "Up", IF(C13<0, "Down", "Flat")) -> Down | E13: =IF(AND(D6="Down", D7="Down", D8="Down", D9="Down", D10="Down", D11="Down", D12="Down"), "7-Day Down Streak", "") | F13: =IF(E13="7-Day Down Streak", C13, "") | G13: =IF(E13="7-Day Down Streak", IF(F13>0, "Yes", "No"), "")
A14: 43957 | B14: 9270.9 | C14: =(B14-B13)/B13 -> 0.0070935083 | D14: =IF(C14>0, "Up", IF(C14<0, "Down", "Flat")) -> Up | E14: =IF(AND(D7="Down", D8="Down", D9="Down", D10="Down", D11="Down", D12="Down", D13="Down"), "7-Day Down Streak", "") | F14: =IF(E14="7-Day Down Streak", C14, "") | G14: =IF(E14="7-Day Down Streak", IF(F14>0, "Yes", "No"), "") | K14: Up | L14: =COUNTIF(G:G, "Yes") -> 6
A15: 43958 | B15: 9199.05 | C15: =(B15-B14)/B14 -> -0.0077500566 | D15: =IF(C15>0, "Up", IF(C15<0, "Down", "Flat")) -> Down | E15: =IF(AND(D8="Down", D9="Down", D10="Down", D11="Down", D12="Down", D13="Down", D14="Down"), "7-Day Down Streak", "") | F15: =IF(E15="7-Day Down Streak", C15, "") | G15: =IF(E15="7-Day Down Streak", IF(F15>0, "Yes", "No"), "") | K15: Down | L15: =COUNTIF(G:G, "No") -> 5
A16: 43959 | B16: 9251.5 | C16: =(B16-B15)/B15 -> 0.0057016757 | D16: =IF(C16>0, "Up", IF(C16<0, "Down", "Flat")) -> Up | E16: =IF(AND(D9="Down", D10="Down", D11="Down", D12="Down", D13="Down", D14="Down", D15="Down"), "7-Day Down Streak", "") | F16: =IF(E16="7-Day Down Streak", C16, "") | G16: =IF(E16="7-Day Down Streak", IF(F16>0, "Yes", "No"), "")
A17: 43962 | B17: 9239.2 | C17: =(B17-B16)/B16 -> -0.0013295141 | D17: =IF(C17>0, "Up", IF(C17<0, "Down", "Flat")) -> Down | E17: =IF(AND(D10="Down", D11="Down", D12="Down", D13="Down", D14="Down", D15="Down", D16="Down"), "7-Day Down Streak", "") | F17: =IF(E17="7-Day Down Streak", C17, "") | G17: =IF(E17="7-Day Down Streak", IF(F17>0, "Yes", "No"), "")
A18: 43963 | B18: 9196.55 | C18: =(B18-B17)/B17 -> -0.0046162005 | D18: =IF(C18>0, "Up", IF(C18<0, "Down", "Flat")) -> Down | E18: =IF(AND(D11="Down", D12="Down", D13="Down", D14="Down", D15="Down", D16="Down", D17="Down"), "7-Day Down Streak", "") | F18: =IF(E18="7-Day Down Streak", C18, "") | G18: =IF(E18="7-Day Down Streak", IF(F18>0, "Yes", "No"), "")
A19: 43964 | B19: 9383.55 | C19: =(B19-B18)/B18 -> 0.020333712 | D19: =IF(C19>0, "Up", IF(C19<0, "Down", "Flat")) -> Up | E19: =IF(AND(D12="Down", D13="Down", D14="Down", D15="Down", D16="Down", D17="Down", D18="Down"), "7-Day Down Streak", "") | F19: =IF(E19="7-Day Down Streak", C19, "") | G19: =IF(E19="7-Day Down Streak", IF(F19>0, "Yes", "No"), "")
A20: 43965 | B20: 9142.75 | C20: =(B20-B19)/B19 -> -0.02566193 | D20: =IF(C20>0, "Up", IF(C20<0, "Down", "Flat")) -> Down | E20: =IF(AND(D13="Down", D14="Down", D15="Down", D16="Down", D17="Down", D18="Down", D19="Down"), "7-Day Down Streak", "") | F20: =IF(E20="7-Day Down Streak", C20, "") | G20: =IF(E20="7-Day Down Streak", IF(F20>0, "Yes", "No"), "")
A21: 43966 | B21: 9136.85 | C21: =(B21-B20)/B20 -> -0.00064532006 | D21: =IF(C21>0, "Up", IF(C21<0, "Down", "Flat")) -> Down | E21: =IF(AND(D14="Down", D15="Down", D16="Down", D17="Down", D18="Down", D19="Down", D20="Down"), "7-Day Down Streak", "") | F21: =IF(E21="7-Day Down Streak", C21, "") | G21: =IF(E21="7-Day Down Streak", IF(F21>0, "Yes", "No"), "")
A22: 43969 | B22: 8823.25 | C22: =(B22-B21)/B21 -> -0.034322551 | D22: =IF(C22>0, "Up", IF(C22<0, "Down", "Flat")) -> Down | E22: =IF(AND(D15="Down", D16="Down", D17="Down", D18="Down", D19="Down", D20="Down", D21="Down"), "7-Day Down Streak", "") | F22: =IF(E22="7-Day Down Streak", C22, "") | G22: =IF(E22="7-Day Down Streak", IF(F22>0, "Yes", "No"), "")
A23: 43970 | B23: 8879.1 | C23: =(B23-B22)/B22 -> 0.0063298671 | D23: =IF(C23>0, "Up", IF(C23<0, "Down", "Flat")) -> Up | E23: =IF(AND(D16="Down", D17="Down", D18="Down", D19="Down", D20="Down", D21="Down", D22="Down"), "7-Day Down Streak", "") | F23: =IF(E23="7-Day Down Streak", C23, "") | G23: =IF(E23="7-Day Down Streak", IF(F23>0, "Yes", "No"), "")
A24: 43971 | B24: 9066.55 | C24: =(B24-B23)/B23 -> 0.021111374 | D24: =IF(C24>0, "Up", IF(C24<0, "Down", "Flat")) -> Up | E24: =IF(AND(D17="Down", D18="Down", D19="Down", D20="Down", D21="Down", D22="Down", D23="Down"), "7-Day Down Streak", "") | F24: =IF(E24="7-Day Down Streak", C24, "") | G24: =IF(E24="7-Day Down Streak", IF(F24>0, "Yes", "No"), "")
A25: 43972 | B25: 9106.25 | C25: =(B25-B24)/B24 -> 0.0043787328 | D25: =IF(C25>0, "Up", IF(C25<0, "Down", "Flat")) -> Up | E25: =IF(AND(D18="Down", D19="Down", D20="Down", D21="Down", D22="Down", D23="Down", D24="Down"), "7-Day Down Streak", "") | F25: =IF(E25="7-Day Down Streak", C25, "") | G25: =IF(E25="7-Day Down Streak", IF(F25>0, "Yes", "No"), "")
A26: 43973 | B26: 9039.25 | C26: =(B26-B25)/B25 -> -0.0073575841 | D26: =IF(C26>0, "Up", IF(C26<0, "Down", "Flat")) -> Down | E26: =IF(AND(D19="Down", D20="Down", D21="Down", D22="Down", D23="Down", D24="Down", D25="Down"), "7-Day Down Streak", "") | F26: =IF(E26="7-Day Down Streak", C26, "") | G26: =IF(E26="7-Day Down Streak", IF(F26>0, "Yes", "No"), "")
A27: 43977 | B27: 9029.05 | C27: =(B27-B26)/B26 -> -0.0011284122 | D27: =IF(C27>0, "Up", IF(C27<0, "Down", "Flat")) -> Down | E27: =IF(AND(D20="Down", D21="Down", D22="Down", D23="Down", D24="Down", D25="Down", D26="Down"), "7-Day Down Streak", "") | F27: =IF(E27="7-Day Down Streak", C27, "") | G27: =IF(E27="7-Day Down Streak", IF(F27>0, "Yes", "No"), "")
... A1245: 45764 | B1245: 23851.65 | C1245: =(B1245-B1244)/B1244 -> 0.017683426 | D1245: =IF(C1245>0, "Up", IF(C1245<0, "Down", "Flat")) -> Up | E1245: =IF(AND(D1238="Down", D1239="Down", D1240="Down", D1241="Down", D1242="Down", D1243="Down", D1244="Down"), "7-Day Down Streak", "") | F1245: =IF(E1245="7-Day Down Streak", C1245, "") | G1245: =IF(E1245="7-Day Down Streak", IF(F1245>0, "Yes", "No"), "")

Sheet 9th Day Trading Pattern
A1: Date | B1: Close | C1: Daily Returns | D1: Up/Down | E1: 8-Day Down Streak | F1: 9th Day Return | G1: Was 8th Day Up?
A2: 43938 | B2: 9266.75 | F2: =IF(E2="8-Day Down Streak", C2, "") | G2: =IF(E2="8-Day Down Streak", IF(F2>0, "Yes", "No"), "")
A3: 43941 | B3: 9261.85 | C3: =(B3-B2)/B2 -> -0.00052877222 | D3: =IF(C3>0, "Up", IF(C3<0, "Down", "Flat")) -> Down | F3: =IF(E3="8-Day Down Streak", C3, "") | G3: =IF(E3="8-Day Down Streak", IF(F3>0, "Yes", "No"), "")
A4: 43942 | B4: 8981.45 | C4: =(B4-B3)/B3 -> -0.030274729 | D4: =IF(C4>0, "Up", IF(C4<0, "Down", "Flat")) -> Down | F4: =IF(E4="8-Day Down Streak", C4, "") | G4: =IF(E4="8-Day Down Streak", IF(F4>0, "Yes", "No"), "")
A5: 43943 | B5: 9187.3 | C5: =(B5-B4)/B4 -> 0.022919462 | D5: =IF(C5>0, "Up", IF(C5<0, "Down", "Flat")) -> Up | F5: =IF(E5="8-Day Down Streak", C5, "") | G5: =IF(E5="8-Day Down Streak", IF(F5>0, "Yes", "No"), "")
A6: 43944 | B6: 9313.9 | C6: =(B6-B5)/B5 -> 0.013779892 | D6: =IF(C6>0, "Up", IF(C6<0, "Down", "Flat")) -> Up | F6: =IF(E6="8-Day Down Streak", C6, "") | G6: =IF(E6="8-Day Down Streak", IF(F6>0, "Yes", "No"), "")
A7: 43945 | B7: 9154.4 | C7: =(B7-B6)/B6 -> -0.017124942 | D7: =IF(C7>0, "Up", IF(C7<0, "Down", "Flat")) -> Down | F7: =IF(E7="8-Day Down Streak", C7, "") | G7: =IF(E7="8-Day Down Streak", IF(F7>0, "Yes", "No"), "")
A8: 43948 | B8: 9282.3 | C8: =(B8-B7)/B7 -> 0.013971424 | D8: =IF(C8>0, "Up", IF(C8<0, "Down", "Flat")) -> Up | F8: =IF(E8="8-Day Down Streak", C8, "") | G8: =IF(E8="8-Day Down Streak", IF(F8>0, "Yes", "No"), "")
A9: 43949 | B9: 9380.9 | C9: =(B9-B8)/B8 -> 0.010622367 | D9: =IF(C9>0, "Up", IF(C9<0, "Down", "Flat")) -> Up | F9: =IF(E9="8-Day Down Streak", C9, "") | G9: =IF(E9="8-Day Down Streak", IF(F9>0, "Yes", "No"), "") | L9: Count of 8-Day Down | M9: =COUNTIF(E:E, "8-Day Down STreak") -> 6
A10: 43950 | B10: 9553.35 | C10: =(B10-B9)/B9 -> 0.018383098 | D10: =IF(C10>0, "Up", IF(C10<0, "Down", "Flat")) -> Up | F10: =IF(E10="8-Day Down Streak", C10, "") | G10: =IF(E10="8-Day Down Streak", IF(F10>0, "Yes", "No"), "") | L10: Count of 8th Day up | M10: =COUNTIF(G:G, "Yes") -> 3
A11: 43951 | B11: 9859.9 | C11: =(B11-B10)/B10 -> 0.03208822 | D11: =IF(C11>0, "Up", IF(C11<0, "Down", "Flat")) -> Up | E11: =IF(AND(D3="Down", D4="Down", D5="Down", D6="Down", D7="Down", D8="Down", D9="Down", D10="Down"), "8-Day Down Streak", "") | F11: =IF(E11="8-Day Down Streak", C11, "") | G11: =IF(E11="8-Day Down Streak", IF(F11>0, "Yes", "No"), "") | L11: % of times | M11: =M10/M9 -> 0.5
A12: 43955 | B12: 9293.5 | C12: =(B12-B11)/B11 -> -0.057444802 | D12: =IF(C12>0, "Up", IF(C12<0, "Down", "Flat")) -> Down | E12: =IF(AND(D4="Down", D5="Down", D6="Down", D7="Down", D8="Down", D9="Down", D10="Down", D11="Down"), "8-Day Down Streak", "") | F12: =IF(E12="8-Day Down Streak", C12, "") | G12: =IF(E12="8-Day Down Streak", IF(F12>0, "Yes", "No"), "") | L12: Average Return on 8th Day (When Up) | M12: =AVERAGEIFS(F:F,G:G,"Yes") -> 0.0071144113
A13: 43956 | B13: 9205.6 | C13: =(B13-B12)/B12 -> -0.0094582235 | D13: =IF(C13>0, "Up", IF(C13<0, "Down", "Flat")) -> Down | E13: =IF(AND(D5="Down", D6="Down", D7="Down", D8="Down", D9="Down", D10="Down", D11="Down", D12="Down"), "8-Day Down Streak", "") | F13: =IF(E13="8-Day Down Streak", C13, "") | G13: =IF(E13="8-Day Down Streak", IF(F13>0, "Yes", "No"), "") | L13: Average Return on All 8th Days (Even if Down) | M13: =AVERAGEIF(E:E, "8-Day Down Streak", F:F) -> 0.0038884477
A14: 43957 | B14: 9270.9 | C14: =(B14-B13)/B13 -> 0.0070935083 | D14: =IF(C14>0, "Up", IF(C14<0, "Down", "Flat")) -> Up | E14: =IF(AND(D6="Down", D7="Down", D8="Down", D9="Down", D10="Down", D11="Down", D12="Down", D13="Down"), "8-Day Down Streak", "") | F14: =IF(E14="8-Day Down Streak", C14, "") | G14: =IF(E14="8-Day Down Streak", IF(F14>0, "Yes", "No"), "")
A15: 43958 | B15: 9199.05 | C15: =(B15-B14)/B14 -> -0.0077500566 | D15: =IF(C15>0, "Up", IF(C15<0, "Down", "Flat")) -> Down | E15: =IF(AND(D7="Down", D8="Down", D9="Down", D10="Down", D11="Down", D12="Down", D13="Down", D14="Down"), "8-Day Down Streak", "") | F15: =IF(E15="8-Day Down Streak", C15, "") | G15: =IF(E15="8-Day Down Streak", IF(F15>0, "Yes", "No"), "") | L15: Up | M15: =COUNTIF(G:G, "Yes") -> 3
A16: 43959 | B16: 9251.5 | C16: =(B16-B15)/B15 -> 0.0057016757 | D16: =IF(C16>0, "Up", IF(C16<0, "Down", "Flat")) -> Up | E16: =IF(AND(D8="Down", D9="Down", D10="Down", D11="Down", D12="Down", D13="Down", D14="Down", D15="Down"), "8-Day Down Streak", "") | F16: =IF(E16="8-Day Down Streak", C16, "") | G16: =IF(E16="8-Day Down Streak", IF(F16>0, "Yes", "No"), "") | L16: Down | M16: =COUNTIF(G:G, "No") -> 2
A17: 43962 | B17: 9239.2 | C17: =(B17-B16)/B16 -> -0.0013295141 | D17: =IF(C17>0, "Up", IF(C17<0, "Down", "Flat")) -> Down | E17: =IF(AND(D9="Down", D10="Down", D11="Down", D12="Down", D13="Down", D14="Down", D15="Down", D16="Down"), "8-Day Down Streak", "") | F17: =IF(E17="8-Day Down Streak", C17, "") | G17: =IF(E17="8-Day Down Streak", IF(F17>0, "Yes", "No"), "")
A18: 43963 | B18: 9196.55 | C18: =(B18-B17)/B17 -> -0.0046162005 | D18: =IF(C18>0, "Up", IF(C18<0, "Down", "Flat")) -> Down | E18: =IF(AND(D10="Down", D11="Down", D12="Down", D13="Down", D14="Down", D15="Down", D16="Down", D17="Down"), "8-Day Down Streak", "") | F18: =IF(E18="8-Day Down Streak", C18, "") | G18: =IF(E18="8-Day Down Streak", IF(F18>0, "Yes", "No"), "")
A19: 43964 | B19: 9383.55 | C19: =(B19-B18)/B18 -> 0.020333712 | D19: =IF(C19>0, "Up", IF(C19<0, "Down", "Flat")) -> Up | E19: =IF(AND(D11="Down", D12="Down", D13="Down", D14="Down", D15="Down", D16="Down", D17="Down", D18="Down"), "8-Day Down Streak", "") | F19: =IF(E19="8-Day Down Streak", C19, "") | G19: =IF(E19="8-Day Down Streak", IF(F19>0, "Yes", "No"), "")
A20: 43965 | B20: 9142.75 | C20: =(B20-B19)/B19 -> -0.02566193 | D20: =IF(C20>0, "Up", IF(C20<0, "Down", "Flat")) -> Down | E20: =IF(AND(D12="Down", D13="Down", D14="Down", D15="Down", D16="Down", D17="Down", D18="Down", D19="Down"), "8-Day Down Streak", "") | F20: =IF(E20="8-Day Down Streak", C20, "") | G20: =IF(E20="8-Day Down Streak", IF(F20>0, "Yes", "No"), "")
A21: 43966 | B21: 9136.85 | C21: =(B21-B20)/B20 -> -0.00064532006 | D21: =IF(C21>0, "Up", IF(C21<0, "Down", "Flat")) -> Down | E21: =IF(AND(D13="Down", D14="Down", D15="Down", D16="Down", D17="Down", D18="Down", D19="Down", D20="Down"), "8-Day Down Streak", "") | F21: =IF(E21="8-Day Down Streak", C21, "") | G21: =IF(E21="8-Day Down Streak", IF(F21>0, "Yes", "No"), "")
A22: 43969 | B22: 8823.25 | C22: =(B22-B21)/B21 -> -0.034322551 | D22: =IF(C22>0, "Up", IF(C22<0, "Down", "Flat")) -> Down | E22: =IF(AND(D14="Down", D15="Down", D16="Down", D17="Down", D18="Down", D19="Down", D20="Down", D21="Down"), "8-Day Down Streak", "") | F22: =IF(E22="8-Day Down Streak", C22, "") | G22: =IF(E22="8-Day Down Streak", IF(F22>0, "Yes", "No"), "")
A23: 43970 | B23: 8879.1 | C23: =(B23-B22)/B22 -> 0.0063298671 | D23: =IF(C23>0, "Up", IF(C23<0, "Down", "Flat")) -> Up | E23: =IF(AND(D15="Down", D16="Down", D17="Down", D18="Down", D19="Down", D20="Down", D21="Down", D22="Down"), "8-Day Down Streak", "") | F23: =IF(E23="8-Day Down Streak", C23, "") | G23: =IF(E23="8-Day Down Streak", IF(F23>0, "Yes", "No"), "")
A24: 43971 | B24: 9066.55 | C24: =(B24-B23)/B23 -> 0.021111374 | D24: =IF(C24>0, "Up", IF(C24<0, "Down", "Flat")) -> Up | E24: =IF(AND(D16="Down", D17="Down", D18="Down", D19="Down", D20="Down", D21="Down", D22="Down", D23="Down"), "8-Day Down Streak", "") | F24: =IF(E24="8-Day Down Streak", C24, "") | G24: =IF(E24="8-Day Down Streak", IF(F24>0, "Yes", "No"), "")
A25: 43972 | B25: 9106.25 | C25: =(B25-B24)/B24 -> 0.0043787328 | D25: =IF(C25>0, "Up", IF(C25<0, "Down", "Flat")) -> Up | E25: =IF(AND(D17="Down", D18="Down", D19="Down", D20="Down", D21="Down", D22="Down", D23="Down", D24="Down"), "8-Day Down Streak", "") | F25: =IF(E25="8-Day Down Streak", C25, "") | G25: =IF(E25="8-Day Down Streak", IF(F25>0, "Yes", "No"), "")
A26: 43973 | B26: 9039.25 | C26: =(B26-B25)/B25 -> -0.0073575841 | D26: =IF(C26>0, "Up", IF(C26<0, "Down", "Flat")) -> Down | E26: =IF(AND(D18="Down", D19="Down", D20="Down", D21="Down", D22="Down", D23="Down", D24="Down", D25="Down"), "8-Day Down Streak", "") | F26: =IF(E26="8-Day Down Streak", C26, "") | G26: =IF(E26="8-Day Down Streak", IF(F26>0, "Yes", "No"), "")
A27: 43977 | B27: 9029.05 | C27: =(B27-B26)/B26 -> -0.0011284122 | D27: =IF(C27>0, "Up", IF(C27<0, "Down", "Flat")) -> Down | E27: =IF(AND(D19="Down", D20="Down", D21="Down", D22="Down", D23="Down", D24="Down", D25="Down", D26="Down"), "8-Day Down Streak", "") | F27: =IF(E27="8-Day Down Streak", C27, "") | G27: =IF(E27="8-Day Down Streak", IF(F27>0, "Yes", "No"), "")
A28: 43978 | B28: 9314.95 | C28: =(B28-B27)/B27 -> 0.031664461 | D28: =IF(C28>0, "Up", IF(C28<0, "Down", "Flat")) -> Up | E28: =IF(AND(D20="Down", D21="Down", D22="Down", D23="Down", D24="Down", D25="Down", D26="Down", D27="Down"), "8-Day Down Streak", "") | F28: =IF(E28="8-Day Down Streak", C28, "") | G28: =IF(E28="8-Day Down Streak", IF(F28>0, "Yes", "No"), "")
... A1245: 45764 | B1245: 23851.65 | C1245: =(B1245-B1244)/B1244 -> 0.017683426 | D1245: =IF(C1245>0, "Up", IF(C1245<0, "Down", "Flat")) -> Up | E1245: =IF(AND(D1237="Down", D1238="Down", D1239="Down", D1240="Down", D1241="Down", D1242="Down", D1243="Down", D1244="Down"), "8-Day Down Streak", "") | F1245: =IF(E1245="8-Day Down Streak", C1245, "") | G1245: =IF(E1245="8-Day Down Streak", IF(F1245>0, "Yes", "No"), "")

Sheet Macroeconomic Monte Carlo
A1: NIFTY
A3: Date | B3: Close | E3: India_Inflation_Data | T3: Crude Oil | X3: INR/USD Exchange Rate
A4: 45748 | B4: 23165.7 | E4: Year | F4: Jan | G4: Feb | H4: Mar | I4: Apr | J4: May | K4: Jun | L4: Jul | M4: Aug | N4: Sep | O4: Oct | P4: Nov | Q4: Dec | T4: Date | U4: Price | X4: Date | Y4: Price
A5: 45717 | B5: 22119.3 | E5: 2015 | F5: 7.17 | G5: 6.3 | H5: 6.28 | I5: 5.79 | J5: 5.74 | K5: 6.1 | L5: 4.37 | M5: 4.35 | N5: 5.14 | O5: 6.32 | P5: 6.72 | Q5: 6.32 | T5: 45661 | U5: 58.21 | X5: 45661 | Y5: 84.599
A6: 45689 | B6: 23482.15 | E6: 2016 | F6: 5.91 | G6: 5.53 | H6: 5.51 | I6: 5.86 | J6: 6.59 | K6: 6.13 | L6: 6.46 | M6: 5.3 | N6: 4.14 | O6: 3.35 | P6: 2.59 | Q6: 2.23 | T6: 45660 | U6: 71.48 | X6: 45660 | Y6: 85.46
A7: 45658 | B7: 23742.9 | E7: 2017 | F7: 1.86 | G7: 2.62 | H7: 2.61 | I7: 2.21 | J7: 1.09 | K7: 1.08 | L7: 1.79 | M7: 2.52 | N7: 2.89 | O7: 3.24 | P7: 3.97 | Q7: 4 | T7: 45659 | U7: 69.76 | X7: 45659 | Y7: 87.471
A8: 45627 | B8: 24276.05 | E8: 2018 | F8: 5.11 | G8: 4.74 | H8: 4.36 | I8: 3.97 | J8: 3.96 | K8: 3.93 | L8: 5.61 | M8: 5.61 | N8: 5.61 | O8: 5.23 | P8: 4.86 | Q8: 5.24 | T8: 45658 | U8: 72.53 | X8: 45658 | Y8: 86.561
A9: 45597 | B9: 24304.35 | E9: 2019 | F9: 6.6 | G9: 6.97 | H9: 7.67 | I9: 8.33 | J9: 8.65 | K9: 8.59 | L9: 5.98 | M9: 6.31 | N9: 6.98 | O9: 7.62 | P9: 8.61 | Q9: 9.63 | T9: 45303 | U9: 71.72 | X9: 45303 | Y9: 85.554
A10: 45566 | B10: 25796.9 | E10: 2020 | F10: 7.49 | G10: 6.84 | H10: 5.5 | I10: 5.45 | J10: 5.1 | K10: 5.06 | L10: 5.33 | M10: 5.63 | N10: - | O10: - | P10: - | Q10: - | T10: 45302 | U10: 68 | X10: 45302 | Y10: 84.559
A11: 45536 | B11: 25278.7 | E11: 2020 Base | F11: - | G11: - | H11: - | I11: - | J11: - | K11: - | L11: - | M11: - | N11: 5.62 | O11: 5.91 | P11: 5.27 | Q11: 3.67 | T11: 45301 | U11: 69.26 | X11: 45301 | Y11: 84.061
A12: 45505 | B12: 25010.9 | E12: 2021 | F12: 3.15 | G12: 4.48 | H12: 5.64 | I12: 5.14 | J12: 5.24 | K12: 5.57 | L12: 5.27 | M12: 4.79 | N12: 4.41 | O12: 4.5 | P12: 4.84 | Q12: 5.56 | T12: 45300 | U12: 68.17 | X12: 45300 | Y12: 83.755
A13: 45474 | B13: 24141.95 | E13: 2022 | F13: 5.84 | G13: 5.04 | H13: 5.35 | I13: 6.33 | J13: 6.97 | K13: 6.16 | L13: 5.78 | M13: 5.85 | N13: 6.49 | O13: 6.08 | P13: 5.41 | Q13: 5.5 | T13: 45299 | U13: 73.55 | X13: 45299 | Y13: 83.867
A14: 45444 | B14: 23263.9 | E14: 2023 | F14: 6.16 | G14: 6.16 | H14: 5.79 | I14: 5.09 | J14: - | K14: - | L14: - | M14: - | N14: - | O14: - | P14: - | Q14: - | T14: 45298 | U14: 77.91 | X14: 45298 | Y14: 83.699
A15: 45413 | B15: 22648.2 | T15: 45297 | U15: 81.54 | X15: 45297 | Y15: 83.355
A16: 45383 | B16: 22462 | T16: 45296 | U16: 76.99 | X16: 45296 | Y16: 83.424
A17: 45352 | B17: 22338.75 | T17: 45295 | U17: 81.93 | X17: 45295 | Y17: 83.45
A18: 45323 | B18: 21697.45 | T18: 45294 | U18: 83.17 | X18: 45294 | Y18: 83.35
A19: 45292 | B19: 21741.9 | T19: 45293 | U19: 78.26 | X19: 45293 | Y19: 82.9
A20: 45261 | B20: 20267.9 | T20: 45292 | U20: 75.85 | X20: 45292 | Y20: 83.095
A21: 45231 | B21: 18989.15 | T21: 44938 | U21: 71.65 | X21: 44938 | Y21: 83.19
A22: 45200 | B22: 19528.75 | T22: 44937 | U22: 75.96 | X22: 44937 | Y22: 83.357
A23: 45170 | B23: 19435.3 | T23: 44936 | U23: 81.02 | X23: 44936 | Y23: 83.256
A24: 45139 | B24: 19733.55 | T24: 44935 | U24: 90.79 | X24: 44935 | Y24: 83.03
A25: 45108 | B25: 19322.55 | T25: 44934 | U25: 83.63 | X25: 44934 | Y25: 82.702
A26: 45078 | B26: 18487.75 | T26: 44933 | U26: 81.8 | X26: 44933 | Y26: 82.24
... A124: 42095 | B124: 8659.9 | T124: 42009 | U124: 60.3 | X124: 42009 | Y124: 63.733

Sheet Simulation
A1: Date | B1: NIFTY | C1: Crude Oil Price | D1: Inflation | E1: INR vs USD | H1: NIFTY Return | I1: Crude Oil Return | J1: Inflation change | K1: Currency change | M1: Date | N1: GDP Growth Rate | P1: Date | Q1: Repo Rate | S1: Date | T1: S&P 500 | V1: Financial Year | W1: INR crores | AC1: Date | AD1: Price | AE1: Open | AF1: High | AG1: Low | AH1: Change %
A2: 45748 | B2: 23165.7 | C2: 58.21 | E2: 84.599 | H2: =LN(B2/B3) -> 0.046222206 | I2: =LN(C2/C3) -> -0.20536053 | K2: =(E2-E3)/E3 -> -0.010074889 | M2: 45657 | N2: 0.062 | P2: 45756 | Q2: 0.06 | S2: 45784 | T2: 5631.28 | W2: Equity | X2: Debt | Y2: Debt-VRR | Z2: Hybrid | AA2: Total | AC2: 45778 | AD2: 6.426 | AE2: 6.468 | AF2: 6.469 | AG2: 6.409 | AH2: 0.012
A3: 45717 | B3: 22119.3 | C3: 71.48 | E3: 85.46 | H3: =LN(B3/B4) -> -0.059790027 | I3: =LN(C3/C4) -> 0.024356911 | K3: =(E3-E4)/E4 -> -0.022990477 | M3: 45565 | N3: 0.056 | P3: 45747 | Q3: 0.0625 | S3: 45778 | T3: 5631.28 | V3: -1 | W3: 1411.95 | X3: 4922.67 | Y3: 195.32 | Z3: 5720.23 | AA3: 12250.17 | AC3: 45748 | AD3: 6.35 | AE3: 6.48 | AF3: 6.5 | AG3: 6.32 | AH3: -0.035
A4: 45689 | B4: 23482.15 | C4: 69.76 | E4: 87.471 | H4: =LN(B4/B5) -> -0.01104298 | I4: =LN(C4/C5) -> -0.03893949 | K4: =(E4-E5)/E5 -> 0.010512818 | M4: 45473 | N4: 0.065 | P4: 45695 | Q4: 0.0625 | S4: 45748 | T4: 5569.06 | V4: 1998-1999 | W4: 29973.2 | X4: -147.4 | Y4: 0 | Z4: 0 | AA4: 29825.8 | AC4: 45717 | AD4: 6.58 | AE4: 6.73 | AF4: 6.74 | AG4: 6.58 | AH4: -0.0208
A5: 45658 | B5: 23742.9 | C5: 72.53 | E5: 86.561 | H5: =LN(B5/B6) -> -0.022206729 | I5: =LN(C5/C6) -> 0.011230621 | K5: =(E5-E6)/E6 -> 0.011770344 | M5: 45382 | N5: 0.078 | P5: 45688 | Q5: 0.065 | S5: 45717 | T5: 5611.85 | V5: 1999-2000 | W5: 9669.5 | X5: 452.6 | Y5: 0 | Z5: 0 | AA5: 10122.1 | AC5: 45689 | AD5: 6.72 | AE5: 6.67 | AF5: 6.72 | AG5: 6.65 | AH5: 0.0045
A6: 45627 | B6: 24276.05 | C6: 71.72 | E6: 85.554 | H6: =LN(B6/B7) -> -0.0011650791 | I6: =LN(C6/C7) -> 0.053261944 | K6: =(E6-E7)/E7 -> 0.011766932 | M6: 45291 | N6: 0.095 | P6: 45632 | Q6: 0.065 | S6: 45689 | T6: 5954.5 | V6: 2000-2001 | W6: 10206.7 | X6: -273.3 | Y6: 0 | Z6: 0 | AA6: 9933.4 | AC6: 45658 | AD6: 6.69 | AE6: 6.78 | AF6: 6.84 | AG6: 6.67 | AH6: -0.0104
A7: 45597 | B7: 24304.35 | C7: 68 | E7: 84.559 | H7: =LN(B7/B8) -> -0.059598983 | I7: =LN(C7/C8) -> -0.018359834 | K7: =(E7-E8)/E8 -> 0.0059242693 | M7: 45199 | N7: 0.093 | P7: 45626 | Q7: 0.065 | S7: 45658 | T7: 6040.53 | V7: 2001-2002 | W7: 8072.2 | X7: 690.4 | Y7: 0 | Z7: 0 | AA7: 8762.6 | AC7: 45627 | AD7: 6.76 | AE7: 6.802 | AF7: 6.807 | AG7: 6.668 | AH7: 0.0013
A8: 45566 | B8: 25796.9 | C8: 69.26 | E8: 84.061 | H8: =LN(B8/B9) -> 0.020292186 | I8: =LN(C8/C9) -> 0.015862954 | K8: =(E8-E9)/E9 -> 0.0036535132 | M8: 45107 | N8: 0.097 | P8: 45565 | Q8: 0.065 | S8: 45627 | T8: 5881.63 | V8: 2002-2003 | W8: 2527 | X8: 162 | Y8: 0 | Z8: 0 | AA8: 2689 | AC8: 45597 | AD8: 6.751 | AE8: 6.831 | AF8: 6.863 | AG8: 6.739 | AH8: -0.0132
A9: 45536 | B9: 25278.7 | C9: 68.17 | E9: 83.755 | H9: =LN(B9/B10) -> 0.010650414 | I9: =LN(C9/C10) -> -0.075960862 | K9: =(E9-E10)/E10 -> -0.0013354478 | M9: 45016 | N9: 0.062 | P9: 45512 | Q9: 0.065 | S9: 45597 | T9: 6032.38 | V9: 2003-2004 | W9: 39959.7 | X9: 5805 | Y9: 0 | Z9: 0 | AA9: 45764.7 | AC9: 45566 | AD9: 6.841 | AE9: 6.759 | AF9: 6.875 | AG9: 6.73 | AH9: 0.0135
A10: 45505 | B10: 25010.9 | C10: 73.55 | E10: 83.867 | H10: =LN(B10/B11) -> 0.035360739 | I10: =LN(C10/C11) -> -0.057588867 | K10: =(E10-E11)/E11 -> 0.0020071924 | M10: 44926 | N10: 0.043 | P10: 45504 | Q10: 0.065 | S10: 45566 | T10: 5705.45 | V10: 2004-2005 | W10: 44122.7 | X10: 1758.6 | Y10: 0 | Z10: 0 | AA10: 45881.3 | AC10: 45536 | AD10: 6.75 | AE10: 6.877 | AF10: 6.885 | AG10: 6.706 | AH10: -0.0165
A11: 45474 | B11: 24141.95 | C11: 77.91 | E11: 83.699 | H11: =LN(B11/B12) -> 0.037048188 | I11: =LN(C11/C12) -> -0.045539383 | K11: =(E11-E12)/E12 -> 0.004126927 | M11: 44834 | N11: 0.055 | P11: 45443 | Q11: 0.065 | S11: 45536 | T11: 5762.48 | V11: 2005-2006 | W11: 48800.5 | X11: -7333.8 | Y11: 0 | Z11: 0 | AA11: 41466.7 | AC11: 45505 | AD11: 6.863 | AE11: 6.912 | AF11: 6.919 | AG11: 6.843 | AH11: -0.0088 | AL11: LINEAR REGRESSION | BT11: MULTIPLE LINEAR REGRESSION (NIFTY VS CRUDE OIL, INFLATION AND CURRENCY EXCHANGE)
A12: 45444 | B12: 23263.9 | C12: 81.54 | E12: 83.355 | H12: =LN(B12/B13) -> 0.026822424 | I12: =LN(C12/C13) -> 0.057418154 | K12: =(E12-E13)/E13 -> -0.00082710012 | M12: 44742 | N12: 0.128 | P12: 45387 | Q12: 0.065 | S12: 45505 | T12: 5648.4 | V12: 2006-2007 | W12: 25235.7 | X12: 5604.7 | Y12: 0 | Z12: 0 | AA12: 30840.4 | AC12: 45474 | AD12: 6.924 | AE12: 7.023 | AF12: 7.024 | AG12: 6.91 | AH12: -0.012
A13: 45413 | B13: 22648.2 | C13: 76.99 | E13: 83.424 | H13: =LN(B13/B14) -> 0.008255386 | I13: =LN(C13/C14) -> -0.062189681 | K13: =(E13-E14)/E14 -> -0.00031156381 | M13: 44651 | N13: 0.045 | P13: 45382 | Q13: 0.065 | S13: 45474 | T13: 5522.3 | V13: 2007-2008 | W13: 53403.8 | X13: 12775.3 | Y13: 0 | Z13: 0 | AA13: 66179.1 | AC13: 45444 | AD13: 7.008 | AE13: 6.955 | AF13: 7.062 | AG13: 6.945 | AH13: 0.0031
A14: 45383 | B14: 22462 | C14: 81.93 | E14: 83.45 | H14: =LN(B14/B15) -> 0.0055021539 | I14: =LN(C14/C15) -> -0.015021482 | K14: =(E14-E15)/E15 -> 0.00119976 | M14: 44561 | N14: 0.055 | P14: 45330 | Q14: 0.065 | S14: 45444 | T14: 5460.48 | V14: 2008-2009 | W14: -47706.2 | X14: 1895.2 | Y14: 0 | Z14: 0 | AA14: -45811 | AC14: 45413 | AD14: 6.986 | AE14: 7.17 | AF14: 7.173 | AG14: 6.967 | AH14: -0.029 | AL14: SUMMARY OUTPUT (NIFTY and Crude Oil) | AW14: SUMMARY OUTPUT (NIFTY and Inflation) | BH14: SUMMARY OUTPUT (NIFTY and Currency Exchange) | BT14: SUMMARY OUTPUT
A15: 45352 | B15: 22338.75 | C15: 83.17 | E15: 83.35 | H15: =LN(B15/B16) -> 0.029128097 | I15: =LN(C15/C16) -> 0.060850089 | K15: =(E15-E16)/E16 -> 0.0054282268 | M15: 44469 | N15: 0.099 | P15: 45322 | Q15: 0.065 | S15: 45413 | T15: 5277.51 | V15: 2009-2010 | W15: 110220.6 | X15: 32437.7 | Y15: 0 | Z15: 0 | AA15: 142658.3 | AC15: 45383 | AD15: 7.195 | AE15: 7.085 | AF15: 7.242 | AG15: 7.075 | AH15: 0.0203
A16: 45323 | B16: 21697.45 | C16: 78.26 | E16: 82.9 | H16: =LN(B16/B17) -> -0.0020465323 | I16: =LN(C16/C17) -> 0.031278911 | K16: =(E16-E17)/E17 -> -0.0023467116 | M16: 44377 | N16: 0.226 | P16: 45268 | Q16: 0.065 | S16: 45383 | T16: 5035.69 | V16: 2010-2011 | W16: 110121.1 | X16: 36317 | Y16: 0 | Z16: 0 | AA16: 146438.1 | AC16: 45352 | AD16: 7.052 | AE16: 7.062 | AF16: 7.103 | AG16: 7.006 | AH16: -0.0037 | AL16: Regression Statistics | AW16: Regression Statistics | BH16: Regression Statistics | BT16: Regression Statistics
A17: 45292 | B17: 21741.9 | C17: 75.85 | E17: 83.095 | H17: =LN(B17/B18) -> 0.070202921 | I17: =LN(C17/C18) -> 0.056964552 | K17: =(E17-E18)/E18 -> -0.0011419642 | M17: 44286 | N17: 0.033 | P17: 31-11-2023 | Q17: 0.065 | S17: 45352 | T17: 5254.35 | V17: 2011-2012 | W17: 43737.6 | X17: 49987.9 | Y17: 0 | Z17: 0 | AA17: 93725.5 | AC17: 45323 | AD17: 7.078 | AE17: 7.129 | AF17: 7.14 | AG17: 7.021 | AH17: -0.0092 | AL17: Multiple R | AM17: 0.25627122 | AW17: Multiple R | AX17: 0.050375923 | BH17: Multiple R | BI17: 0.039364873 | BT17: Multiple R | BU17: 0.27728939
A18: 45261 | B18: 20267.9 | C18: 71.65 | E18: 83.19 | H18: =LN(B18/B19) -> 0.06517059 | I18: =LN(C18/C19) -> -0.058413732 | K18: =(E18-E19)/E19 -> -0.002003431 | M18: 44196 | N18: 0.018 | P18: 45205 | Q18: 0.065 | S18: 45323 | T18: 5096.27 | V18: 2012-2013 | W18: 140032.6 | X18: 28334.4 | Y18: 0 | Z18: 0 | AA18: 168367 | AC18: 45292 | AD18: 7.144 | AE18: 7.207 | AF18: 7.239 | AG18: 7.134 | AH18: -0.0045 | AL18: R Square | AM18: 0.065674937 | AW18: R Square | AX18: 0.0025377336 | BH18: R Square | BI18: 0.0015495932 | BT18: R Square | BU18: 0.076889408
A19: 45231 | B19: 18989.15 | C19: 75.96 | E19: 83.357 | H19: =LN(B19/B20) -> -0.028019975 | I19: =LN(C19/C20) -> -0.064489152 | K19: =(E19-E20)/E20 -> 0.0012131258 | M19: 44104 | N19: -0.058 | P19: 45199 | Q19: 0.065 | S19: 45292 | T19: 4845.65 | V19: 2013-2014 | W19: 79708.68 | X19: -28059.89 | Y19: 0 | Z19: 0 | AA19: 51648.79 | AC19: 45261 | AD19: 7.176 | AE19: 7.293 | AF19: 7.298 | AG19: 7.147 | AH19: -0.0142 | AL19: Adjusted R Square | AM19: 0.057620411 | AW19: Adjusted R Square | AX19: -0.0084233902 | BH19: Adjusted R Square | BI19: -0.0070577379 | BT19: Adjusted R Square | BU19: 0.045773321
A20: 45200 | B20: 19528.75 | C20: 81.02 | E20: 83.256 | H20: =LN(B20/B21) -> 0.0047967385 | I20: =LN(C20/C21) -> -0.11385311 | K20: =(E20-E21)/E21 -> 0.0027219077 | M20: 44012 | N20: -0.231 | P20: 45148 | Q20: 0.065 | S20: 45261 | T20: 4769.83 | V20: 2014-2015 | W20: 111332.59 | X20: 166127.09 | Y20: 0 | Z20: 0 | AA20: 277459.68 | AC20: 45231 | AD20: 7.279 | AE20: 7.376 | AF20: 7.376 | AG20: 7.194 | AH20: -0.0098 | AL20: Standard Error | AM20: 0.047680204 | AW20: Standard Error | AX20: 0.05306606 | BH20: Standard Error | BI20: 0.049289266 | BT20: Standard Error | BU20: 0.051620376
A21: 45170 | B21: 19435.3 | C21: 90.79 | E21: 83.03 | H21: =LN(B21/B22) -> -0.015229233 | I21: =LN(C21/C22) -> 0.08214684 | K21: =(E21-E22)/E22 -> 0.0039660468 | M21: 43921 | N21: 0.029 | P21: 45138 | Q21: 0.065 | S21: 45231 | T21: 4567.8 | V21: 2015-2016 | W21: -14171.57 | X21: -4003.76 | Y21: 0 | Z21: 0 | AA21: -18175.33 | AC21: 45200 | AD21: 7.351 | AE21: 7.239 | AF21: 7.395 | AG21: 7.205 | AH21: 0.0196 | AL21: Observations | AM21: 118 | AW21: Observations | AX21: 93 | BH21: Observations | BI21: 118 | BT21: Observations | BU21: 93
A22: 45139 | B22: 19733.55 | C22: 83.63 | E22: 82.702 | H22: =LN(B22/B23) -> 0.021047425 | I22: =LN(C22/C23) -> 0.022125064 | K22: =(E22-E23)/E23 -> 0.0056177043 | M22: 43830 | N22: 0.033 | P22: 45085 | Q22: 0.065 | S22: 45200 | T22: 4193.8 | V22: 2016-2017 | W22: 55702.67 | X22: -7291.64 | Y22: 0 | Z22: 0 | AA22: 48411.03 | AC22: 45170 | AD22: 7.21 | AE22: 7.174 | AF22: 7.241 | AG22: 7.086 | AH22: 0.0061
A23: 45108 | B23: 19322.55 | C23: 81.8 | E23: 82.24 | H23: =LN(B23/B24) -> 0.044164457 | I23: =LN(C23/C24) -> 0.14668069 | K23: =(E23-E24)/E24 -> 0.0018150589 | M23: 43738 | N23: 0.043 | P23: 45077 | Q23: 0.065 | S23: 45170 | T23: 4288.05 | V23: 2017-2018 | W23: 25634.19 | X23: 119035.74 | Y23: 0 | Z23: 10.29 | AA23: 144680.22 | AC23: 45139 | AD23: 7.166 | AE23: 7.186 | AF23: 7.256 | AG23: 7.147 | AH23: -0.0008 | AL23: ANOVA | AW23: ANOVA | BH23: ANOVA | BT23: ANOVA
A24: 45078 | B24: 18487.75 | C24: 70.64 | E24: 82.091 | H24: =LN(B24/B25) -> 0.018567275 | I24: =LN(C24/C25) -> 0.036766197 | K24: =(E24-E25)/E25 -> -0.007123851 | M24: 43646 | N24: 0.051 | P24: 45022 | Q24: 0.065 | S24: 45139 | T24: 4507.66 | V24: 2018-2019 | W24: -87.73 | X24: -42355.97 | Y24: 0 | Z24: 3514.24 | AA24: -38929.46 | AC24: 45108 | AD24: 7.172 | AE24: 7.113 | AF24: 7.185 | AG24: 7.047 | AH24: 0.0087 | AM24: df | AN24: SS | AO24: MS | AP24: F | AQ24: Significance F | AX24: df | AY24: SS | AZ24: MS | BA24: F | BB24: Significance F | BI24: df | BJ24: SS | BK24: MS | BL24: F | BM24: Significance F | BU24: df | BV24: SS | BW24: MS | BX24: F | BY24: Significance F
A25: 45047 | B25: 18147.65 | C25: 68.09 | E25: 82.68 | H25: =LN(B25/B26) -> 0.042182945 | I25: =LN(C25/C26) -> -0.12011383 | K25: =(E25-E26)/E26 -> 0.01174743 | M25: 43555 | N25: 0.057 | P25: 45016 | Q25: 0.065 | S25: 45108 | T25: 4588.96 | V25: 2019-2020 | W25: 6152.26 | X25: -48710.23 | Y25: 7331.17 | Z25: 7697.63 | AA25: -27529.17 | AC25: 45078 | AD25: 7.11 | AE25: 7.019 | AF25: 7.117 | AG25: 6.963 | AH25: 0.0173 | AL25: Regression | AM25: 1 | AN25: 0.018536847 | AO25: 0.018536847 | AP25: 8.1537925 | AQ25: 0.0050925358 | AW25: Regression | AX25: 1 | AY25: 0.00065196553 | AZ25: 0.00065196553 | BA25: 0.2315213 | BB25: 0.63155306 | BH25: Regression | BI25: 1 | BJ25: 0.00043737495 | BK25: 0.00043737495 | BL25: 0.18003179 | BM25: 0.67213179 | BT25: Regression | BU25: 3 | BV25: 0.019753548 | BW25: 0.0065845161 | BX25: 2.47105 | BY25: 0.066966031
A26: 45017 | B26: 17398.05 | C26: 76.78 | E26: 81.72 | H26: =LN(B26/B27) -> -0.0030330923 | I26: =LN(C26/C27) -> 0.014562409 | K26: =(E26-E27)/E27 -> -0.0053554041 | M26: 43465 | N26: 0.062 | P26: 44965 | Q26: 0.065 | S26: 45078 | T26: 4450.38 | V26: 2020-2021 | W26: 274031.96 | X26: -50443.62 | Y26: 33264.56 | Z26: 10247.09 | AA26: 267099.99 | AC26: 45047 | AD26: 6.989 | AE26: 7.135 | AF26: 7.138 | AG26: 6.947 | AH26: -0.0178 | AL26: Residual | AM26: 116 | AN26: 0.26371461 | AO26: 0.0022734018 | AW26: Residual | AX26: 91 | AY26: 0.25625661 | AZ26: 0.0028160067 | BH26: Residual | BI26: 116 | BJ26: 0.28181408 | BK26: 0.0024294317 | BT26: Residual | BU26: 89 | BV26: 0.23715503 | BW26: 0.0026646632
A27: 44986 | B27: 17450.9 | C27: 75.67 | D27: 5.79 | E27: 82.16 | H27: =LN(B27/B28) -> -0.0094333866 | I27: =LN(C27/C28) -> -0.018072781 | J27: =(D27-D28)/D28 -> -0.060064935 | K27: =(E27-E28)/E28 -> -0.0058083253 | M27: 43373 | N27: 0.065 | P27: 44957 | Q27: 0.0625 | S27: 45047 | T27: 4179.83 | V27: 2021-2022 | W27: -140009.6 | X27: 1628.53 | Y27: 12642.83 | Z27: 3498.41 | AA27: -122239.83 | AC27: 45017 | AD27: 7.116 | AE27: 7.37 | AF27: 7.37 | AG27: 7.077 | AH27: -0.0272 | AL27: Total | AM27: 117 | AN27: 0.28225146 | AW27: Total | AX27: 92 | AY27: 0.25690858 | BH27: Total | BI27: 117 | BJ27: 0.28225146 | BT27: Total | BU27: 92 | BV27: 0.25690858
A28: 44958 | B28: 17616.3 | C28: 77.05 | D28: 6.16 | E28: 82.64 | H28: =LN(B28/B29) -> -0.032456865 | I28: =LN(C28/C29) -> -0.038946128 | J28: =(D28-D29)/D29 -> 0.0016260163 | K28: =(E28-E29)/E29 -> 0.01102289 | M28: 43281 | N28: 0.075 | P28: 44902 | Q28: 0.0625 | S28: 45017 | T28: 4169.48 | V28: 2022-2023 | W28: -37631.57 | X28: -8937.74 | Y28: 5814.04 | Z28: -181.71 | AA28: -40936.98 | AC28: 44986 | AD28: 7.315 | AE28: 7.468 | AF28: 7.473 | AG28: 7.28 | AH28: -0.019
A29: 44927 | B29: 18197.45 | C29: 80.11 | D29: 6.15 | E29: 81.739 | H29: =LN(B29/B30) -> -0.033240068 | I29: =LN(C29/C30) -> -0.0044837539 | J29: =(D29-D30)/D30 -> 0.11818182 | K29: =(E29-E30)/E30 -> -0.011823446 | M29: 43190 | N29: 0.089 | P29: 44895 | Q29: 0.059 | S29: 44986 | T29: 4109.31 | V29: 2023-2024 | W29: 208211.24 | X29: 121058.84 | Y29: -2972.37 | Z29: 12766.91 | AA29: 339064.62 | AC29: 44958 | AD29: 7.457 | AE29: 7.416 | AF29: 7.465 | AG29: 7.245 | AH29: 0.0155 | AM29: Coefficients | AN29: Standard Error | AO29: t Stat | AP29: P-value | AQ29: Lower 95% | AR29: Upper 95% | AS29: Lower 95.0% | AT29: Upper 95.0% | AX29: Coefficients | AY29: Standard Error | AZ29: t Stat | BA29: P-value | BB29: Lower 95% | BC29: Upper 95% | BD29: Lower 95.0% | BE29: Upper 95.0% | BI29: Coefficients | BJ29: Standard Error | BK29: t Stat | BL29: P-value | BM29: Lower 95% | BN29: Upper 95% | BO29: Lower 95.0% | BP29: Upper 95.0% | BU29: Coefficients | BV29: Standard Error | BW29: t Stat | BX29: P-value | BY29: Lower 95% | BZ29: Upper 95% | CA29: Lower 95.0% | CB29: Upper 95.0%
A30: 44896 | B30: 18812.5 | C30: 80.47 | D30: 5.5 | E30: 82.717 | H30: =LN(B30/B31) -> 0.036104457 | I30: =LN(C30/C31) -> -0.0011178043 | J30: =(D30-D31)/D31 -> 0.01663586 | K30: =(E30-E31)/E31 -> 0.016691454 | M30: 43100 | N30: 0.067 | P30: 44865 | Q30: 0.059 | S30: 44958 | T30: 3970.15 | V30: 2024-2025 | W30: 31991.9 | X30: 53090.09 | Y30: -497.77 | Z30: 2291.67 | AA30: 86875.89 | AC30: 44927 | AD30: 7.343 | AE30: 7.346 | AF30: 7.407 | AG30: 7.266 | AH30: 0.0022 | AL30: Intercept | AM30: 0.0081334488 | AN30: 0.0043895952 | AO30: 1.8528927 | AP30: 0.066439324 | AQ30: -0.00056069755 | AR30: 0.016827595 | AS30: -0.00056069755 | AT30: 0.016827595 | AW30: Intercept | AX30: 0.0078025554 | AY30: 0.0055268327 | AZ30: 1.4117589 | BA30: 0.16143124 | BB30: -0.0031758189 | BC30: 0.01878093 | BD30: -0.0031758189 | BE30: 0.01878093 | BH30: Intercept | BI30: 0.0079285269 | BJ30: 0.004609993 | BK30: 1.7198566 | BL30: 0.088125398 | BM30: -0.0012021451 | BN30: 0.017059199 | BO30: -0.0012021451 | BP30: 0.017059199 | BT30: Intercept | BU30: 0.0072762978 | BV30: 0.0054756558 | BW30: 1.328845 | BX30: 0.18729599 | BY30: -0.0036037135 | BZ30: 0.018156309 | CA30: -0.0036037135 | CB30: 0.018156309
A31: 44866 | B31: 18145.4 | C31: 80.56 | D31: 5.41 | E31: 81.359 | H31: =LN(B31/B32) -> 0.071852264 | I31: =LN(C31/C32) -> -0.071488926 | J31: =(D31-D32)/D32 -> -0.11019737 | K31: =(E31-E32)/E32 -> -0.017047239 | M31: 43008 | N31: 0.053 | P31: 44834 | Q31: 0.059 | S31: 44927 | T31: 4076.6 | V31: Total | W31: 1230653.7 | X31: 444526.41 | Y31: 55777.78 | Z31: 45564.76 | AA31: 1776522.6 | AC31: 44896 | AD31: 7.327 | AE31: 7.255 | AF31: 7.344 | AG31: 7.181 | AH31: 0.0065 | AL31: -0.20536053 | AM31: 0.097633476 | AN31: 0.034191561 | AO31: 2.8554846 | AP31: 0.0050925358 | AQ31: 0.029912782 | AR31: 0.16535417 | AS31: 0.029912782 | AT31: 0.16535417 | AW31: -0.060064935 | AX31: 0.013938376 | AY31: 0.02896788 | AZ31: 0.4811666 | BA31: 0.63155306 | BB31: -0.043602759 | BC31: 0.071479511 | BD31: -0.043602759 | BE31: 0.071479511 | BH31: -0.010074889 | BI31: 0.13327686 | BJ31: 0.31410883 | BK31: 0.42430153 | BL31: 0.67213179 | BM31: -0.48885527 | BN31: 0.75540899 | BO31: -0.48885527 | BP31: 0.75540899 | BT31: -0.018072781 | BU31: 0.10242777 | BV31: 0.038544475 | BW31: 2.6573916 | BX31: 0.0093342103 | BY31: 0.025840714 | BZ31: 0.17901482 | CA31: 0.025840714 | CB31: 0.17901482
A32: 44835 | B32: 16887.35 | C32: 86.53 | D32: 6.08 | E32: 82.77 | H32: =LN(B32/B33) -> -0.038078788 | I32: =LN(C32/C33) -> 0.084859947 | J32: =(D32-D33)/D33 -> -0.063174114 | K32: =(E32-E33)/E33 -> 0.015470684 | M32: 42916 | N32: 0.061 | P32: 44777 | Q32: 0.054 | S32: 44896 | T32: 3839.5 | AC32: 44866 | AD32: 7.28 | AE32: 7.435 | AF32: 7.497 | AG32: 7.235 | AH32: -0.0222 | BT32: -0.060064935 | BU32: 0.0027522225 | BV32: 0.028642567 | BW32: 0.096088541 | BX32: 0.92366629 | BY32: -0.054159948 | BZ32: 0.059664393 | CA32: -0.054159948 | CB32: 0.059664393
A33: 44805 | B33: 17542.8 | C33: 79.49 | D33: 6.49 | E33: 81.509 | H33: =LN(B33/B34) -> 0.011624754 | I33: =LN(C33/C34) -> -0.1191659 | J33: =(D33-D34)/D34 -> 0.10940171 | K33: =(E33-E34)/E34 -> 0.025386522 | M33: 42825 | N33: 0.063 | P33: 44773 | Q33: 0.049 | S33: 44866 | T33: 4080.11 | AC33: 44835 | AD33: 7.445 | AE33: 7.403 | AF33: 7.541 | AG33: 7.361 | AH33: 0.0064 | BT33: -0.0058083253 | BU33: 0.15586564 | BV33: 0.34000527 | BW33: 0.45842125 | BX33: 0.64776727 | BY33: -0.51971759 | BZ33: 0.83144888 | CA33: -0.51971759 | CB33: 0.83144888
A34: 44774 | B34: 17340.05 | C34: 89.55 | D34: 5.85 | E34: 79.491 | H34: =LN(B34/B35) -> 0.096048339 | I34: =LN(C34/C35) -> -0.096476952 | J34: =(D34-D35)/D35 -> 0.012110727 | K34: =(E34-E35)/E35 -> 0.0019537158 | M34: 42735 | N34: 0.086 | P34: 44720 | Q34: 0.049 | S34: 44835 | T34: 3871.98 | AC34: 44805 | AD34: 7.398 | AE34: 7.23 | AF34: 7.423 | AG34: 7.106 | AH34: 0.0292
A35: 44743 | B35: 15752.05 | C35: 98.62 | D35: 5.78 | E35: 79.336 | H35: =LN(B35/B36) -> -0.047767704 | I35: =LN(C35/C36) -> -0.069898295 | J35: =(D35-D36)/D36 -> -0.061688312 | K35: =(E35-E36)/E36 -> 0.0048891704 | M35: 42643 | N35: 0.097 | P35: 44685 | Q35: 0.044 | S35: 44805 | T35: 3585.62 | AC35: 44774 | AD35: 7.188 | AE35: 7.357 | AF35: 7.366 | AG35: 7.11 | AH35: -0.018
A36: 44713 | B36: 16522.75 | C36: 105.76 | D36: 6.16 | E36: 78.95 | H36: =LN(B36/B37) -> -0.032531592 | I36: =LN(C36/C37) -> -0.080886062 | J36: =(D36-D37)/D37 -> -0.11621234 | K36: =(E36-E37)/E37 -> 0.017803504 | M36: 42551 | N36: 0.087 | P36: 44659 | Q36: 0.04 | S36: 44774 | T36: 3955 | AC36: 44743 | AD36: 7.32 | AE36: 7.427 | AF36: 7.475 | AG36: 7.255 | AH36: -0.0174
A37: 44682 | B37: 17069.1 | C37: 114.67 | D37: 6.97 | E37: 77.569 | H37: =LN(B37/B38) -> -0.034623942 | I37: =LN(C37/C38) -> 0.091054836 | J37: =(D37-D38)/D38 -> 0.10110585 | K37: =(E37-E38)/E38 -> 0.013708834 | M37: 42460 | N37: 0.091 | P37: 44601 | Q37: 0.04 | S37: 44743 | T37: 4130.29 | AC37: 44713 | AD37: 7.45 | AE37: 7.437 | AF37: 7.617 | AG37: 7.365 | AH37: 0.0047
A38: 44652 | B38: 17670.45 | C38: 104.69 | D38: 6.33 | E38: 76.52 | H38: =LN(B38/B39) -> 0.062132688 | I38: =LN(C38/C39) -> 0.043037329 | J38: =(D38-D39)/D39 -> 0.18317757 | K38: =(E38-E39)/E39 -> 0.0081553603 | M38: 42369 | N38: 0.072 | P38: 44538 | Q38: 0.04 | S38: 44713 | T38: 3785.38 | AC38: 44682 | AD38: 7.415 | AE38: 7.138 | AF38: 7.491 | AG38: 7.116 | AH38: 0.0387
A39: 44621 | B39: 16605.95 | C39: 100.28 | D39: 5.35 | E39: 75.901 | H39: =LN(B39/B40) -> -0.05682163 | I39: =LN(C39/C40) -> 0.04653901 | J39: =(D39-D40)/D40 -> 0.061507937 | K39: =(E39-E40)/E40 -> 0.0054044746 | M39: 42277 | N39: 0.08 | P39: 44477 | Q39: 0.04 | S39: 44682 | T39: 4132.15 | AC39: 44652 | AD39: 7.139 | AE39: 6.951 | AF39: 7.285 | AG39: 6.891 | AH39: 0.0433
A40: 44593 | B40: 17576.85 | C40: 95.72 | D40: 5.04 | E40: 75.493 | H40: =LN(B40/B41) -> -0.0027753689 | I40: =LN(C40/C41) -> 0.082387354 | J40: =(D40-D41)/D41 -> -0.1369863 | K40: =(E40-E41)/E41 -> 0.012934562 | M40: 42185 | N40: 0.076 | P40: 44408 | Q40: 0.04 | S40: 44652 | T40: 4131.93 | AC40: 44621 | AD40: 6.843 | AE40: 6.799 | AF40: 6.919 | AG40: 6.773 | AH40: 0.0108
A41: 44562 | B41: 17625.7 | C41: 88.15 | D41: 5.84 | E41: 74.529 | H41: =LN(B41/B42) -> 0.026374953 | I41: =LN(C41/C42) -> 0.15875571 | J41: =(D41-D42)/D42 -> 0.050359712 | K41: =(E41-E42)/E42 -> 0.00083258356 | P41: 44351 | Q41: 0.04 | S41: 44621 | T41: 4530.41 | AC41: 44593 | AD41: 6.77 | AE41: 6.728 | AF41: 6.955 | AG41: 6.615 | AH41: 0.0129
A42: 44531 | B42: 17166.9 | C42: 75.21 | D42: 5.56 | E42: 74.467 | H42: =LN(B42/B43) -> -0.043472656 | I42: =LN(C42/C43) -> 0.1279059 | J42: =(D42-D43)/D43 -> 0.14876033 | K42: =(E42-E43)/E43 -> -0.0082967106 | P42: 44232 | Q42: 0.04 | S42: 44593 | T42: 4373.94 | AC42: 44562 | AD42: 6.684 | AE42: 6.463 | AF42: 6.802 | AG42: 6.455 | AH42: 0.0356
A43: 44501 | B43: 17929.65 | C43: 66.18 | D43: 4.84 | E43: 75.09 | H43: =LN(B43/B44) -> 0.022425133 | I43: =LN(C43/C44) -> -0.2333063 | J43: =(D43-D44)/D44 -> 0.075555556 | K43: =(E43-E44)/E44 -> 0.0023359808 | P43: 44169 | Q43: 0.04 | S43: 44562 | T43: 4515.55 | AC43: 44531 | AD43: 6.454 | AE43: 6.36 | AF43: 6.497 | AG43: 6.34 | AH43: 0.0202
A44: 44470 | B44: 17532.05 | C44: 83.57 | D44: 4.5 | E44: 74.915 | H44: =LN(B44/B45) -> 0.026342025 | I44: =LN(C44/C45) -> 0.10779657 | J44: =(D44-D45)/D45 -> 0.020408163 | K44: =(E44-E45)/E45 -> 0.010126207 | P44: 44104 | Q44: 0.04 | S44: 44531 | T44: 4766.18 | AC44: 44501 | AD44: 6.326 | AE44: 6.391 | AF44: 6.393 | AG44: 6.287 | AH44: -0.0097
A45: 44440 | B45: 17076.25 | C45: 75.03 | D45: 4.41 | E45: 74.164 | H45: =LN(B45/B46) -> 0.072303899 | I45: =LN(C45/C46) -> 0.091054288 | J45: =(D45-D46)/D46 -> -0.079331942 | K45: =(E45-E46)/E46 -> 0.016683345 | P45: 43973 | Q45: 0.04 | S45: 44501 | T45: 4567 | AC45: 44470 | AD45: 6.388 | AE45: 6.23 | AF45: 6.429 | AG45: 6.226 | AH45: 0.0265
A46: 44409 | B46: 15885.15 | C46: 68.5 | D46: 4.79 | E46: 72.947 | H46: =LN(B46/B47) -> 0.012998696 | I46: =LN(C46/C47) -> -0.076555444 | J46: =(D46-D47)/D47 -> -0.091081594 | K46: =(E46-E47)/E47 -> -0.018698629 | P46: 43951 | Q46: 0.044 | S46: 44470 | T46: 4605.38 | AC46: 44440 | AD46: 6.223 | AE46: 6.235 | AF46: 6.235 | AG46: 6.116 | AH46: 0.0013
A47: 44378 | B47: 15680 | C47: 73.95 | D47: 5.27 | E47: 74.337 | H47: =LN(B47/B48) -> 0.0067285811 | I47: =LN(C47/C48) -> 0.0065120295 | J47: =(D47-D48)/D48 -> -0.053859964 | K47: =(E47-E48)/E48 -> -0.00030930608 | P47: 43867 | Q47: 0.0515 | S47: 44440 | T47: 4307.54 | AC47: 44409 | AD47: 6.215 | AE47: 6.204 | AF47: 6.284 | AG47: 6.188 | AH47: 0.0018
A48: 44348 | B48: 15574.85 | C48: 73.47 | D48: 5.57 | E48: 74.36 | H48: =LN(B48/B49) -> 0.062299595 | I48: =LN(C48/C49) -> 0.10238565 | J48: =(D48-D49)/D49 -> 0.062977099 | K48: =(E48-E49)/E49 -> 0.025499579 | P48: 43742 | Q48: 0.0515 | S48: 44409 | T48: 4522.68 | AC48: 44378 | AD48: 6.204 | AE48: 6.082 | AF48: 6.277 | AG48: 6.035 | AH48: 0.0253
A49: 44317 | B49: 14634.15 | C49: 66.32 | D49: 5.24 | E49: 72.511 | H49: =LN(B49/B50) -> -0.015809695 | I49: =LN(C49/C50) -> 0.042192555 | J49: =(D49-D50)/D50 -> 0.019455253 | K49: =(E49-E50)/E50 -> -0.020783255 | P49: 43738 | Q49: 0.054 | S49: 44378 | T49: 4395.26 | AC49: 44348 | AD49: 6.051 | AE49: 6.032 | AF49: 6.089 | AG49: 5.984 | AH49: 0.0048
A50: 44287 | B50: 14867.35 | C50: 63.58 | D50: 5.14 | E50: 74.05 | H50: =LN(B50/B51) -> 0.0071417062 | I50: =LN(C50/C51) -> 0.072053318 | J50: =(D50-D51)/D51 -> -0.088652482 | K50: =(E50-E51)/E51 -> 0.012483422 | P50: 43677 | Q50: 0.0575 | S50: 44348 | T50: 4297.5 | AC50: 44317 | AD50: 6.022 | AE50: 6.029 | AF50: 6.048 | AG50: 5.958 | AH50: -0.0013
A51: 44256 | B51: 14761.55 | C51: 59.16 | D51: 5.64 | E51: 73.137 | H51: =LN(B51/B52) -> 0.03308184 | I51: =LN(C51/C52) -> -0.038791537 | J51: =(D51-D52)/D52 -> 0.25892857 | K51: =(E51-E52)/E52 -> -0.010592532 | P51: 43616 | Q51: 0.06 | S51: 44317 | T51: 4204.11 | AC51: 44287 | AD51: 6.03 | AE51: 6.202 | AF51: 6.202 | AG51: 5.99 | AH51: -0.0238
A52: 44228 | B52: 14281.2 | C52: 61.5 | D52: 4.48 | E52: 73.92 | H52: =LN(B52/B53) -> 0.018566101 | I52: =LN(C52/C53) -> 0.16395468 | J52: =(D52-D53)/D53 -> 0.42222222 | K52: =(E52-E53)/E53 -> 0.014311786 | P52: 43555 | Q52: 0.0625 | S52: 44287 | T52: 4181.17 | AC52: 44256 | AD52: 6.177 | AE52: 6.236 | AF52: 6.274 | AG52: 6.114 | AH52: -0.0083
... A66: 43800 | B66: 12048.2 | C66: 61.06 | D66: 9.63 | E66: 71.35 | H66: =LN(B66/B67) -> 0.013167099 | I66: =LN(C66/C67) -> 0.10143766 | J66: =(D66-D67)/D67 -> 0.71657754 | K66: =(E66-E67)/E67 -> -0.0055194715 | P66: 42155 | Q66: 0.075 | S66: 43862 | T66: 2954.22 | AC66: 43831 | AD66: 6.599 | AE66: 6.548 | AF66: 6.692 | AG66: 6.485 | AH66: 0.0069
A67: 43770 | B67: 11890.6 | C67: 55.17 | D67: 5.61 | E67: 71.746 | H67: =LN(B67/B68) -> 0.045658562 | I67: =LN(C67/C68) -> 0.018107491 | J67: =(D67-D68)/D68 -> -0.26377953 | K67: =(E67-E68)/E68 -> 0.010820254 | S67: 43831 | T67: 3225.52 | AC67: 43800 | AD67: 6.554 | AE67: 6.463 | AF67: 6.837 | AG67: 6.448 | AH67: 0.0146
A68: 43739 | B68: 11359.9 | C68: 54.18 | D68: 7.62 | E68: 70.978 | H68: =LN(B68/B69) -> 0.05073794 | I68: =LN(C68/C69) -> 0.0020323333 | J68: =(D68-D69)/D69 -> 0.091690544 | K68: =(E68-E69)/E69 -> 0.0047848245 | S68: 43800 | T68: 3230.78 | AC68: 43770 | AD68: 6.46 | AE68: 6.431 | AF68: 6.574 | AG68: 6.415 | AH68: -0.0275
A69: 43709 | B69: 10797.9 | C69: 54.07 | D69: 6.98 | E69: 70.64 | H69: =LN(B69/B70) -> -0.016723765 | I69: =LN(C69/C70) -> -0.018870213 | J69: =(D69-D70)/D70 -> 0.10618067 | K69: =(E69-E70)/E70 -> -0.011350436 | S69: 43770 | T69: 3140.98 | AC69: 43739 | AD69: 6.643 | AE69: 6.68 | AF69: 6.739 | AG69: 6.582 | AH69: -0.0078
A70: 43678 | B70: 10980 | C70: 55.1 | D70: 6.31 | E70: 71.451 | H70: =LN(B70/B71) -> -0.077568021 | I70: =LN(C70/C71) -> -0.061243625 | J70: =(D70-D71)/D71 -> 0.055183946 | K70: =(E70-E71)/E71 -> 0.037627069 | S70: 43739 | T70: 3037.56 | AC70: 43709 | AD70: 6.695 | AE70: 6.498 | AF70: 6.874 | AG70: 6.488 | AH70: 0.0212
A71: 43647 | B71: 11865.6 | C71: 58.58 | D71: 5.98 | E71: 68.86 | H71: =LN(B71/B72) -> -0.018615266 | I71: =LN(C71/C72) -> 0.0018795392 | J71: =(D71-D72)/D72 -> -0.30384168 | K71: =(E71-E72)/E72 -> -0.0011604294 | S71: 43709 | T71: 2976.74 | AC71: 43678 | AD71: 6.556 | AE71: 6.394 | AF71: 6.639 | AG71: 6.296 | AH71: 0.0294
A72: 43617 | B72: 12088.55 | C72: 58.47 | D72: 8.59 | E72: 68.94 | H72: =LN(B72/B73) -> 0.030556731 | I72: =LN(C72/C73) -> 0.088832148 | J72: =(D72-D73)/D73 -> -0.0069364162 | K72: =(E72-E73)/E73 -> -0.0090556274 | S72: 43678 | T72: 2926.46 | AC72: 43647 | AD72: 6.369 | AE72: 6.906 | AF72: 6.93 | AG72: 6.266 | AH72: -0.0741
A73: 43586 | B73: 11724.75 | C73: 53.5 | D73: 8.65 | E73: 69.57 | H73: =LN(B73/B74) -> 0.0047533848 | I73: =LN(C73/C74) -> -0.17779419 | J73: =(D73-D74)/D74 -> 0.038415366 | K73: =(E73-E74)/E74 -> -0.00094778563 | S73: 43647 | T73: 2980.38 | AC73: 43617 | AD73: 6.879 | AE73: 6.949 | AF73: 7.097 | AG73: 6.734 | AH73: -0.0218
A74: 43556 | B74: 11669.15 | C74: 63.91 | D74: 8.33 | E74: 69.636 | H74: =LN(B74/B75) -> 0.071540061 | I74: =LN(C74/C75) -> 0.060800666 | J74: =(D74-D75)/D75 -> 0.086049544 | K74: =(E74-E75)/E75 -> 0.0065915004 | S74: 43617 | T74: 2941.76 | AC74: 43586 | AD74: 7.032 | AE74: 7.411 | AF74: 7.426 | AG74: 7.03 | AH74: -0.0515
A75: 43525 | B75: 10863.5 | C75: 60.14 | D75: 7.67 | E75: 69.18 | H75: =LN(B75/B76) -> -0.0027715045 | I75: =LN(C75/C76) -> 0.04977169 | J75: =(D75-D76)/D76 -> 0.10043042 | K75: =(E75-E76)/E76 -> -0.023295214 | S75: 43586 | T75: 2752.06 | AC75: 43556 | AD75: 7.414 | AE75: 7.356 | AF75: 7.497 | AG75: 7.229 | AH75: 0.0093
A76: 43497 | B76: 10893.65 | C76: 57.22 | D76: 6.97 | E76: 70.83 | H76: =LN(B76/B77) -> -0.001508915 | I76: =LN(C76/C77) -> 0.061815911 | J76: =(D76-D77)/D77 -> 0.056060606 | K76: =(E76-E77)/E77 -> -0.0016913319 | S76: 43556 | T76: 2945.83 | AC76: 43525 | AD76: 7.346 | AE76: 7.588 | AF76: 7.59 | AG76: 7.301 | AH76: -0.0323
A77: 43466 | B77: 10910.1 | C77: 53.79 | D77: 6.6 | E77: 70.95 | H77: =LN(B77/B78) -> 0.0024181145 | I77: =LN(C77/C78) -> 0.16935523 | J77: =(D77-D78)/D78 -> 0.25954198 | K77: =(E77-E78)/E78 -> 0.019982749 | S77: 43525 | T77: 2834.4 | AC77: 43497 | AD77: 7.591 | AE77: 7.47 | AF77: 7.699 | AG77: 7.425 | AH77: 0.0144
A78: 43435 | B78: 10883.75 | C78: 45.41 | D78: 5.24 | E78: 69.56 | H78: =LN(B78/B79) -> 0.047346622 | I78: =LN(C78/C79) -> -0.1147198 | J78: =(D78-D79)/D79 -> 0.0781893 | K78: =(E78-E79)/E79 -> -0.0011487651 | S78: 43497 | T78: 2784.49 | AC78: 43466 | AD78: 7.483 | AE78: 7.401 | AF78: 7.65 | AG78: 7.35 | AH78: 0.0153
... A121: 42125 | B121: 8331.95 | C121: 60.3 | D121: 5.74 | E121: 63.733 | H121: =LN(B121/B122) -> -0.038605653 | I121: =LN(C121/C122) -> #DIV/0! | J121: =(D121-D122)/D122 -> -0.0086355786 | K121: =(E121-E122)/E122 -> #DIV/0! | S121: 42186 | T121: 2103.84 | AC121: 42156 | AD121: 7.861 | AE121: 7.815 | AF121: 8.017 | AG121: 7.689 | AH121: 0.0059
A122: 42095 | B122: 8659.9 | D122: 5.79 | H122: =LN(B122/B123) -> #DIV/0! | I122: =LN(C122/C123) -> #DIV/0! | J122: =(D122-D123)/D123 -> #DIV/0! | K122: =(E122-E123)/E123 -> #DIV/0! | S122: 42156 | T122: 2063.11 | AC122: 42125 | AD122: 7.815 | AE122: 7.875 | AF122: 8.007 | AG122: 7.809 | AH122: -0.0057
S123: 42125 | T123: 2107.39 | AC123: 42095 | AD123: 7.86 | AE123: 7.722 | AF123: 7.873 | AG123: 7.711 | AH123: 0.0158
S124: 42095 | T124: 2085.51 | AC124: 42064 | AD124: 7.738 | AE124: 7.738 | AF124: 7.811 | AG124: 7.648 | AH124: 0.0018
S125: 42064 | T125: 2067.89 | AC125: 42036 | AD125: 7.724 | AE125: 7.7 | AF125: 7.752 | AG125: 7.64 | AH125: 0.0043
S126: 42036 | T126: 2104.5 | AC126: 42005 | AD126: 7.691 | AE126: 7.852 | AF126: 7.918 | AG126: 7.672 | AH126: -0.0209
S127: 0101-2015 | T127: 1994.99

Sheet Additional Macro Variables
A1: Date | B1: NIFTY Return | C1: Crude Oil Return | D1: Inflation change | E1: Currency change | F1: Change in Repo Rate | G1: Repo Rate | H1: S&P 500 | I1: S&P 500 Return | J1: 10-Year Government Bond Yield | K1: Change in Bond Yield
A2: 45748 | B2: 0.046222206 | C2: -0.20536053 | E2: -0.010074889 | F2: =(G2-G3)/G3 -> -0.04 | G2: 0.06 | H2: 5569.06 | I2: =(H2-H3)/H3 -> -0.0076249365 | J2: 6.35 | K2: =(J2-J3)/J3 -> -0.034954407
A3: 45717 | B3: -0.059790027 | C3: 0.024356911 | E3: -0.022990477 | F3: =(G3-G4)/G4 -> 0 | G3: 0.0625 | H3: 5611.85 | I3: =(H3-H4)/H4 -> -0.057544714 | J3: 6.58 | K3: =(J3-J4)/J4 -> -0.020833333
A4: 45689 | B4: -0.01104298 | C4: -0.03893949 | E4: 0.010512818 | F4: =(G4-G5)/G5 -> -0.038461538 | G4: 0.0625 | H4: 5954.5 | I4: =(H4-H5)/H5 -> -0.014242128 | J4: 6.72 | K4: =(J4-J5)/J5 -> 0.0044843049
A5: 45658 | B5: -0.022206729 | C5: 0.011230621 | E5: 0.011770344 | F5: =(G5-G6)/G6 -> 0 | G5: 0.065 | H5: 6040.53 | I5: =(H5-H6)/H6 -> 0.02701632 | J5: 6.69 | K5: =(J5-J6)/J6 -> -0.01035503
A6: 45627 | B6: -0.0011650791 | C6: 0.053261944 | E6: 0.011766932 | F6: =(G6-G7)/G7 -> 0 | G6: 0.065 | H6: 5881.63 | I6: =(H6-H7)/H7 -> -0.024990137 | J6: 6.76 | K6: =(J6-J7)/J7 -> 0.0013331358
A7: 45597 | B7: -0.059598983 | C7: -0.018359834 | E7: 0.0059242693 | F7: =(G7-G8)/G8 -> 0 | G7: 0.065 | H7: 6032.38 | I7: =(H7-H8)/H8 -> 0.057301352 | J7: 6.751 | K7: =(J7-J8)/J8 -> -0.013155971
A8: 45566 | B8: 0.020292186 | C8: 0.015862954 | E8: 0.0036535132 | F8: =(G8-G9)/G9 -> 0 | G8: 0.065 | H8: 5705.45 | I8: =(H8-H9)/H9 -> -0.0098967806 | J8: 6.841 | K8: =(J8-J9)/J9 -> 0.013481481
A9: 45536 | B9: 0.010650414 | C9: -0.075960862 | E9: -0.0013354478 | F9: =(G9-G10)/G10 -> 0 | G9: 0.065 | H9: 5762.48 | I9: =(H9-H10)/H10 -> 0.02019687 | J9: 6.75 | K9: =(J9-J10)/J10 -> -0.016465103
A10: 45505 | B10: 0.035360739 | C10: -0.057588867 | E10: 0.0020071924 | F10: =(G10-G11)/G11 -> 0 | G10: 0.065 | H10: 5648.4 | I10: =(H10-H11)/H11 -> 0.022834688 | J10: 6.863 | K10: =(J10-J11)/J11 -> -0.0088099365
A11: 45474 | B11: 0.037048188 | C11: -0.045539383 | E11: 0.004126927 | F11: =(G11-G12)/G12 -> 0 | G11: 0.065 | H11: 5522.3 | I11: =(H11-H12)/H12 -> 0.011321349 | J11: 6.924 | K11: =(J11-J12)/J12 -> -0.011986301
A12: 45444 | B12: 0.026822424 | C12: 0.057418154 | E12: -0.00082710012 | F12: =(G12-G13)/G13 -> 0 | G12: 0.065 | H12: 5460.48 | I12: =(H12-H13)/H13 -> 0.034669759 | J12: 7.008 | K12: =(J12-J13)/J13 -> 0.0031491555
A13: 45413 | B13: 0.008255386 | C13: -0.062189681 | E13: -0.00031156381 | F13: =(G13-G14)/G14 -> 0 | G13: 0.065 | H13: 5277.51 | I13: =(H13-H14)/H14 -> 0.048021224 | J13: 6.986 | K13: =(J13-J14)/J14 -> -0.02904795
... A26: 45017 | B26: -0.0030330923 | C26: 0.014562409 | E26: -0.0053554041 | F26: =(G26-G27)/G27 -> 0 | G26: 0.065 | H26: 4169.48 | I26: =(H26-H27)/H27 -> 0.014642361 | J26: 7.116 | K26: =(J26-J27)/J27 -> -0.027204375
A27: 44986 | B27: -0.0094333866 | C27: -0.018072781 | D27: -0.060064935 | E27: -0.0058083253 | F27: =(G27-G28)/G28 -> 0 | G27: 0.065 | H27: 4109.31 | I27: =(H27-H28)/H28 -> 0.035051572 | J27: 7.315 | K27: =(J27-J28)/J28 -> -0.01904251
A28: 44958 | B28: -0.032456865 | C28: -0.038946128 | D28: 0.0016260163 | E28: 0.01102289 | F28: =(G28-G29)/G29 -> 0.04 | G28: 0.065 | H28: 3970.15 | I28: =(H28-H29)/H29 -> -0.026112447 | J28: 7.457 | K28: =(J28-J29)/J29 -> 0.01552499
A29: 44927 | B29: -0.033240068 | C29: -0.0044837539 | D29: 0.11818182 | E29: -0.011823446 | F29: =(G29-G30)/G30 -> 0 | G29: 0.0625 | H29: 4076.6 | I29: =(H29-H30)/H30 -> 0.061752832 | J29: 7.343 | K29: =(J29-J30)/J30 -> 0.0021837041
A30: 44896 | B30: 0.036104457 | C30: -0.0011178043 | D30: 0.01663586 | E30: 0.016691454 | F30: =(G30-G31)/G31 -> 0.059322034 | G30: 0.0625 | H30: 3839.5 | I30: =(H30-H31)/H31 -> -0.058971449 | J30: 7.327 | K30: =(J30-J31)/J31 -> 0.006456044
A31: 44866 | B31: 0.071852264 | C31: -0.071488926 | D31: -0.11019737 | E31: -0.017047239 | F31: =(G31-G32)/G32 -> 0 | G31: 0.059 | H31: 4080.11 | I31: =(H31-H32)/H32 -> 0.05375286 | J31: 7.28 | K31: =(J31-J32)/J32 -> -0.022162525
A32: 44835 | B32: -0.038078788 | C32: 0.084859947 | D32: -0.063174114 | E32: 0.015470684 | F32: =(G32-G33)/G33 -> 0 | G32: 0.059 | H32: 3871.98 | I32: =(H32-H33)/H33 -> 0.079863455 | J32: 7.445 | K32: =(J32-J33)/J33 -> 0.0063530684
A33: 44805 | B33: 0.011624754 | C33: -0.1191659 | D33: 0.10940171 | E33: 0.025386522 | F33: =(G33-G34)/G34 -> 0.092592593 | G33: 0.059 | H33: 3585.62 | I33: =(H33-H34)/H34 -> -0.093395702 | J33: 7.398 | K33: =(J33-J34)/J34 -> 0.029215359
A34: 44774 | B34: 0.096048339 | C34: -0.096476952 | D34: 0.012110727 | E34: 0.0019537158 | F34: =(G34-G35)/G35 -> 0.10204082 | G34: 0.054 | H34: 3955 | I34: =(H34-H35)/H35 -> -0.042440119 | J34: 7.188 | K34: =(J34-J35)/J35 -> -0.018032787
A35: 44743 | B35: -0.047767704 | C35: -0.069898295 | D35: -0.061688312 | E35: 0.0048891704 | F35: =(G35-G36)/G36 -> 0 | G35: 0.049 | H35: 4130.29 | I35: =(H35-H36)/H36 -> 0.091116348 | J35: 7.32 | K35: =(J35-J36)/J36 -> -0.017449664
A36: 44713 | B36: -0.032531592 | C36: -0.080886062 | D36: -0.11621234 | E36: 0.017803504 | F36: =(G36-G37)/G37 -> 0.11363636 | G36: 0.049 | H36: 3785.38 | I36: =(H36-H37)/H37 -> -0.083919993 | J36: 7.45 | K36: =(J36-J37)/J37 -> 0.0047201618
A37: 44682 | B37: -0.034623942 | C37: 0.091054836 | D37: 0.10110585 | E37: 0.013708834 | F37: =(G37-G38)/G38 -> 0 | G37: 0.044 | H37: 4132.15 | I37: =(H37-H38)/H38 -> 5.3243884e-05 | J37: 7.415 | K37: =(J37-J38)/J38 -> 0.038660877
A38: 44652 | B38: 0.062132688 | C38: 0.043037329 | D38: 0.18317757 | E38: 0.0081553603 | F38: =(G38-G39)/G39 -> 0 | G38: 0.044 | H38: 4131.93 | I38: =(H38-H39)/H39 -> -0.087956719 | J38: 7.139 | K38: =(J38-J39)/J39 -> 0.043255882
... A120: 42156 | B120: 0.01210249 | C120: -0.01386012 | D120: 0.06271777 | E120: -0.0021809737 | F120: =(G120-G121)/G121 -> 0 | G120: 0.075 | H120: 2063.11 | I120: =(H120-H121)/H121 -> -0.021011773 | J120: 7.861 | K120: =(J120-J121)/J121 -> 0.0058861164
A121: 42125 | B121: -0.038605653 | C121: #DIV/0! | D121: -0.0086355786 | E121: #DIV/0! | F121: =(G121-G122)/G122 -> #DIV/0! | G121: 0.075 | H121: 2107.39 | I121: =(H121-H122)/H122 -> 0.010491439 | J121: 7.815 | K121: =(J121-J122)/J122 -> -0.0057251908
A122: 42095 | B122: #DIV/0! | C122: #DIV/0! | D122: #DIV/0! | E122: #DIV/0! | F122: =(G122-G123)/G123 -> #DIV/0! | H122: 2085.51 | I122: =(H122-H123)/H123 -> #DIV/0! | J122: 7.86 | K122: =(J122-J123)/J123 -> 0.015766348
F123: =(G123-G124)/G124 -> #DIV/0! | J123: 7.738 | K123: =(J123-J124)/J124 -> 0.0018125324
F124: =(G124-G125)/G125 -> #DIV/0! | J124: 7.724 | K124: =(J124-J125)/J125 -> 0.0042907294
F125: =(G125-G126)/G126 -> #DIV/0! | J125: 7.691 | K125: =(J125-J126)/J126 -> #DIV/0!

Sheet Multiple Regression Result
A1: Date | B1: NIFTY Return | C1: Crude Oil Return | D1: Inflation change | E1: Currency change | F1: Change in Repo Rate | G1: S&P 500 Return | H1: Change in Bond Yield | I1: Crude_Lag 1 | J1: Crude_Lag 2 | K1: Crude_Lag 3 | L1: Crude_Lag 4 | M1: Crude_Lag 5 | N1: Inflation_Lag1 | O1: Inflation_Lag2 | P1: Inflation_Lag3 | Q1: Inflation_Lag4 | R1: Inflation_Lag5 | S1: Currency_Lag1 | T1: Currency_Lag2 | U1: Currency_Lag3 | V1: Currency_Lag4 | W1: Currency_Lag5 | X1: Repo_Lag1 | Y1: Repo_Lag2 | Z1: Repo_Lag3 | AA1: Repo_Lag4 | AB1: Repo_Lag5 | AC1: S&P_Lag1 | AD1: S&P_Lag2 | AE1: S&P_Lag3 | AF1: S&P_Lag4 | AG1: S&P_Lag5 | AH1: Bond_Lag1 | AI1: Bond_Lag2 | AJ1: Bond_Lag3 | AK1: Bond_Lag4 | AL1: Bond_Lag5 | AP1: Repo Rate | AQ1: S&P 500 | AR1: 10-Year Government Bond Yield
A2: 42095 | B2: #DIV/0! | C2: #DIV/0! | D2: #DIV/0! | E2: #DIV/0! | F2: =(AP2-AP3)/AP3 -> -0.04 | G2: =(AQ2-AQ3)/AQ3 -> -0.0076249365 | H2: =(AR2-AR3)/AR3 -> -0.034954407 | AP2: 0.06 | AQ2: 5569.06 | AR2: 6.35
A3: 42125 | B3: -0.038605653 | C3: #DIV/0! | D3: -0.0086355786 | E3: #DIV/0! | F3: =(AP3-AP4)/AP4 -> 0 | G3: =(AQ3-AQ4)/AQ4 -> -0.057544714 | H3: =(AR3-AR4)/AR4 -> -0.020833333 | I3: =OFFSET(C3, -1, 0) -> #DIV/0! | K3: =OFFSET(C3, -3, 0) -> #REF! | L3: =OFFSET(C3, -4, 0) -> #REF! | M3: =OFFSET(C5, -5, 0) -> #REF! | N3: =OFFSET(D3, -1, 0) -> #DIV/0! | O3: =OFFSET(D3, -2, 0) -> Inflation change | P3: =OFFSET(D3, -3, 0) -> #REF! | Q3: =OFFSET(D3, -4, 0) -> #REF! | R3: =OFFSET(D3, -5, 0) -> #REF! | S3: =OFFSET(E3, -1, 0) -> #DIV/0! | T3: =OFFSET(E3, -2, 0) -> Currency change | U3: =OFFSET(E3, -2, 0) -> Currency change | V3: =OFFSET(E3, -4, 0) -> #REF! | W3: =OFFSET(E3, -5, 0) -> #REF! | X3: =OFFSET(F3, -1, 0) -> -0.04 | Y3: =OFFSET(F3, -2, 0) -> Change in Repo Rate | Z3: =OFFSET(F3, -3, 0) -> #REF! | AA3: =OFFSET(F3, -4, 0) -> #REF! | AB3: =OFFSET(F3, -5, 0) -> #REF! | AC3: =OFFSET(G3, -1, 0) -> -0.0076249365 | AD3: =OFFSET(G3, -2, 0) -> S&P 500 Return | AE3: =OFFSET(G3, -3, 0) -> #REF! | AF3: =OFFSET(G3, -4, 0) -> #REF! | AG3: =OFFSET(G3, -5, 0) -> #REF! | AH3: =OFFSET(H3, -1, 0) -> -0.034954407 | AI3: =OFFSET(H3, -2, 0) -> Change in Bond Yield | AJ3: =OFFSET(H3, -3, 0) -> #REF! | AK3: =OFFSET(H3, -4, 0) -> #REF! | AL3: =OFFSET(H3, -5, 0) -> #REF! | AP3: 0.0625 | AQ3: 5611.85 | AR3: 6.58 | AU3: SUMMARY OUTPUT
A4: 42156 | B4: 0.01210249 | C4: -0.01386012 | D4: 0.06271777 | E4: -0.0021809737 | F4: =(AP4-AP5)/AP5 -> -0.038461538 | G4: =(AQ4-AQ5)/AQ5 -> -0.014242128 | H4: =(AR4-AR5)/AR5 -> 0.0044843049 | I4: =OFFSET(C4, -1, 0) -> #DIV/0! | J4: =OFFSET(C4, -2, 0) -> #DIV/0! | K4: =OFFSET(C4, -3, 0) -> Crude Oil Return | L4: =OFFSET(C4, -4, 0) -> #REF! | M4: =OFFSET(C6, -5, 0) -> Crude Oil Return | N4: =OFFSET(D4, -1, 0) -> -0.0086355786 | O4: =OFFSET(D4, -2, 0) -> #DIV/0! | P4: =OFFSET(D4, -3, 0) -> Inflation change | Q4: =OFFSET(D4, -4, 0) -> #REF! | R4: =OFFSET(D4, -5, 0) -> #REF! | S4: =OFFSET(E4, -1, 0) -> #DIV/0! | T4: =OFFSET(E4, -2, 0) -> #DIV/0! | U4: =OFFSET(E4, -2, 0) -> #DIV/0! | V4: =OFFSET(E4, -4, 0) -> #REF! | W4: =OFFSET(E4, -5, 0) -> #REF! | X4: =OFFSET(F4, -1, 0) -> 0 | Y4: =OFFSET(F4, -2, 0) -> -0.04 | Z4: =OFFSET(F4, -3, 0) -> Change in Repo Rate | AA4: =OFFSET(F4, -4, 0) -> #REF! | AB4: =OFFSET(F4, -5, 0) -> #REF! | AC4: =OFFSET(G4, -1, 0) -> -0.057544714 | AD4: =OFFSET(G4, -2, 0) -> -0.0076249365 | AE4: =OFFSET(G4, -3, 0) -> S&P 500 Return | AF4: =OFFSET(G4, -4, 0) -> #REF! | AG4: =OFFSET(G4, -5, 0) -> #REF! | AH4: =OFFSET(H4, -1, 0) -> -0.020833333 | AI4: =OFFSET(H4, -2, 0) -> -0.034954407 | AJ4: =OFFSET(H4, -3, 0) -> Change in Bond Yield | AK4: =OFFSET(H4, -4, 0) -> #REF! | AL4: =OFFSET(H4, -5, 0) -> #REF! | AP4: 0.0625 | AQ4: 5954.5 | AR4: 6.72
A5: 42186 | B5: 0.0023273108 | C5: -0.23277444 | D5: -0.28360656 | E5: 0.0060383055 | F5: =(AP5-AP6)/AP6 -> 0 | G5: =(AQ5-AQ6)/AQ6 -> 0.02701632 | H5: =(AR5-AR6)/AR6 -> -0.01035503 | I5: =OFFSET(C5, -1, 0) -> -0.01386012 | J5: =OFFSET(C5, -2, 0) -> #DIV/0! | K5: =OFFSET(C5, -3, 0) -> #DIV/0! | L5: =OFFSET(C5, -4, 0) -> Crude Oil Return | M5: =OFFSET(C7, -5, 0) -> #DIV/0! | N5: =OFFSET(D5, -1, 0) -> 0.06271777 | O5: =OFFSET(D5, -2, 0) -> -0.0086355786 | P5: =OFFSET(D5, -3, 0) -> #DIV/0! | Q5: =OFFSET(D5, -4, 0) -> Inflation change | R5: =OFFSET(D5, -5, 0) -> #REF! | S5: =OFFSET(E5, -1, 0) -> -0.0021809737 | T5: =OFFSET(E5, -2, 0) -> #DIV/0! | U5: =OFFSET(E5, -2, 0) -> #DIV/0! | V5: =OFFSET(E5, -4, 0) -> Currency change | W5: =OFFSET(E5, -5, 0) -> #REF! | X5: =OFFSET(F5, -1, 0) -> -0.038461538 | Y5: =OFFSET(F5, -2, 0) -> 0 | Z5: =OFFSET(F5, -3, 0) -> -0.04 | AA5: =OFFSET(F5, -4, 0) -> Change in Repo Rate | AB5: =OFFSET(F5, -5, 0) -> #REF! | AC5: =OFFSET(G5, -1, 0) -> -0.014242128 | AD5: =OFFSET(G5, -2, 0) -> -0.057544714 | AE5: =OFFSET(G5, -3, 0) -> -0.0076249365 | AF5: =OFFSET(G5, -4, 0) -> S&P 500 Return | AG5: =OFFSET(G5, -5, 0) -> #REF! | AH5: =OFFSET(H5, -1, 0) -> 0.0044843049 | AI5: =OFFSET(H5, -2, 0) -> -0.020833333 | AJ5: =OFFSET(H5, -3, 0) -> -0.034954407 | AK5: =OFFSET(H5, -4, 0) -> Change in Bond Yield | AL5: =OFFSET(H5, -5, 0) -> #REF! | AP5: 0.065 | AQ5: 6040.53 | AR5: 6.69 | AU5: Regression Statistics
A6: 42217 | B6: 0.010590764 | C6: 0.043196084 | D6: -0.004576659 | E6: 0.037888024 | F6: =(AP6-AP7)/AP7 -> 0 | G6: =(AQ6-AQ7)/AQ7 -> -0.024990137 | H6: =(AR6-AR7)/AR7 -> 0.0013331358 | I6: =OFFSET(C6, -1, 0) -> -0.23277444 | J6: =OFFSET(C6, -2, 0) -> -0.01386012 | K6: =OFFSET(C6, -3, 0) -> #DIV/0! | L6: =OFFSET(C6, -4, 0) -> #DIV/0! | M6: =OFFSET(C8, -5, 0) -> #DIV/0! | N6: =OFFSET(D6, -1, 0) -> -0.28360656 | O6: =OFFSET(D6, -2, 0) -> 0.06271777 | P6: =OFFSET(D6, -3, 0) -> -0.0086355786 | Q6: =OFFSET(D6, -4, 0) -> #DIV/0! | R6: =OFFSET(D6, -5, 0) -> Inflation change | S6: =OFFSET(E6, -1, 0) -> 0.0060383055 | T6: =OFFSET(E6, -2, 0) -> -0.0021809737 | U6: =OFFSET(E6, -2, 0) -> -0.0021809737 | V6: =OFFSET(E6, -4, 0) -> #DIV/0! | W6: =OFFSET(E6, -5, 0) -> Currency change | X6: =OFFSET(F6, -1, 0) -> 0 | Y6: =OFFSET(F6, -2, 0) -> -0.038461538 | Z6: =OFFSET(F6, -3, 0) -> 0 | AA6: =OFFSET(F6, -4, 0) -> -0.04 | AB6: =OFFSET(F6, -5, 0) -> Change in Repo Rate | AC6: =OFFSET(G6, -1, 0) -> 0.02701632 | AD6: =OFFSET(G6, -2, 0) -> -0.014242128 | AE6: =OFFSET(G6, -3, 0) -> -0.057544714 | AF6: =OFFSET(G6, -4, 0) -> -0.0076249365 | AG6: =OFFSET(G6, -5, 0) -> S&P 500 Return | AH6: =OFFSET(H6, -1, 0) -> -0.01035503 | AI6: =OFFSET(H6, -2, 0) -> 0.0044843049 | AJ6: =OFFSET(H6, -3, 0) -> -0.020833333 | AK6: =OFFSET(H6, -4, 0) -> -0.034954407 | AL6: =OFFSET(H6, -5, 0) -> Change in Bond Yield | AP6: 0.065 | AQ6: 5881.63 | AR6: 6.76 | AU6: Multiple R | AV6: 0.49097549
A7: 42248 | B7: -0.092810103 | C7: -0.087233131 | D7: 0.1816092 | E7: -0.01347851 | F7: =(AP7-AP8)/AP8 -> 0 | G7: =(AQ7-AQ8)/AQ8 -> 0.057301352 | H7: =(AR7-AR8)/AR8 -> -0.013155971 | I7: =OFFSET(C7, -1, 0) -> 0.043196084 | J7: =OFFSET(C7, -2, 0) -> -0.23277444 | K7: =OFFSET(C7, -3, 0) -> -0.01386012 | L7: =OFFSET(C7, -4, 0) -> #DIV/0! | M7: =OFFSET(C9, -5, 0) -> -0.01386012 | N7: =OFFSET(D7, -1, 0) -> -0.004576659 | O7: =OFFSET(D7, -2, 0) -> -0.28360656 | P7: =OFFSET(D7, -3, 0) -> 0.06271777 | Q7: =OFFSET(D7, -4, 0) -> -0.0086355786 | R7: =OFFSET(D7, -5, 0) -> #DIV/0! | S7: =OFFSET(E7, -1, 0) -> 0.037888024 | T7: =OFFSET(E7, -2, 0) -> 0.0060383055 | U7: =OFFSET(E7, -2, 0) -> 0.0060383055 | V7: =OFFSET(E7, -4, 0) -> #DIV/0! | W7: =OFFSET(E7, -5, 0) -> #DIV/0! | X7: =OFFSET(F7, -1, 0) -> 0 | Y7: =OFFSET(F7, -2, 0) -> 0 | Z7: =OFFSET(F7, -3, 0) -> -0.038461538 | AA7: =OFFSET(F7, -4, 0) -> 0 | AB7: =OFFSET(F7, -5, 0) -> -0.04 | AC7: =OFFSET(G7, -1, 0) -> -0.024990137 | AD7: =OFFSET(G7, -2, 0) -> 0.02701632 | AE7: =OFFSET(G7, -3, 0) -> -0.014242128 | AF7: =OFFSET(G7, -4, 0) -> -0.057544714 | AG7: =OFFSET(G7, -5, 0) -> -0.0076249365 | AH7: =OFFSET(H7, -1, 0) -> 0.0013331358 | AI7: =OFFSET(H7, -2, 0) -> -0.01035503 | AJ7: =OFFSET(H7, -3, 0) -> 0.0044843049 | AK7: =OFFSET(H7, -4, 0) -> -0.020833333 | AL7: =OFFSET(H7, -5, 0) -> -0.034954407 | AP7: 0.065 | AQ7: 6032.38 | AR7: 6.751 | AU7: R Square | AV7: 0.24105693
A8: 42278 | B8: 0.020977146 | C8: 0.032725433 | D8: 0.22957198 | E8: -0.0014349611 | F8: =(AP8-AP9)/AP9 -> 0 | G8: =(AQ8-AQ9)/AQ9 -> -0.0098967806 | H8: =(AR8-AR9)/AR9 -> 0.013481481 | I8: =OFFSET(C8, -1, 0) -> -0.087233131 | J8: =OFFSET(C8, -2, 0) -> 0.043196084 | K8: =OFFSET(C8, -3, 0) -> -0.23277444 | L8: =OFFSET(C8, -4, 0) -> -0.01386012 | M8: =OFFSET(C10, -5, 0) -> -0.23277444 | N8: =OFFSET(D8, -1, 0) -> 0.1816092 | O8: =OFFSET(D8, -2, 0) -> -0.004576659 | P8: =OFFSET(D8, -3, 0) -> -0.28360656 | Q8: =OFFSET(D8, -4, 0) -> 0.06271777 | R8: =OFFSET(D8, -5, 0) -> -0.0086355786 | S8: =OFFSET(E8, -1, 0) -> -0.01347851 | T8: =OFFSET(E8, -2, 0) -> 0.037888024 | U8: =OFFSET(E8, -2, 0) -> 0.037888024 | V8: =OFFSET(E8, -4, 0) -> -0.0021809737 | W8: =OFFSET(E8, -5, 0) -> #DIV/0! | X8: =OFFSET(F8, -1, 0) -> 0 | Y8: =OFFSET(F8, -2, 0) -> 0 | Z8: =OFFSET(F8, -3, 0) -> 0 | AA8: =OFFSET(F8, -4, 0) -> -0.038461538 | AB8: =OFFSET(F8, -5, 0) -> 0 | AC8: =OFFSET(G8, -1, 0) -> 0.057301352 | AD8: =OFFSET(G8, -2, 0) -> -0.024990137 | AE8: =OFFSET(G8, -3, 0) -> 0.02701632 | AF8: =OFFSET(G8, -4, 0) -> -0.014242128 | AG8: =OFFSET(G8, -5, 0) -> -0.057544714 | AH8: =OFFSET(H8, -1, 0) -> -0.013155971 | AI8: =OFFSET(H8, -2, 0) -> 0.0013331358 | AJ8: =OFFSET(H8, -3, 0) -> -0.01035503 | AK8: =OFFSET(H8, -4, 0) -> 0.0044843049 | AL8: =OFFSET(H8, -5, 0) -> -0.020833333 | AP8: 0.065 | AQ8: 5705.45 | AR8: 6.841 | AU8: Adjusted R Square | AV8: 0.18871603
A9: 42309 | B9: 0.012486336 | C9: -0.11208456 | D9: 0.063291139 | E9: 0.015883693 | F9: =(AP9-AP10)/AP10 -> 0 | G9: =(AQ9-AQ10)/AQ10 -> 0.02019687 | H9: =(AR9-AR10)/AR10 -> -0.016465103 | I9: =OFFSET(C9, -1, 0) -> 0.032725433 | J9: =OFFSET(C9, -2, 0) -> -0.087233131 | K9: =OFFSET(C9, -3, 0) -> 0.043196084 | L9: =OFFSET(C9, -4, 0) -> -0.23277444 | M9: =OFFSET(C11, -5, 0) -> 0.043196084 | N9: =OFFSET(D9, -1, 0) -> 0.22957198 | O9: =OFFSET(D9, -2, 0) -> 0.1816092 | P9: =OFFSET(D9, -3, 0) -> -0.004576659 | Q9: =OFFSET(D9, -4, 0) -> -0.28360656 | R9: =OFFSET(D9, -5, 0) -> 0.06271777 | S9: =OFFSET(E9, -1, 0) -> -0.0014349611 | T9: =OFFSET(E9, -2, 0) -> -0.01347851 | U9: =OFFSET(E9, -2, 0) -> -0.01347851 | V9: =OFFSET(E9, -4, 0) -> 0.0060383055 | W9: =OFFSET(E9, -5, 0) -> -0.0021809737 | X9: =OFFSET(F9, -1, 0) -> 0 | Y9: =OFFSET(F9, -2, 0) -> 0 | Z9: =OFFSET(F9, -3, 0) -> 0 | AA9: =OFFSET(F9, -4, 0) -> 0 | AB9: =OFFSET(F9, -5, 0) -> -0.038461538 | AC9: =OFFSET(G9, -1, 0) -> -0.0098967806 | AD9: =OFFSET(G9, -2, 0) -> 0.057301352 | AE9: =OFFSET(G9, -3, 0) -> -0.024990137 | AF9: =OFFSET(G9, -4, 0) -> 0.02701632 | AG9: =OFFSET(G9, -5, 0) -> -0.014242128 | AH9: =OFFSET(H9, -1, 0) -> 0.013481481 | AI9: =OFFSET(H9, -2, 0) -> -0.013155971 | AJ9: =OFFSET(H9, -3, 0) -> 0.0013331358 | AK9: =OFFSET(H9, -4, 0) -> -0.01035503 | AL9: =OFFSET(H9, -5, 0) -> 0.0044843049 | AP9: 0.065 | AQ9: 5762.48 | AR9: 6.75 | AU9: Standard Error | AV9: 0.047368514
A10: 42339 | B10: -0.011983374 | C10: -0.11730296 | D10: -0.05952381 | E10: -0.0038223078 | F10: =(AP10-AP11)/AP11 -> 0 | G10: =(AQ10-AQ11)/AQ11 -> 0.022834688 | H10: =(AR10-AR11)/AR11 -> -0.0088099365 | I10: =OFFSET(C10, -1, 0) -> -0.11208456 | J10: =OFFSET(C10, -2, 0) -> 0.032725433 | K10: =OFFSET(C10, -3, 0) -> -0.087233131 | L10: =OFFSET(C10, -4, 0) -> 0.043196084 | M10: =OFFSET(C12, -5, 0) -> -0.087233131 | N10: =OFFSET(D10, -1, 0) -> 0.063291139 | O10: =OFFSET(D10, -2, 0) -> 0.22957198 | P10: =OFFSET(D10, -3, 0) -> 0.1816092 | Q10: =OFFSET(D10, -4, 0) -> -0.004576659 | R10: =OFFSET(D10, -5, 0) -> -0.28360656 | S10: =OFFSET(E10, -1, 0) -> 0.015883693 | T10: =OFFSET(E10, -2, 0) -> -0.0014349611 | U10: =OFFSET(E10, -2, 0) -> -0.0014349611 | V10: =OFFSET(E10, -4, 0) -> 0.037888024 | W10: =OFFSET(E10, -5, 0) -> 0.0060383055 | X10: =OFFSET(F10, -1, 0) -> 0 | Y10: =OFFSET(F10, -2, 0) -> 0 | Z10: =OFFSET(F10, -3, 0) -> 0 | AA10: =OFFSET(F10, -4, 0) -> 0 | AB10: =OFFSET(F10, -5, 0) -> 0 | AC10: =OFFSET(G10, -1, 0) -> 0.02019687 | AD10: =OFFSET(G10, -2, 0) -> -0.0098967806 | AE10: =OFFSET(G10, -3, 0) -> 0.057301352 | AF10: =OFFSET(G10, -4, 0) -> -0.024990137 | AG10: =OFFSET(G10, -5, 0) -> 0.02701632 | AH10: =OFFSET(H10, -1, 0) -> -0.016465103 | AI10: =OFFSET(H10, -2, 0) -> 0.013481481 | AJ10: =OFFSET(H10, -3, 0) -> -0.013155971 | AK10: =OFFSET(H10, -4, 0) -> 0.0013331358 | AL10: =OFFSET(H10, -5, 0) -> -0.01035503 | AP10: 0.065 | AQ10: 5648.4 | AR10: 6.863 | AU10: Observations | AV10: 94
A11: 42370 | B11: 0.0010428381 | C11: -0.096877282 | D11: -0.064873418 | E11: 0.025227348 | F11: =(AP11-AP12)/AP12 -> 0 | G11: =(AQ11-AQ12)/AQ12 -> 0.011321349 | H11: =(AR11-AR12)/AR12 -> -0.011986301 | I11: =OFFSET(C11, -1, 0) -> -0.11730296 | J11: =OFFSET(C11, -2, 0) -> -0.11208456 | K11: =OFFSET(C11, -3, 0) -> 0.032725433 | L11: =OFFSET(C11, -4, 0) -> -0.087233131 | M11: =OFFSET(C13, -5, 0) -> 0.032725433 | N11: =OFFSET(D11, -1, 0) -> -0.05952381 | O11: =OFFSET(D11, -2, 0) -> 0.063291139 | P11: =OFFSET(D11, -3, 0) -> 0.22957198 | Q11: =OFFSET(D11, -4, 0) -> 0.1816092 | R11: =OFFSET(D11, -5, 0) -> -0.004576659 | S11: =OFFSET(E11, -1, 0) -> -0.0038223078 | T11: =OFFSET(E11, -2, 0) -> 0.015883693 | U11: =OFFSET(E11, -2, 0) -> 0.015883693 | V11: =OFFSET(E11, -4, 0) -> -0.01347851 | W11: =OFFSET(E11, -5, 0) -> 0.037888024 | X11: =OFFSET(F11, -1, 0) -> 0 | Y11: =OFFSET(F11, -2, 0) -> 0 | Z11: =OFFSET(F11, -3, 0) -> 0 | AA11: =OFFSET(F11, -4, 0) -> 0 | AB11: =OFFSET(F11, -5, 0) -> 0 | AC11: =OFFSET(G11, -1, 0) -> 0.022834688 | AD11: =OFFSET(G11, -2, 0) -> 0.02019687 | AE11: =OFFSET(G11, -3, 0) -> -0.0098967806 | AF11: =OFFSET(G11, -4, 0) -> 0.057301352 | AG11: =OFFSET(G11, -5, 0) -> -0.024990137 | AH11: =OFFSET(H11, -1, 0) -> -0.0088099365 | AI11: =OFFSET(H11, -2, 0) -> -0.016465103 | AJ11: =OFFSET(H11, -3, 0) -> 0.013481481 | AK11: =OFFSET(H11, -4, 0) -> -0.013155971 | AL11: =OFFSET(H11, -5, 0) -> 0.0013331358 | AP11: 0.065 | AQ11: 5522.3 | AR11: 6.924
A12: 42401 | B12: -0.052495597 | C12: 0.0038592893 | D12: -0.0642978 | E12: 0.0048623799 | F12: =(AP12-AP13)/AP13 -> 0 | G12: =(AQ12-AQ13)/AQ13 -> 0.034669759 | H12: =(AR12-AR13)/AR13 -> 0.0031491555 | I12: =OFFSET(C12, -1, 0) -> -0.096877282 | J12: =OFFSET(C12, -2, 0) -> -0.11730296 | K12: =OFFSET(C12, -3, 0) -> -0.11208456 | L12: =OFFSET(C12, -4, 0) -> 0.032725433 | M12: =OFFSET(C14, -5, 0) -> -0.11208456 | N12: =OFFSET(D12, -1, 0) -> -0.064873418 | O12: =OFFSET(D12, -2, 0) -> -0.05952381 | P12: =OFFSET(D12, -3, 0) -> 0.063291139 | Q12: =OFFSET(D12, -4, 0) -> 0.22957198 | R12: =OFFSET(D12, -5, 0) -> 0.1816092 | S12: =OFFSET(E12, -1, 0) -> 0.025227348 | T12: =OFFSET(E12, -2, 0) -> -0.0038223078 | U12: =OFFSET(E12, -2, 0) -> -0.0038223078 | V12: =OFFSET(E12, -4, 0) -> -0.0014349611 | W12: =OFFSET(E12, -5, 0) -> -0.01347851 | X12: =OFFSET(F12, -1, 0) -> 0 | Y12: =OFFSET(F12, -2, 0) -> 0 | Z12: =OFFSET(F12, -3, 0) -> 0 | AA12: =OFFSET(F12, -4, 0) -> 0 | AB12: =OFFSET(F12, -5, 0) -> 0 | AC12: =OFFSET(G12, -1, 0) -> 0.011321349 | AD12: =OFFSET(G12, -2, 0) -> 0.022834688 | AE12: =OFFSET(G12, -3, 0) -> 0.02019687 | AF12: =OFFSET(G12, -4, 0) -> -0.0098967806 | AG12: =OFFSET(G12, -5, 0) -> 0.057301352 | AH12: =OFFSET(H12, -1, 0) -> -0.011986301 | AI12: =OFFSET(H12, -2, 0) -> -0.0088099365 | AJ12: =OFFSET(H12, -3, 0) -> -0.016465103 | AK12: =OFFSET(H12, -4, 0) -> 0.013481481 | AL12: =OFFSET(H12, -5, 0) -> -0.013155971 | AP12: 0.065 | AQ12: 5460.48 | AR12: 7.008 | AU12: ANOVA
A13: 42430 | B13: -0.045161871 | C13: 0.12751332 | D13: -0.0036166365 | E13: -0.028563888 | F13: =(AP13-AP14)/AP14 -> 0 | G13: =(AQ13-AQ14)/AQ14 -> 0.048021224 | H13: =(AR13-AR14)/AR14 -> -0.02904795 | I13: =OFFSET(C13, -1, 0) -> 0.0038592893 | J13: =OFFSET(C13, -2, 0) -> -0.096877282 | K13: =OFFSET(C13, -3, 0) -> -0.11730296 | L13: =OFFSET(C13, -4, 0) -> -0.11208456 | M13: =OFFSET(C15, -5, 0) -> -0.11730296 | N13: =OFFSET(D13, -1, 0) -> -0.0642978 | O13: =OFFSET(D13, -2, 0) -> -0.064873418 | P13: =OFFSET(D13, -3, 0) -> -0.05952381 | Q13: =OFFSET(D13, -4, 0) -> 0.063291139 | R13: =OFFSET(D13, -5, 0) -> 0.22957198 | S13: =OFFSET(E13, -1, 0) -> 0.0048623799 | T13: =OFFSET(E13, -2, 0) -> 0.025227348 | U13: =OFFSET(E13, -2, 0) -> 0.025227348 | V13: =OFFSET(E13, -4, 0) -> 0.015883693 | W13: =OFFSET(E13, -5, 0) -> -0.0014349611 | X13: =OFFSET(F13, -1, 0) -> 0 | Y13: =OFFSET(F13, -2, 0) -> 0 | Z13: =OFFSET(F13, -3, 0) -> 0 | AA13: =OFFSET(F13, -4, 0) -> 0 | AB13: =OFFSET(F13, -5, 0) -> 0 | AC13: =OFFSET(G13, -1, 0) -> 0.034669759 | AD13: =OFFSET(G13, -2, 0) -> 0.011321349 | AE13: =OFFSET(G13, -3, 0) -> 0.022834688 | AF13: =OFFSET(G13, -4, 0) -> 0.02019687 | AG13: =OFFSET(G13, -5, 0) -> -0.0098967806 | AH13: =OFFSET(H13, -1, 0) -> 0.0031491555 | AI13: =OFFSET(H13, -2, 0) -> -0.011986301 | AJ13: =OFFSET(H13, -3, 0) -> -0.0088099365 | AK13: =OFFSET(H13, -4, 0) -> -0.016465103 | AL13: =OFFSET(H13, -5, 0) -> 0.013481481 | AP13: 0.065 | AQ13: 5277.51 | AR13: 6.986 | AV13: df | AW13: SS | AX13: MS | AY13: F | AZ13: Significance F
A14: 42461 | B14: 0.065740238 | C14: 0.18040701 | D14: 0.063520871 | E14: 0.002490566 | F14: =(AP14-AP15)/AP15 -> 0 | G14: =(AQ14-AQ15)/AQ15 -> -0.041615043 | H14: =(AR14-AR15)/AR15 -> 0.020277935 | I14: =OFFSET(C14, -1, 0) -> 0.12751332 | J14: =OFFSET(C14, -2, 0) -> 0.0038592893 | K14: =OFFSET(C14, -3, 0) -> -0.096877282 | L14: =OFFSET(C14, -4, 0) -> -0.11730296 | M14: =OFFSET(C16, -5, 0) -> -0.096877282 | N14: =OFFSET(D14, -1, 0) -> -0.0036166365 | O14: =OFFSET(D14, -2, 0) -> -0.0642978 | P14: =OFFSET(D14, -3, 0) -> -0.064873418 | Q14: =OFFSET(D14, -4, 0) -> -0.05952381 | R14: =OFFSET(D14, -5, 0) -> 0.063291139 | S14: =OFFSET(E14, -1, 0) -> -0.028563888 | T14: =OFFSET(E14, -2, 0) -> 0.0048623799 | U14: =OFFSET(E14, -2, 0) -> 0.0048623799 | V14: =OFFSET(E14, -4, 0) -> -0.0038223078 | W14: =OFFSET(E14, -5, 0) -> 0.015883693 | X14: =OFFSET(F14, -1, 0) -> 0 | Y14: =OFFSET(F14, -2, 0) -> 0 | Z14: =OFFSET(F14, -3, 0) -> 0 | AA14: =OFFSET(F14, -4, 0) -> 0 | AB14: =OFFSET(F14, -5, 0) -> 0 | AC14: =OFFSET(G14, -1, 0) -> 0.048021224 | AD14: =OFFSET(G14, -2, 0) -> 0.034669759 | AE14: =OFFSET(G14, -3, 0) -> 0.011321349 | AF14: =OFFSET(G14, -4, 0) -> 0.022834688 | AG14: =OFFSET(G14, -5, 0) -> 0.02019687 | AH14: =OFFSET(H14, -1, 0) -> -0.02904795 | AI14: =OFFSET(H14, -2, 0) -> 0.0031491555 | AJ14: =OFFSET(H14, -3, 0) -> -0.011986301 | AK14: =OFFSET(H14, -4, 0) -> -0.0088099365 | AL14: =OFFSET(H14, -5, 0) -> -0.016465103 | AP14: 0.065 | AQ14: 5035.69 | AR14: 7.195 | AU14: Regression | AV14: 6 | AW14: 0.0620025 | AX14: 0.01033375 | AY14: 4.6055174 | AZ14: 0.00041674116
A15: 42491 | B15: 0.011966159 | C15: 0.066958283 | D15: 0.12457338 | E15: 0.011804562 | F15: =(AP15-AP16)/AP16 -> 0 | G15: =(AQ15-AQ16)/AQ16 -> 0.031018765 | H15: =(AR15-AR16)/AR16 -> -0.0036733541 | I15: =OFFSET(C15, -1, 0) -> 0.18040701 | J15: =OFFSET(C15, -2, 0) -> 0.12751332 | K15: =OFFSET(C15, -3, 0) -> 0.0038592893 | L15: =OFFSET(C15, -4, 0) -> -0.096877282 | M15: =OFFSET(C17, -5, 0) -> 0.0038592893 | N15: =OFFSET(D15, -1, 0) -> 0.063520871 | O15: =OFFSET(D15, -2, 0) -> -0.0036166365 | P15: =OFFSET(D15, -3, 0) -> -0.0642978 | Q15: =OFFSET(D15, -4, 0) -> -0.064873418 | R15: =OFFSET(D15, -5, 0) -> -0.05952381 | S15: =OFFSET(E15, -1, 0) -> 0.002490566 | T15: =OFFSET(E15, -2, 0) -> -0.028563888 | U15: =OFFSET(E15, -2, 0) -> -0.028563888 | V15: =OFFSET(E15, -4, 0) -> 0.025227348 | W15: =OFFSET(E15, -5, 0) -> -0.0038223078 | X15: =OFFSET(F15, -1, 0) -> 0 | Y15: =OFFSET(F15, -2, 0) -> 0 | Z15: =OFFSET(F15, -3, 0) -> 0 | AA15: =OFFSET(F15, -4, 0) -> 0 | AB15: =OFFSET(F15, -5, 0) -> 0 | AC15: =OFFSET(G15, -1, 0) -> -0.041615043 | AD15: =OFFSET(G15, -2, 0) -> 0.048021224 | AE15: =OFFSET(G15, -3, 0) -> 0.034669759 | AF15: =OFFSET(G15, -4, 0) -> 0.011321349 | AG15: =OFFSET(G15, -5, 0) -> 0.022834688 | AH15: =OFFSET(H15, -1, 0) -> 0.020277935 | AI15: =OFFSET(H15, -2, 0) -> -0.02904795 | AJ15: =OFFSET(H15, -3, 0) -> 0.0031491555 | AK15: =OFFSET(H15, -4, 0) -> -0.011986301 | AL15: =OFFSET(H15, -5, 0) -> -0.0088099365 | AP15: 0.065 | AQ15: 5254.35 | AR15: 7.052 | AU15: Residual | AV15: 87 | AW15: 0.19520852 | AX15: 0.0022437761
A16: 42522 | B16: 0.04680618 | C16: -0.015806549 | D16: -0.069802731 | E16: 0.0043750651 | F16: =(AP16-AP17)/AP17 -> 0 | G16: =(AQ16-AQ17)/AQ17 -> 0.051720615 | H16: =(AR16-AR17)/AR17 -> -0.0092385218 | I16: =OFFSET(C16, -1, 0) -> 0.066958283 | J16: =OFFSET(C16, -2, 0) -> 0.18040701 | K16: =OFFSET(C16, -3, 0) -> 0.12751332 | L16: =OFFSET(C16, -4, 0) -> 0.0038592893 | M16: =OFFSET(C18, -5, 0) -> 0.12751332 | N16: =OFFSET(D16, -1, 0) -> 0.12457338 | O16: =OFFSET(D16, -2, 0) -> 0.063520871 | P16: =OFFSET(D16, -3, 0) -> -0.0036166365 | Q16: =OFFSET(D16, -4, 0) -> -0.0642978 | R16: =OFFSET(D16, -5, 0) -> -0.064873418 | S16: =OFFSET(E16, -1, 0) -> 0.011804562 | T16: =OFFSET(E16, -2, 0) -> 0.002490566 | U16: =OFFSET(E16, -2, 0) -> 0.002490566 | V16: =OFFSET(E16, -4, 0) -> 0.0048623799 | W16: =OFFSET(E16, -5, 0) -> 0.025227348 | X16: =OFFSET(F16, -1, 0) -> 0 | Y16: =OFFSET(F16, -2, 0) -> 0 | Z16: =OFFSET(F16, -3, 0) -> 0 | AA16: =OFFSET(F16, -4, 0) -> 0 | AB16: =OFFSET(F16, -5, 0) -> 0 | AC16: =OFFSET(G16, -1, 0) -> 0.031018765 | AD16: =OFFSET(G16, -2, 0) -> -0.041615043 | AE16: =OFFSET(G16, -3, 0) -> 0.048021224 | AF16: =OFFSET(G16, -4, 0) -> 0.034669759 | AG16: =OFFSET(G16, -5, 0) -> 0.011321349 | AH16: =OFFSET(H16, -1, 0) -> -0.0036733541 | AI16: =OFFSET(H16, -2, 0) -> 0.020277935 | AJ16: =OFFSET(H16, -3, 0) -> -0.02904795 | AK16: =OFFSET(H16, -4, 0) -> 0.0031491555 | AL16: =OFFSET(H16, -5, 0) -> -0.011986301 | AP16: 0.065 | AQ16: 5096.27 | AR16: 7.078 | AU16: Total | AV16: 93 | AW16: 0.25721102
A17: 42552 | B17: 0.017979319 | C17: -0.14995232 | D17: 0.053833605 | E17: -0.012786511 | F17: =(AP17-AP18)/AP18 -> 0 | G17: =(AQ17-AQ18)/AQ18 -> 0.015895745 | H17: =(AR17-AR18)/AR18 -> -0.0044593088 | I17: =OFFSET(C17, -1, 0) -> -0.015806549 | J17: =OFFSET(C17, -2, 0) -> 0.066958283 | K17: =OFFSET(C17, -3, 0) -> 0.18040701 | L17: =OFFSET(C17, -4, 0) -> 0.12751332 | M17: =OFFSET(C19, -5, 0) -> 0.18040701 | N17: =OFFSET(D17, -1, 0) -> -0.069802731 | O17: =OFFSET(D17, -2, 0) -> 0.12457338 | P17: =OFFSET(D17, -3, 0) -> 0.063520871 | Q17: =OFFSET(D17, -4, 0) -> -0.0036166365 | R17: =OFFSET(D17, -5, 0) -> -0.0642978 | S17: =OFFSET(E17, -1, 0) -> 0.0043750651 | T17: =OFFSET(E17, -2, 0) -> 0.011804562 | U17: =OFFSET(E17, -2, 0) -> 0.011804562 | V17: =OFFSET(E17, -4, 0) -> -0.028563888 | W17: =OFFSET(E17, -5, 0) -> 0.0048623799 | X17: =OFFSET(F17, -1, 0) -> 0 | Y17: =OFFSET(F17, -2, 0) -> 0 | Z17: =OFFSET(F17, -3, 0) -> 0 | AA17: =OFFSET(F17, -4, 0) -> 0 | AB17: =OFFSET(F17, -5, 0) -> 0 | AC17: =OFFSET(G17, -1, 0) -> 0.051720615 | AD17: =OFFSET(G17, -2, 0) -> 0.031018765 | AE17: =OFFSET(G17, -3, 0) -> -0.041615043 | AF17: =OFFSET(G17, -4, 0) -> 0.048021224 | AG17: =OFFSET(G17, -5, 0) -> 0.034669759 | AH17: =OFFSET(H17, -1, 0) -> -0.0092385218 | AI17: =OFFSET(H17, -2, 0) -> -0.0036733541 | AJ17: =OFFSET(H17, -3, 0) -> 0.020277935 | AK17: =OFFSET(H17, -4, 0) -> -0.02904795 | AL17: =OFFSET(H17, -5, 0) -> 0.0031491555 | AP17: 0.065 | AQ17: 4845.65 | AR17: 7.144
A18: 42583 | B18: 0.03633784 | C18: 0.071873334 | D18: -0.17956656 | E18: 0.0049977488 | F18: =(AP18-AP19)/AP19 -> 0 | G18: =(AQ18-AQ19)/AQ19 -> 0.044229169 | H18: =(AR18-AR19)/AR19 -> -0.014150295 | I18: =OFFSET(C18, -1, 0) -> -0.14995232 | J18: =OFFSET(C18, -2, 0) -> -0.015806549 | K18: =OFFSET(C18, -3, 0) -> 0.066958283 | L18: =OFFSET(C18, -4, 0) -> 0.18040701 | M18: =OFFSET(C20, -5, 0) -> 0.066958283 | N18: =OFFSET(D18, -1, 0) -> 0.053833605 | O18: =OFFSET(D18, -2, 0) -> -0.069802731 | P18: =OFFSET(D18, -3, 0) -> 0.12457338 | Q18: =OFFSET(D18, -4, 0) -> 0.063520871 | R18: =OFFSET(D18, -5, 0) -> -0.0036166365 | S18: =OFFSET(E18, -1, 0) -> -0.012786511 | T18: =OFFSET(E18, -2, 0) -> 0.0043750651 | U18: =OFFSET(E18, -2, 0) -> 0.0043750651 | V18: =OFFSET(E18, -4, 0) -> 0.002490566 | W18: =OFFSET(E18, -5, 0) -> -0.028563888 | X18: =OFFSET(F18, -1, 0) -> 0 | Y18: =OFFSET(F18, -2, 0) -> 0 | Z18: =OFFSET(F18, -3, 0) -> 0 | AA18: =OFFSET(F18, -4, 0) -> 0 | AB18: =OFFSET(F18, -5, 0) -> 0 | AC18: =OFFSET(G18, -1, 0) -> 0.015895745 | AD18: =OFFSET(G18, -2, 0) -> 0.051720615 | AE18: =OFFSET(G18, -3, 0) -> 0.031018765 | AF18: =OFFSET(G18, -4, 0) -> -0.041615043 | AG18: =OFFSET(G18, -5, 0) -> 0.048021224 | AH18: =OFFSET(H18, -1, 0) -> -0.0044593088 | AI18: =OFFSET(H18, -2, 0) -> -0.0092385218 | AJ18: =OFFSET(H18, -3, 0) -> -0.0036733541 | AK18: =OFFSET(H18, -4, 0) -> 0.020277935 | AL18: =OFFSET(H18, -5, 0) -> -0.02904795 | AP18: 0.065 | AQ18: 4769.83 | AR18: 7.176 | AV18: Coefficients | AW18: Standard Error | AX18: t Stat | AY18: P-value | AZ18: Lower 95% | BA18: Upper 95% | BB18: Lower 95.0% | BC18: Upper 95.0%
A19: 42614 | B19: 0.015863685 | C19: 0.076215051 | D19: -0.21886792 | E19: -0.0062273196 | F19: =(AP19-AP20)/AP20 -> 0 | G19: =(AQ19-AQ20)/AQ20 -> 0.089179265 | H19: =(AR19-AR20)/AR20 -> -0.0097945858 | I19: =OFFSET(C19, -1, 0) -> 0.071873334 | J19: =OFFSET(C19, -2, 0) -> -0.14995232 | K19: =OFFSET(C19, -3, 0) -> -0.015806549 | L19: =OFFSET(C19, -4, 0) -> 0.066958283 | M19: =OFFSET(C21, -5, 0) -> -0.015806549 | N19: =OFFSET(D19, -1, 0) -> -0.17956656 | O19: =OFFSET(D19, -2, 0) -> 0.053833605 | P19: =OFFSET(D19, -3, 0) -> -0.069802731 | Q19: =OFFSET(D19, -4, 0) -> 0.12457338 | R19: =OFFSET(D19, -5, 0) -> 0.063520871 | S19: =OFFSET(E19, -1, 0) -> 0.0049977488 | T19: =OFFSET(E19, -2, 0) -> -0.012786511 | U19: =OFFSET(E19, -2, 0) -> -0.012786511 | V19: =OFFSET(E19, -4, 0) -> 0.011804562 | W19: =OFFSET(E19, -5, 0) -> 0.002490566 | X19: =OFFSET(F19, -1, 0) -> 0 | Y19: =OFFSET(F19, -2, 0) -> 0 | Z19: =OFFSET(F19, -3, 0) -> 0 | AA19: =OFFSET(F19, -4, 0) -> 0 | AB19: =OFFSET(F19, -5, 0) -> 0 | AC19: =OFFSET(G19, -1, 0) -> 0.044229169 | AD19: =OFFSET(G19, -2, 0) -> 0.015895745 | AE19: =OFFSET(G19, -3, 0) -> 0.051720615 | AF19: =OFFSET(G19, -4, 0) -> 0.031018765 | AG19: =OFFSET(G19, -5, 0) -> -0.041615043 | AH19: =OFFSET(H19, -1, 0) -> -0.014150295 | AI19: =OFFSET(H19, -2, 0) -> -0.0044593088 | AJ19: =OFFSET(H19, -3, 0) -> -0.0092385218 | AK19: =OFFSET(H19, -4, 0) -> -0.0036733541 | AL19: =OFFSET(H19, -5, 0) -> 0.020277935 | AP19: 0.065 | AQ19: 4567.8 | AR19: 7.279 | AU19: Intercept | AV19: 0.010387117 | AW19: 0.0051842674 | AX19: 2.0035843 | AY19: 0.048226241 | AZ19: 8.2823882e-05 | BA19: 0.020691409 | BB19: 8.2823882e-05 | BC19: 0.020691409
A20: 42644 | B20: -0.0041741078 | C20: -0.029024119 | D20: -0.19082126 | E20: 0.0019385087 | F20: =(AP20-AP21)/AP21 -> 0 | G20: =(AQ20-AQ21)/AQ21 -> -0.021979688 | H20: =(AR20-AR21)/AR21 -> 0.019556172 | I20: =OFFSET(C20, -1, 0) -> 0.076215051 | J20: =OFFSET(C20, -2, 0) -> 0.071873334 | K20: =OFFSET(C20, -3, 0) -> -0.14995232 | L20: =OFFSET(C20, -4, 0) -> -0.015806549 | M20: =OFFSET(C22, -5, 0) -> -0.14995232 | N20: =OFFSET(D20, -1, 0) -> -0.21886792 | O20: =OFFSET(D20, -2, 0) -> -0.17956656 | P20: =OFFSET(D20, -3, 0) -> 0.053833605 | Q20: =OFFSET(D20, -4, 0) -> -0.069802731 | R20: =OFFSET(D20, -5, 0) -> 0.12457338 | S20: =OFFSET(E20, -1, 0) -> -0.0062273196 | T20: =OFFSET(E20, -2, 0) -> 0.0049977488 | U20: =OFFSET(E20, -2, 0) -> 0.0049977488 | V20: =OFFSET(E20, -4, 0) -> 0.0043750651 | W20: =OFFSET(E20, -5, 0) -> 0.011804562 | X20: =OFFSET(F20, -1, 0) -> 0 | Y20: =OFFSET(F20, -2, 0) -> 0 | Z20: =OFFSET(F20, -3, 0) -> 0 | AA20: =OFFSET(F20, -4, 0) -> 0 | AB20: =OFFSET(F20, -5, 0) -> 0 | AC20: =OFFSET(G20, -1, 0) -> 0.089179265 | AD20: =OFFSET(G20, -2, 0) -> 0.044229169 | AE20: =OFFSET(G20, -3, 0) -> 0.015895745 | AF20: =OFFSET(G20, -4, 0) -> 0.051720615 | AG20: =OFFSET(G20, -5, 0) -> 0.031018765 | AH20: =OFFSET(H20, -1, 0) -> -0.0097945858 | AI20: =OFFSET(H20, -2, 0) -> -0.014150295 | AJ20: =OFFSET(H20, -3, 0) -> -0.0044593088 | AK20: =OFFSET(H20, -4, 0) -> -0.0092385218 | AL20: =OFFSET(H20, -5, 0) -> -0.0036733541 | AP20: 0.065 | AQ20: 4193.8 | AR20: 7.351 | AU20: X Variable 1 | AV20: 0.13335935 | AW20: 0.040295431 | AX20: 3.3095403 | AY20: 0.0013609703 | AZ20: 0.053267819 | BA20: 0.21345089 | BB20: 0.053267819 | BC20: 0.21345089
A21: 42675 | B21: -0.012882895 | C21: 0.05359538 | D21: -0.22686567 | E21: 0.028691414 | F21: =(AP21-AP22)/AP22 -> 0 | G21: =(AQ21-AQ22)/AQ22 -> -0.048719291 | H21: =(AR21-AR22)/AR22 -> 0.0061401061 | I21: =OFFSET(C21, -1, 0) -> -0.029024119 | J21: =OFFSET(C21, -2, 0) -> 0.076215051 | K21: =OFFSET(C21, -3, 0) -> 0.071873334 | L21: =OFFSET(C21, -4, 0) -> -0.14995232 | M21: =OFFSET(C23, -5, 0) -> 0.071873334 | N21: =OFFSET(D21, -1, 0) -> -0.19082126 | O21: =OFFSET(D21, -2, 0) -> -0.21886792 | P21: =OFFSET(D21, -3, 0) -> -0.17956656 | Q21: =OFFSET(D21, -4, 0) -> 0.053833605 | R21: =OFFSET(D21, -5, 0) -> -0.069802731 | S21: =OFFSET(E21, -1, 0) -> 0.0019385087 | T21: =OFFSET(E21, -2, 0) -> -0.0062273196 | U21: =OFFSET(E21, -2, 0) -> -0.0062273196 | V21: =OFFSET(E21, -4, 0) -> -0.012786511 | W21: =OFFSET(E21, -5, 0) -> 0.0043750651 | X21: =OFFSET(F21, -1, 0) -> 0 | Y21: =OFFSET(F21, -2, 0) -> 0 | Z21: =OFFSET(F21, -3, 0) -> 0 | AA21: =OFFSET(F21, -4, 0) -> 0 | AB21: =OFFSET(F21, -5, 0) -> 0 | AC21: =OFFSET(G21, -1, 0) -> -0.021979688 | AD21: =OFFSET(G21, -2, 0) -> 0.089179265 | AE21: =OFFSET(G21, -3, 0) -> 0.044229169 | AF21: =OFFSET(G21, -4, 0) -> 0.015895745 | AG21: =OFFSET(G21, -5, 0) -> 0.051720615 | AH21: =OFFSET(H21, -1, 0) -> 0.019556172 | AI21: =OFFSET(H21, -2, 0) -> -0.0097945858 | AJ21: =OFFSET(H21, -3, 0) -> -0.014150295 | AK21: =OFFSET(H21, -4, 0) -> -0.0044593088 | AL21: =OFFSET(H21, -5, 0) -> -0.0092385218 | AP21: 0.065 | AQ21: 4288.05 | AR21: 7.21 | AU21: X Variable 2 | AV21: 0.007903824 | AW21: 0.028168378 | AX21: 0.28059209 | AY21: 0.77968945 | AZ21: -0.048083877 | BA21: 0.063891525 | BB21: -0.048083877 | BC21: 0.063891525
A22: 42705 | B22: -0.051541954 | C22: 0.083025559 | D22: -0.13899614 | E22: -0.0093748178 | F22: =(AP22-AP23)/AP23 -> 0 | G22: =(AQ22-AQ23)/AQ23 -> -0.017716432 | H22: =(AR22-AR23)/AR23 -> -0.00083658673 | I22: =OFFSET(C22, -1, 0) -> 0.05359538 | J22: =OFFSET(C22, -2, 0) -> -0.029024119 | K22: =OFFSET(C22, -3, 0) -> 0.076215051 | L22: =OFFSET(C22, -4, 0) -> 0.071873334 | M22: =OFFSET(C24, -5, 0) -> 0.076215051 | N22: =OFFSET(D22, -1, 0) -> -0.22686567 | O22: =OFFSET(D22, -2, 0) -> -0.19082126 | P22: =OFFSET(D22, -3, 0) -> -0.21886792 | Q22: =OFFSET(D22, -4, 0) -> -0.17956656 | R22: =OFFSET(D22, -5, 0) -> 0.053833605 | S22: =OFFSET(E22, -1, 0) -> 0.028691414 | T22: =OFFSET(E22, -2, 0) -> 0.0019385087 | U22: =OFFSET(E22, -2, 0) -> 0.0019385087 | V22: =OFFSET(E22, -4, 0) -> 0.0049977488 | W22: =OFFSET(E22, -5, 0) -> -0.012786511 | X22: =OFFSET(F22, -1, 0) -> 0 | Y22: =OFFSET(F22, -2, 0) -> 0 | Z22: =OFFSET(F22, -3, 0) -> 0 | AA22: =OFFSET(F22, -4, 0) -> 0 | AB22: =OFFSET(F22, -5, 0) -> 0 | AC22: =OFFSET(G22, -1, 0) -> -0.048719291 | AD22: =OFFSET(G22, -2, 0) -> -0.021979688 | AE22: =OFFSET(G22, -3, 0) -> 0.089179265 | AF22: =OFFSET(G22, -4, 0) -> 0.044229169 | AG22: =OFFSET(G22, -5, 0) -> 0.015895745 | AH22: =OFFSET(H22, -1, 0) -> 0.0061401061 | AI22: =OFFSET(H22, -2, 0) -> 0.019556172 | AJ22: =OFFSET(H22, -3, 0) -> -0.0097945858 | AK22: =OFFSET(H22, -4, 0) -> -0.014150295 | AL22: =OFFSET(H22, -5, 0) -> -0.0044593088 | AP22: 0.065 | AQ22: 4507.66 | AR22: 7.166 | AU22: X Variable 3 | AV22: -0.25269095 | AW22: 0.34175738 | AX22: -0.73938695 | AY22: 0.46166242 | AZ22: -0.93197075 | BA22: 0.42658885 | BB22: -0.93197075 | BC22: 0.42658885
A23: 42736 | B23: -0.0016369015 | C23: -0.017084805 | D23: -0.16591928 | E23: -0.0066965928 | F23: =(AP23-AP24)/AP24 -> 0 | G23: =(AQ23-AQ24)/AQ24 -> 0.031138914 | H23: =(AR23-AR24)/AR24 -> 0.0087201125 | I23: =OFFSET(C23, -1, 0) -> 0.083025559 | J23: =OFFSET(C23, -2, 0) -> 0.05359538 | K23: =OFFSET(C23, -3, 0) -> -0.029024119 | L23: =OFFSET(C23, -4, 0) -> 0.076215051 | M23: =OFFSET(C25, -5, 0) -> -0.029024119 | N23: =OFFSET(D23, -1, 0) -> -0.13899614 | O23: =OFFSET(D23, -2, 0) -> -0.22686567 | P23: =OFFSET(D23, -3, 0) -> -0.19082126 | Q23: =OFFSET(D23, -4, 0) -> -0.21886792 | R23: =OFFSET(D23, -5, 0) -> -0.17956656 | S23: =OFFSET(E23, -1, 0) -> -0.0093748178 | T23: =OFFSET(E23, -2, 0) -> 0.028691414 | U23: =OFFSET(E23, -2, 0) -> 0.028691414 | V23: =OFFSET(E23, -4, 0) -> -0.0062273196 | W23: =OFFSET(E23, -5, 0) -> 0.0049977488 | X23: =OFFSET(F23, -1, 0) -> 0 | Y23: =OFFSET(F23, -2, 0) -> 0 | Z23: =OFFSET(F23, -3, 0) -> 0 | AA23: =OFFSET(F23, -4, 0) -> 0 | AB23: =OFFSET(F23, -5, 0) -> 0 | AC23: =OFFSET(G23, -1, 0) -> -0.017716432 | AD23: =OFFSET(G23, -2, 0) -> -0.048719291 | AE23: =OFFSET(G23, -3, 0) -> -0.021979688 | AF23: =OFFSET(G23, -4, 0) -> 0.089179265 | AG23: =OFFSET(G23, -5, 0) -> 0.044229169 | AH23: =OFFSET(H23, -1, 0) -> -0.00083658673 | AI23: =OFFSET(H23, -2, 0) -> 0.0061401061 | AJ23: =OFFSET(H23, -3, 0) -> 0.019556172 | AK23: =OFFSET(H23, -4, 0) -> -0.0097945858 | AL23: =OFFSET(H23, -5, 0) -> -0.014150295 | AP23: 0.065 | AQ23: 4588.96 | AR23: 7.172 | AU23: X Variable 4 | AV23: 0.61878456 | AW23: 0.17680026 | AX23: 3.4999075 | AY23: 0.00073629251 | AZ23: 0.2673749 | BA23: 0.97019422 | BB23: 0.2673749 | BC23: 0.97019422
A24: 42767 | B24: 0.063575285 | C24: 0.022468648 | D24: 0.40860215 | E24: -0.011705438 | F24: =(AP24-AP25)/AP25 -> 0 | G24: =(AQ24-AQ25)/AQ25 -> 0.064727513 | H24: =(AR24-AR25)/AR25 -> 0.01731292 | I24: =OFFSET(C24, -1, 0) -> -0.017084805 | J24: =OFFSET(C24, -2, 0) -> 0.083025559 | K24: =OFFSET(C24, -3, 0) -> 0.05359538 | L24: =OFFSET(C24, -4, 0) -> -0.029024119 | M24: =OFFSET(C26, -5, 0) -> 0.05359538 | N24: =OFFSET(D24, -1, 0) -> -0.16591928 | O24: =OFFSET(D24, -2, 0) -> -0.13899614 | P24: =OFFSET(D24, -3, 0) -> -0.22686567 | Q24: =OFFSET(D24, -4, 0) -> -0.19082126 | R24: =OFFSET(D24, -5, 0) -> -0.21886792 | S24: =OFFSET(E24, -1, 0) -> -0.0066965928 | T24: =OFFSET(E24, -2, 0) -> -0.0093748178 | U24: =OFFSET(E24, -2, 0) -> -0.0093748178 | V24: =OFFSET(E24, -4, 0) -> 0.0019385087 | W24: =OFFSET(E24, -5, 0) -> -0.0062273196 | X24: =OFFSET(F24, -1, 0) -> 0 | Y24: =OFFSET(F24, -2, 0) -> 0 | Z24: =OFFSET(F24, -3, 0) -> 0 | AA24: =OFFSET(F24, -4, 0) -> 0 | AB24: =OFFSET(F24, -5, 0) -> 0 | AC24: =OFFSET(G24, -1, 0) -> 0.031138914 | AD24: =OFFSET(G24, -2, 0) -> -0.017716432 | AE24: =OFFSET(G24, -3, 0) -> -0.048719291 | AF24: =OFFSET(G24, -4, 0) -> -0.021979688 | AG24: =OFFSET(G24, -5, 0) -> 0.089179265 | AH24: =OFFSET(H24, -1, 0) -> 0.0087201125 | AI24: =OFFSET(H24, -2, 0) -> -0.00083658673 | AJ24: =OFFSET(H24, -3, 0) -> 0.0061401061 | AK24: =OFFSET(H24, -4, 0) -> 0.019556172 | AL24: =OFFSET(H24, -5, 0) -> -0.0097945858 | AP24: 0.065 | AQ24: 4450.38 | AR24: 7.11 | AU24: X Variable 5 | AV24: -0.19615402 | AW24: 0.13214612 | AX24: -1.4843721 | AY24: 0.14132443 | AZ24: -0.45880875 | BA24: 0.066500706 | BB24: -0.45880875 | BC24: 0.066500706
A25: 42795 | B25: 0.02597784 | C25: -0.065217638 | D25: -0.0038167939 | E25: -0.027736132 | F25: =(AP25-AP26)/AP26 -> 0 | G25: =(AQ25-AQ26)/AQ26 -> 0.0024823239 | H25: =(AR25-AR26)/AR26 -> -0.017847105 | I25: =OFFSET(C25, -1, 0) -> 0.022468648 | J25: =OFFSET(C25, -2, 0) -> -0.017084805 | K25: =OFFSET(C25, -3, 0) -> 0.083025559 | L25: =OFFSET(C25, -4, 0) -> 0.05359538 | M25: =OFFSET(C27, -5, 0) -> 0.083025559 | N25: =OFFSET(D25, -1, 0) -> 0.40860215 | O25: =OFFSET(D25, -2, 0) -> -0.16591928 | P25: =OFFSET(D25, -3, 0) -> -0.13899614 | Q25: =OFFSET(D25, -4, 0) -> -0.22686567 | R25: =OFFSET(D25, -5, 0) -> -0.19082126 | S25: =OFFSET(E25, -1, 0) -> -0.011705438 | T25: =OFFSET(E25, -2, 0) -> -0.0066965928 | U25: =OFFSET(E25, -2, 0) -> -0.0066965928 | V25: =OFFSET(E25, -4, 0) -> 0.028691414 | W25: =OFFSET(E25, -5, 0) -> 0.0019385087 | X25: =OFFSET(F25, -1, 0) -> 0 | Y25: =OFFSET(F25, -2, 0) -> 0 | Z25: =OFFSET(F25, -3, 0) -> 0 | AA25: =OFFSET(F25, -4, 0) -> 0 | AB25: =OFFSET(F25, -5, 0) -> 0 | AC25: =OFFSET(G25, -1, 0) -> 0.064727513 | AD25: =OFFSET(G25, -2, 0) -> 0.031138914 | AE25: =OFFSET(G25, -3, 0) -> -0.017716432 | AF25: =OFFSET(G25, -4, 0) -> -0.048719291 | AG25: =OFFSET(G25, -5, 0) -> -0.021979688 | AH25: =OFFSET(H25, -1, 0) -> 0.01731292 | AI25: =OFFSET(H25, -2, 0) -> 0.0087201125 | AJ25: =OFFSET(H25, -3, 0) -> -0.00083658673 | AK25: =OFFSET(H25, -4, 0) -> 0.0061401061 | AL25: =OFFSET(H25, -5, 0) -> 0.019556172 | AP25: 0.065 | AQ25: 4179.83 | AR25: 6.989 | AU25: X Variable 6 | AV25: -0.04338637 | AW25: 0.20254881 | AX25: -0.21420205 | AY25: 0.83089075 | AZ25: -0.44597407 | BA25: 0.35920133 | BB25: -0.44597407 | BC25: 0.35920133
A26: 42826 | B26: 0.032125026 | C26: -0.025419161 | D26: -0.1532567 | E26: -0.0089437163 | F26: =(AP26-AP27)/AP27 -> 0 | G26: =(AQ26-AQ27)/AQ27 -> 0.014642361 | H26: =(AR26-AR27)/AR27 -> -0.027204375 | I26: =OFFSET(C26, -1, 0) -> -0.065217638 | J26: =OFFSET(C26, -2, 0) -> 0.022468648 | K26: =OFFSET(C26, -3, 0) -> -0.017084805 | L26: =OFFSET(C26, -4, 0) -> 0.083025559 | M26: =OFFSET(C28, -5, 0) -> -0.017084805 | N26: =OFFSET(D26, -1, 0) -> -0.0038167939 | O26: =OFFSET(D26, -2, 0) -> 0.40860215 | P26: =OFFSET(D26, -3, 0) -> -0.16591928 | Q26: =OFFSET(D26, -4, 0) -> -0.13899614 | R26: =OFFSET(D26, -5, 0) -> -0.22686567 | S26: =OFFSET(E26, -1, 0) -> -0.027736132 | T26: =OFFSET(E26, -2, 0) -> -0.011705438 | U26: =OFFSET(E26, -2, 0) -> -0.011705438 | V26: =OFFSET(E26, -4, 0) -> -0.0093748178 | W26: =OFFSET(E26, -5, 0) -> 0.028691414 | X26: =OFFSET(F26, -1, 0) -> 0 | Y26: =OFFSET(F26, -2, 0) -> 0 | Z26: =OFFSET(F26, -3, 0) -> 0 | AA26: =OFFSET(F26, -4, 0) -> 0 | AB26: =OFFSET(F26, -5, 0) -> 0 | AC26: =OFFSET(G26, -1, 0) -> 0.0024823239 | AD26: =OFFSET(G26, -2, 0) -> 0.064727513 | AE26: =OFFSET(G26, -3, 0) -> 0.031138914 | AF26: =OFFSET(G26, -4, 0) -> -0.017716432 | AG26: =OFFSET(G26, -5, 0) -> -0.048719291 | AH26: =OFFSET(H26, -1, 0) -> -0.017847105 | AI26: =OFFSET(H26, -2, 0) -> 0.01731292 | AJ26: =OFFSET(H26, -3, 0) -> 0.0087201125 | AK26: =OFFSET(H26, -4, 0) -> -0.00083658673 | AL26: =OFFSET(H26, -5, 0) -> 0.0061401061 | AP26: 0.065 | AQ26: 4169.48 | AR26: 7.116
A27: 42856 | B27: 0.0081879967 | C27: -0.020686862 | D27: -0.50678733 | E27: 0.0036564494 | F27: =(AP27-AP28)/AP28 -> 0 | G27: =(AQ27-AQ28)/AQ28 -> 0.035051572 | H27: =(AR27-AR28)/AR28 -> -0.01904251 | I27: =OFFSET(C27, -1, 0) -> -0.025419161 | J27: =OFFSET(C27, -2, 0) -> -0.065217638 | K27: =OFFSET(C27, -3, 0) -> 0.022468648 | L27: =OFFSET(C27, -4, 0) -> -0.017084805 | M27: =OFFSET(C29, -5, 0) -> 0.022468648 | N27: =OFFSET(D27, -1, 0) -> -0.1532567 | O27: =OFFSET(D27, -2, 0) -> -0.0038167939 | P27: =OFFSET(D27, -3, 0) -> 0.40860215 | Q27: =OFFSET(D27, -4, 0) -> -0.16591928 | R27: =OFFSET(D27, -5, 0) -> -0.13899614 | S27: =OFFSET(E27, -1, 0) -> -0.0089437163 | T27: =OFFSET(E27, -2, 0) -> -0.027736132 | U27: =OFFSET(E27, -2, 0) -> -0.027736132 | V27: =OFFSET(E27, -4, 0) -> -0.0066965928 | W27: =OFFSET(E27, -5, 0) -> -0.0093748178 | X27: =OFFSET(F27, -1, 0) -> 0 | Y27: =OFFSET(F27, -2, 0) -> 0 | Z27: =OFFSET(F27, -3, 0) -> 0 | AA27: =OFFSET(F27, -4, 0) -> 0 | AB27: =OFFSET(F27, -5, 0) -> 0 | AC27: =OFFSET(G27, -1, 0) -> 0.014642361 | AD27: =OFFSET(G27, -2, 0) -> 0.0024823239 | AE27: =OFFSET(G27, -3, 0) -> 0.064727513 | AF27: =OFFSET(G27, -4, 0) -> 0.031138914 | AG27: =OFFSET(G27, -5, 0) -> -0.017716432 | AH27: =OFFSET(H27, -1, 0) -> -0.027204375 | AI27: =OFFSET(H27, -2, 0) -> -0.017847105 | AJ27: =OFFSET(H27, -3, 0) -> 0.01731292 | AK27: =OFFSET(H27, -4, 0) -> 0.0087201125 | AL27: =OFFSET(H27, -5, 0) -> -0.00083658673 | AP27: 0.065 | AQ27: 4109.31 | AR27: 7.315
A28: 42887 | B28: 0.031941606 | C28: -0.04833497 | D28: -0.0091743119 | E28: 0.0017052942 | F28: =(AP28-AP29)/AP29 -> 0.04 | G28: =(AQ28-AQ29)/AQ29 -> -0.026112447 | H28: =(AR28-AR29)/AR29 -> 0.01552499 | I28: =OFFSET(C28, -1, 0) -> -0.020686862 | J28: =OFFSET(C28, -2, 0) -> -0.025419161 | K28: =OFFSET(C28, -3, 0) -> -0.065217638 | L28: =OFFSET(C28, -4, 0) -> 0.022468648 | M28: =OFFSET(C30, -5, 0) -> -0.065217638 | N28: =OFFSET(D28, -1, 0) -> -0.50678733 | O28: =OFFSET(D28, -2, 0) -> -0.1532567 | P28: =OFFSET(D28, -3, 0) -> -0.0038167939 | Q28: =OFFSET(D28, -4, 0) -> 0.40860215 | R28: =OFFSET(D28, -5, 0) -> -0.16591928 | S28: =OFFSET(E28, -1, 0) -> 0.0036564494 | T28: =OFFSET(E28, -2, 0) -> -0.0089437163 | U28: =OFFSET(E28, -2, 0) -> -0.0089437163 | V28: =OFFSET(E28, -4, 0) -> -0.011705438 | W28: =OFFSET(E28, -5, 0) -> -0.0066965928 | X28: =OFFSET(F28, -1, 0) -> 0 | Y28: =OFFSET(F28, -2, 0) -> 0 | Z28: =OFFSET(F28, -3, 0) -> 0 | AA28: =OFFSET(F28, -4, 0) -> 0 | AB28: =OFFSET(F28, -5, 0) -> 0 | AC28: =OFFSET(G28, -1, 0) -> 0.035051572 | AD28: =OFFSET(G28, -2, 0) -> 0.014642361 | AE28: =OFFSET(G28, -3, 0) -> 0.0024823239 | AF28: =OFFSET(G28, -4, 0) -> 0.064727513 | AG28: =OFFSET(G28, -5, 0) -> 0.031138914 | AH28: =OFFSET(H28, -1, 0) -> -0.01904251 | AI28: =OFFSET(H28, -2, 0) -> -0.027204375 | AJ28: =OFFSET(H28, -3, 0) -> -0.017847105 | AK28: =OFFSET(H28, -4, 0) -> 0.01731292 | AL28: =OFFSET(H28, -5, 0) -> 0.0087201125 | AP28: 0.065 | AQ28: 3970.15 | AR28: 7.457
A29: 42917 | B29: -0.00011439803 | C29: 0.085906655 | D29: 0.65740741 | E29: -0.0068869458 | F29: =(AP29-AP30)/AP30 -> 0 | G29: =(AQ29-AQ30)/AQ30 -> 0.061752832 | H29: =(AR29-AR30)/AR30 -> 0.0021837041 | I29: =OFFSET(C29, -1, 0) -> -0.04833497 | J29: =OFFSET(C29, -2, 0) -> -0.020686862 | K29: =OFFSET(C29, -3, 0) -> -0.025419161 | L29: =OFFSET(C29, -4, 0) -> -0.065217638 | M29: =OFFSET(C31, -5, 0) -> -0.025419161 | N29: =OFFSET(D29, -1, 0) -> -0.0091743119 | O29: =OFFSET(D29, -2, 0) -> -0.50678733 | P29: =OFFSET(D29, -3, 0) -> -0.1532567 | Q29: =OFFSET(D29, -4, 0) -> -0.0038167939 | R29: =OFFSET(D29, -5, 0) -> 0.40860215 | S29: =OFFSET(E29, -1, 0) -> 0.0017052942 | T29: =OFFSET(E29, -2, 0) -> 0.0036564494 | U29: =OFFSET(E29, -2, 0) -> 0.0036564494 | V29: =OFFSET(E29, -4, 0) -> -0.027736132 | W29: =OFFSET(E29, -5, 0) -> -0.011705438 | X29: =OFFSET(F29, -1, 0) -> 0.04 | Y29: =OFFSET(F29, -2, 0) -> 0 | Z29: =OFFSET(F29, -3, 0) -> 0 | AA29: =OFFSET(F29, -4, 0) -> 0 | AB29: =OFFSET(F29, -5, 0) -> 0 | AC29: =OFFSET(G29, -1, 0) -> -0.026112447 | AD29: =OFFSET(G29, -2, 0) -> 0.035051572 | AE29: =OFFSET(G29, -3, 0) -> 0.014642361 | AF29: =OFFSET(G29, -4, 0) -> 0.0024823239 | AG29: =OFFSET(G29, -5, 0) -> 0.064727513 | AH29: =OFFSET(H29, -1, 0) -> 0.01552499 | AI29: =OFFSET(H29, -2, 0) -> -0.01904251 | AJ29: =OFFSET(H29, -3, 0) -> -0.027204375 | AK29: =OFFSET(H29, -4, 0) -> -0.017847105 | AL29: =OFFSET(H29, -5, 0) -> 0.01731292 | AP29: 0.0625 | AQ29: 4076.6 | AR29: 7.343
A30: 42948 | B30: 0.050660489 | C30: -0.060387955 | D30: 0.40782123 | E30: -0.0037400655 | F30: =(AP30-AP31)/AP31 -> 0.059322034 | G30: =(AQ30-AQ31)/AQ31 -> -0.058971449 | H30: =(AR30-AR31)/AR31 -> 0.006456044 | I30: =OFFSET(C30, -1, 0) -> 0.085906655 | J30: =OFFSET(C30, -2, 0) -> -0.04833497 | K30: =OFFSET(C30, -3, 0) -> -0.020686862 | L30: =OFFSET(C30, -4, 0) -> -0.025419161 | M30: =OFFSET(C32, -5, 0) -> -0.020686862 | N30: =OFFSET(D30, -1, 0) -> 0.65740741 | O30: =OFFSET(D30, -2, 0) -> -0.0091743119 | P30: =OFFSET(D30, -3, 0) -> -0.50678733 | Q30: =OFFSET(D30, -4, 0) -> -0.1532567 | R30: =OFFSET(D30, -5, 0) -> -0.0038167939 | S30: =OFFSET(E30, -1, 0) -> -0.0068869458 | T30: =OFFSET(E30, -2, 0) -> 0.0017052942 | U30: =OFFSET(E30, -2, 0) -> 0.0017052942 | V30: =OFFSET(E30, -4, 0) -> -0.0089437163 | W30: =OFFSET(E30, -5, 0) -> -0.027736132 | X30: =OFFSET(F30, -1, 0) -> 0 | Y30: =OFFSET(F30, -2, 0) -> 0.04 | Z30: =OFFSET(F30, -3, 0) -> 0 | AA30: =OFFSET(F30, -4, 0) -> 0 | AB30: =OFFSET(F30, -5, 0) -> 0 | AC30: =OFFSET(G30, -1, 0) -> 0.061752832 | AD30: =OFFSET(G30, -2, 0) -> -0.026112447 | AE30: =OFFSET(G30, -3, 0) -> 0.035051572 | AF30: =OFFSET(G30, -4, 0) -> 0.014642361 | AG30: =OFFSET(G30, -5, 0) -> 0.0024823239 | AH30: =OFFSET(H30, -1, 0) -> 0.0021837041 | AI30: =OFFSET(H30, -2, 0) -> 0.01552499 | AJ30: =OFFSET(H30, -3, 0) -> -0.01904251 | AK30: =OFFSET(H30, -4, 0) -> -0.027204375 | AL30: =OFFSET(H30, -5, 0) -> -0.017847105 | AP30: 0.0625 | AQ30: 3839.5 | AR30: 7.327
A31: 42979 | B31: -0.013963057 | C31: 0.089848058 | D31: 0.1468254 | E31: 0.021507899 | F31: =(AP31-AP32)/AP32 -> 0 | G31: =(AQ31-AQ32)/AQ32 -> 0.05375286 | H31: =(AR31-AR32)/AR32 -> -0.022162525 | I31: =OFFSET(C31, -1, 0) -> -0.060387955 | J31: =OFFSET(C31, -2, 0) -> 0.085906655 | K31: =OFFSET(C31, -3, 0) -> -0.04833497 | L31: =OFFSET(C31, -4, 0) -> -0.020686862 | M31: =OFFSET(C33, -5, 0) -> -0.04833497 | N31: =OFFSET(D31, -1, 0) -> 0.40782123 | O31: =OFFSET(D31, -2, 0) -> 0.65740741 | P31: =OFFSET(D31, -3, 0) -> -0.0091743119 | Q31: =OFFSET(D31, -4, 0) -> -0.50678733 | R31: =OFFSET(D31, -5, 0) -> -0.1532567 | S31: =OFFSET(E31, -1, 0) -> -0.0037400655 | T31: =OFFSET(E31, -2, 0) -> -0.0068869458 | U31: =OFFSET(E31, -2, 0) -> -0.0068869458 | V31: =OFFSET(E31, -4, 0) -> 0.0036564494 | W31: =OFFSET(E31, -5, 0) -> -0.0089437163 | X31: =OFFSET(F31, -1, 0) -> 0.059322034 | Y31: =OFFSET(F31, -2, 0) -> 0 | Z31: =OFFSET(F31, -3, 0) -> 0.04 | AA31: =OFFSET(F31, -4, 0) -> 0 | AB31: =OFFSET(F31, -5, 0) -> 0 | AC31: =OFFSET(G31, -1, 0) -> -0.058971449 | AD31: =OFFSET(G31, -2, 0) -> 0.061752832 | AE31: =OFFSET(G31, -3, 0) -> -0.026112447 | AF31: =OFFSET(G31, -4, 0) -> 0.035051572 | AG31: =OFFSET(G31, -5, 0) -> 0.014642361 | AH31: =OFFSET(H31, -1, 0) -> 0.006456044 | AI31: =OFFSET(H31, -2, 0) -> 0.0021837041 | AJ31: =OFFSET(H31, -3, 0) -> 0.01552499 | AK31: =OFFSET(H31, -4, 0) -> -0.01904251 | AL31: =OFFSET(H31, -5, 0) -> -0.027204375 | AP31: 0.059 | AQ31: 4080.11 | AR31: 7.28
A32: 43009 | B32: -0.011586353 | C32: 0.051119097 | D32: 0.12110727 | E32: -0.0086517112 | F32: =(AP32-AP33)/AP33 -> 0 | G32: =(AQ32-AQ33)/AQ33 -> 0.079863455 | H32: =(AR32-AR33)/AR33 -> 0.0063530684 | I32: =OFFSET(C32, -1, 0) -> 0.089848058 | J32: =OFFSET(C32, -2, 0) -> -0.060387955 | K32: =OFFSET(C32, -3, 0) -> 0.085906655 | L32: =OFFSET(C32, -4, 0) -> -0.04833497 | M32: =OFFSET(C34, -5, 0) -> 0.085906655 | N32: =OFFSET(D32, -1, 0) -> 0.1468254 | O32: =OFFSET(D32, -2, 0) -> 0.40782123 | P32: =OFFSET(D32, -3, 0) -> 0.65740741 | Q32: =OFFSET(D32, -4, 0) -> -0.0091743119 | R32: =OFFSET(D32, -5, 0) -> -0.50678733 | S32: =OFFSET(E32, -1, 0) -> 0.021507899 | T32: =OFFSET(E32, -2, 0) -> -0.0037400655 | U32: =OFFSET(E32, -2, 0) -> -0.0037400655 | V32: =OFFSET(E32, -4, 0) -> 0.0017052942 | W32: =OFFSET(E32, -5, 0) -> 0.0036564494 | X32: =OFFSET(F32, -1, 0) -> 0 | Y32: =OFFSET(F32, -2, 0) -> 0.059322034 | Z32: =OFFSET(F32, -3, 0) -> 0 | AA32: =OFFSET(F32, -4, 0) -> 0.04 | AB32: =OFFSET(F32, -5, 0) -> 0 | AC32: =OFFSET(G32, -1, 0) -> 0.05375286 | AD32: =OFFSET(G32, -2, 0) -> -0.058971449 | AE32: =OFFSET(G32, -3, 0) -> 0.061752832 | AF32: =OFFSET(G32, -4, 0) -> -0.026112447 | AG32: =OFFSET(G32, -5, 0) -> 0.035051572 | AH32: =OFFSET(H32, -1, 0) -> -0.022162525 | AI32: =OFFSET(H32, -2, 0) -> 0.006456044 | AJ32: =OFFSET(H32, -3, 0) -> 0.0021837041 | AK32: =OFFSET(H32, -4, 0) -> 0.01552499 | AL32: =OFFSET(H32, -5, 0) -> -0.01904251 | AP32: 0.059 | AQ32: 3871.98 | AR32: 7.445
A33: 43040 | B33: 0.057257017 | C33: 0.054047864 | D33: 0.22530864 | E33: -0.0040160643 | F33: =(AP33-AP34)/AP34 -> 0.092592593 | G33: =(AQ33-AQ34)/AQ34 -> -0.093395702 | H33: =(AR33-AR34)/AR34 -> 0.029215359 | I33: =OFFSET(C33, -1, 0) -> 0.051119097 | J33: =OFFSET(C33, -2, 0) -> 0.089848058 | K33: =OFFSET(C33, -3, 0) -> -0.060387955 | L33: =OFFSET(C33, -4, 0) -> 0.085906655 | M33: =OFFSET(C35, -5, 0) -> -0.060387955 | N33: =OFFSET(D33, -1, 0) -> 0.12110727 | O33: =OFFSET(D33, -2, 0) -> 0.1468254 | P33: =OFFSET(D33, -3, 0) -> 0.40782123 | Q33: =OFFSET(D33, -4, 0) -> 0.65740741 | R33: =OFFSET(D33, -5, 0) -> -0.0091743119 | S33: =OFFSET(E33, -1, 0) -> -0.0086517112 | T33: =OFFSET(E33, -2, 0) -> 0.021507899 | U33: =OFFSET(E33, -2, 0) -> 0.021507899 | V33: =OFFSET(E33, -4, 0) -> -0.0068869458 | W33: =OFFSET(E33, -5, 0) -> 0.0017052942 | X33: =OFFSET(F33, -1, 0) -> 0 | Y33: =OFFSET(F33, -2, 0) -> 0 | Z33: =OFFSET(F33, -3, 0) -> 0.059322034 | AA33: =OFFSET(F33, -4, 0) -> 0 | AB33: =OFFSET(F33, -5, 0) -> 0.04 | AC33: =OFFSET(G33, -1, 0) -> 0.079863455 | AD33: =OFFSET(G33, -2, 0) -> 0.05375286 | AE33: =OFFSET(G33, -3, 0) -> -0.058971449 | AF33: =OFFSET(G33, -4, 0) -> 0.061752832 | AG33: =OFFSET(G33, -5, 0) -> -0.026112447 | AH33: =OFFSET(H33, -1, 0) -> 0.0063530684 | AI33: =OFFSET(H33, -2, 0) -> -0.022162525 | AJ33: =OFFSET(H33, -3, 0) -> 0.006456044 | AK33: =OFFSET(H33, -4, 0) -> 0.0021837041 | AL33: =OFFSET(H33, -5, 0) -> 0.01552499 | AP33: 0.059 | AQ33: 3585.62 | AR33: 7.398
A34: 43070 | B34: -0.03100096 | C34: 0.051275873 | D34: 0.0075566751 | E34: -0.010080645 | F34: =(AP34-AP35)/AP35 -> 0.10204082 | G34: =(AQ34-AQ35)/AQ35 -> -0.042440119 | H34: =(AR34-AR35)/AR35 -> -0.018032787 | I34: =OFFSET(C34, -1, 0) -> 0.054047864 | J34: =OFFSET(C34, -2, 0) -> 0.051119097 | K34: =OFFSET(C34, -3, 0) -> 0.089848058 | L34: =OFFSET(C34, -4, 0) -> -0.060387955 | M34: =OFFSET(C36, -5, 0) -> 0.089848058 | N34: =OFFSET(D34, -1, 0) -> 0.22530864 | O34: =OFFSET(D34, -2, 0) -> 0.12110727 | P34: =OFFSET(D34, -3, 0) -> 0.1468254 | Q34: =OFFSET(D34, -4, 0) -> 0.40782123 | R34: =OFFSET(D34, -5, 0) -> 0.65740741 | S34: =OFFSET(E34, -1, 0) -> -0.0040160643 | T34: =OFFSET(E34, -2, 0) -> -0.0086517112 | U34: =OFFSET(E34, -2, 0) -> -0.0086517112 | V34: =OFFSET(E34, -4, 0) -> -0.0037400655 | W34: =OFFSET(E34, -5, 0) -> -0.0068869458 | X34: =OFFSET(F34, -1, 0) -> 0.092592593 | Y34: =OFFSET(F34, -2, 0) -> 0 | Z34: =OFFSET(F34, -3, 0) -> 0 | AA34: =OFFSET(F34, -4, 0) -> 0.059322034 | AB34: =OFFSET(F34, -5, 0) -> 0 | AC34: =OFFSET(G34, -1, 0) -> -0.093395702 | AD34: =OFFSET(G34, -2, 0) -> 0.079863455 | AE34: =OFFSET(G34, -3, 0) -> 0.05375286 | AF34: =OFFSET(G34, -4, 0) -> -0.058971449 | AG34: =OFFSET(G34, -5, 0) -> 0.061752832 | AH34: =OFFSET(H34, -1, 0) -> 0.029215359 | AI34: =OFFSET(H34, -2, 0) -> 0.0063530684 | AJ34: =OFFSET(H34, -3, 0) -> -0.022162525 | AK34: =OFFSET(H34, -4, 0) -> 0.006456044 | AL34: =OFFSET(H34, -5, 0) -> 0.0021837041 | AP34: 0.054 | AQ34: 3955 | AR34: 7.188
A35: 43101 | B35: 0.030526733 | C35: 0.068904597 | D35: 0.2775 | E35: -0.0045433182 | F35: =(AP35-AP36)/AP36 -> 0 | G35: =(AQ35-AQ36)/AQ36 -> 0.091116348 | H35: =(AR35-AR36)/AR36 -> -0.017449664 | I35: =OFFSET(C35, -1, 0) -> 0.051275873 | J35: =OFFSET(C35, -2, 0) -> 0.054047864 | K35: =OFFSET(C35, -3, 0) -> 0.051119097 | L35: =OFFSET(C35, -4, 0) -> 0.089848058 | M35: =OFFSET(C37, -5, 0) -> 0.051119097 | N35: =OFFSET(D35, -1, 0) -> 0.0075566751 | O35: =OFFSET(D35, -2, 0) -> 0.22530864 | P35: =OFFSET(D35, -3, 0) -> 0.12110727 | Q35: =OFFSET(D35, -4, 0) -> 0.1468254 | R35: =OFFSET(D35, -5, 0) -> 0.40782123 | S35: =OFFSET(E35, -1, 0) -> -0.010080645 | T35: =OFFSET(E35, -2, 0) -> -0.0040160643 | U35: =OFFSET(E35, -2, 0) -> -0.0040160643 | V35: =OFFSET(E35, -4, 0) -> 0.021507899 | W35: =OFFSET(E35, -5, 0) -> -0.0037400655 | X35: =OFFSET(F35, -1, 0) -> 0.10204082 | Y35: =OFFSET(F35, -2, 0) -> 0.092592593 | Z35: =OFFSET(F35, -3, 0) -> 0 | AA35: =OFFSET(F35, -4, 0) -> 0 | AB35: =OFFSET(F35, -5, 0) -> 0.059322034 | AC35: =OFFSET(G35, -1, 0) -> -0.042440119 | AD35: =OFFSET(G35, -2, 0) -> -0.093395702 | AE35: =OFFSET(G35, -3, 0) -> 0.079863455 | AF35: =OFFSET(G35, -4, 0) -> 0.05375286 | AG35: =OFFSET(G35, -5, 0) -> -0.058971449 | AH35: =OFFSET(H35, -1, 0) -> -0.018032787 | AI35: =OFFSET(H35, -2, 0) -> 0.029215359 | AJ35: =OFFSET(H35, -3, 0) -> 0.0063530684 | AK35: =OFFSET(H35, -4, 0) -> -0.022162525 | AL35: =OFFSET(H35, -5, 0) -> 0.006456044 | AP35: 0.049 | AQ35: 4130.29 | AR35: 7.32
A36: 43132 | B36: 0.054212211 | C36: -0.048913762 | D36: -0.072407045 | E36: 0.026125275 | F36: =(AP36-AP37)/AP37 -> 0.11363636 | G36: =(AQ36-AQ37)/AQ37 -> -0.083919993 | H36: =(AR36-AR37)/AR37 -> 0.0047201618 | I36: =OFFSET(C36, -1, 0) -> 0.068904597 | J36: =OFFSET(C36, -2, 0) -> 0.051275873 | K36: =OFFSET(C36, -3, 0) -> 0.054047864 | L36: =OFFSET(C36, -4, 0) -> 0.051119097 | M36: =OFFSET(C38, -5, 0) -> 0.054047864 | N36: =OFFSET(D36, -1, 0) -> 0.2775 | O36: =OFFSET(D36, -2, 0) -> 0.0075566751 | P36: =OFFSET(D36, -3, 0) -> 0.22530864 | Q36: =OFFSET(D36, -4, 0) -> 0.12110727 | R36: =OFFSET(D36, -5, 0) -> 0.1468254 | S36: =OFFSET(E36, -1, 0) -> -0.0045433182 | T36: =OFFSET(E36, -2, 0) -> -0.010080645 | U36: =OFFSET(E36, -2, 0) -> -0.010080645 | V36: =OFFSET(E36, -4, 0) -> -0.0086517112 | W36: =OFFSET(E36, -5, 0) -> 0.021507899 | X36: =OFFSET(F36, -1, 0) -> 0 | Y36: =OFFSET(F36, -2, 0) -> 0.10204082 | Z36: =OFFSET(F36, -3, 0) -> 0.092592593 | AA36: =OFFSET(F36, -4, 0) -> 0 | AB36: =OFFSET(F36, -5, 0) -> 0 | AC36: =OFFSET(G36, -1, 0) -> 0.091116348 | AD36: =OFFSET(G36, -2, 0) -> -0.042440119 | AE36: =OFFSET(G36, -3, 0) -> -0.093395702 | AF36: =OFFSET(G36, -4, 0) -> 0.079863455 | AG36: =OFFSET(G36, -5, 0) -> 0.05375286 | AH36: =OFFSET(H36, -1, 0) -> -0.017449664 | AI36: =OFFSET(H36, -2, 0) -> -0.018032787 | AJ36: =OFFSET(H36, -3, 0) -> 0.029215359 | AK36: =OFFSET(H36, -4, 0) -> 0.0063530684 | AL36: =OFFSET(H36, -5, 0) -> -0.022162525 | AP36: 0.049 | AQ36: 3785.38 | AR36: 7.45
A37: 43160 | B37: -0.052029755 | C37: 0.052152756 | D37: -0.10126582 | E37: -0.0013803681 | F37: =(AP37-AP38)/AP38 -> 0 | G37: =(AQ37-AQ38)/AQ38 -> 5.3243884e-05 | H37: =(AR37-AR38)/AR38 -> 0.038660877 | I37: =OFFSET(C37, -1, 0) -> -0.048913762 | J37: =OFFSET(C37, -2, 0) -> 0.068904597 | K37: =OFFSET(C37, -3, 0) -> 0.051275873 | L37: =OFFSET(C37, -4, 0) -> 0.054047864 | M37: =OFFSET(C39, -5, 0) -> 0.051275873 | N37: =OFFSET(D37, -1, 0) -> -0.072407045 | O37: =OFFSET(D37, -2, 0) -> 0.2775 | P37: =OFFSET(D37, -3, 0) -> 0.0075566751 | Q37: =OFFSET(D37, -4, 0) -> 0.22530864 | R37: =OFFSET(D37, -5, 0) -> 0.12110727 | S37: =OFFSET(E37, -1, 0) -> 0.026125275 | T37: =OFFSET(E37, -2, 0) -> -0.0045433182 | U37: =OFFSET(E37, -2, 0) -> -0.0045433182 | V37: =OFFSET(E37, -4, 0) -> -0.0040160643 | W37: =OFFSET(E37, -5, 0) -> -0.0086517112 | X37: =OFFSET(F37, -1, 0) -> 0.11363636 | Y37: =OFFSET(F37, -2, 0) -> 0 | Z37: =OFFSET(F37, -3, 0) -> 0.10204082 | AA37: =OFFSET(F37, -4, 0) -> 0.092592593 | AB37: =OFFSET(F37, -5, 0) -> 0 | AC37: =OFFSET(G37, -1, 0) -> -0.083919993 | AD37: =OFFSET(G37, -2, 0) -> 0.091116348 | AE37: =OFFSET(G37, -3, 0) -> -0.042440119 | AF37: =OFFSET(G37, -4, 0) -> -0.093395702 | AG37: =OFFSET(G37, -5, 0) -> 0.079863455 | AH37: =OFFSET(H37, -1, 0) -> 0.0047201618 | AI37: =OFFSET(H37, -2, 0) -> -0.017449664 | AJ37: =OFFSET(H37, -3, 0) -> -0.018032787 | AK37: =OFFSET(H37, -4, 0) -> 0.029215359 | AL37: =OFFSET(H37, -5, 0) -> 0.0063530684 | AP37: 0.044 | AQ37: 4132.15 | AR37: 7.415
... A97: 44986 | B97: -0.0094333866 | C97: -0.018072781 | D97: -0.060064935 | E97: -0.0058083253 | F97: =(AP97-AP98)/AP98 -> 0 | G97: =(AQ97-AQ98)/AQ98 -> 0.01157621 | H97: =(AR97-AR98)/AR98 -> -0.043097256 | I97: =OFFSET(C97, -1, 0) -> -0.038946128 | J97: =OFFSET(C97, -2, 0) -> -0.0044837539 | K97: =OFFSET(C97, -3, 0) -> -0.0011178043 | L97: =OFFSET(C97, -4, 0) -> -0.071488926 | M97: =OFFSET(C99, -5, 0) -> -0.0011178043 | N97: =OFFSET(D97, -1, 0) -> 0.0016260163 | O97: =OFFSET(D97, -2, 0) -> 0.11818182 | P97: =OFFSET(D97, -3, 0) -> 0.01663586 | Q97: =OFFSET(D97, -4, 0) -> -0.11019737 | R97: =OFFSET(D97, -5, 0) -> -0.063174114 | S97: =OFFSET(E97, -1, 0) -> 0.01102289 | T97: =OFFSET(E97, -2, 0) -> -0.011823446 | U97: =OFFSET(E97, -2, 0) -> -0.011823446 | V97: =OFFSET(E97, -4, 0) -> -0.017047239 | W97: =OFFSET(E97, -5, 0) -> 0.015470684 | X97: =OFFSET(F97, -1, 0) -> 0 | Y97: =OFFSET(F97, -2, 0) -> 0 | Z97: =OFFSET(F97, -3, 0) -> -0.04 | AA97: =OFFSET(F97, -4, 0) -> 0 | AB97: =OFFSET(F97, -5, 0) -> 0 | AC97: =OFFSET(G97, -1, 0) -> 0.004813832 | AD97: =OFFSET(G97, -2, 0) -> 0.019348769 | AE97: =OFFSET(G97, -3, 0) -> 0.00054649233 | AF97: =OFFSET(G97, -4, 0) -> 0.019302895 | AG97: =OFFSET(G97, -5, 0) -> 0.022188175 | AH97: =OFFSET(H97, -1, 0) -> -0.022519141 | AI97: =OFFSET(H97, -2, 0) -> -0.007064967 | AJ97: =OFFSET(H97, -3, 0) -> 0.0092807425 | AK97: =OFFSET(H97, -4, 0) -> 0.021149425 | AL97: =OFFSET(H97, -5, 0) -> 0.029866427 | AP97: 0.0625 | AQ97: 2411.8 | AR97: 6.661
A98: 45017 | B98: -0.0030330923 | C98: 0.014562409 | E98: -0.0053554041 | F98: =(AP98-AP99)/AP99 -> 0 | G98: =(AQ98-AQ99)/AQ99 -> 0.0090912169 | H98: =(AR98-AR99)/AR99 -> 0.045509162 | I98: =OFFSET(C98, -1, 0) -> -0.018072781 | J98: =OFFSET(C98, -2, 0) -> -0.038946128 | K98: =OFFSET(C98, -3, 0) -> -0.0044837539 | L98: =OFFSET(C98, -4, 0) -> -0.0011178043 | M98: =OFFSET(C100, -5, 0) -> -0.0044837539 | N98: =OFFSET(D98, -1, 0) -> -0.060064935 | O98: =OFFSET(D98, -2, 0) -> 0.0016260163 | P98: =OFFSET(D98, -3, 0) -> 0.11818182 | Q98: =OFFSET(D98, -4, 0) -> 0.01663586 | R98: =OFFSET(D98, -5, 0) -> -0.11019737 | S98: =OFFSET(E98, -1, 0) -> -0.0058083253 | T98: =OFFSET(E98, -2, 0) -> 0.01102289 | U98: =OFFSET(E98, -2, 0) -> 0.01102289 | V98: =OFFSET(E98, -4, 0) -> 0.016691454 | W98: =OFFSET(E98, -5, 0) -> -0.017047239 | X98: =OFFSET(F98, -1, 0) -> 0 | Y98: =OFFSET(F98, -2, 0) -> 0 | Z98: =OFFSET(F98, -3, 0) -> 0 | AA98: =OFFSET(F98, -4, 0) -> -0.04 | AB98: =OFFSET(F98, -5, 0) -> 0 | AC98: =OFFSET(G98, -1, 0) -> 0.01157621 | AD98: =OFFSET(G98, -2, 0) -> 0.004813832 | AE98: =OFFSET(G98, -3, 0) -> 0.019348769 | AF98: =OFFSET(G98, -4, 0) -> 0.00054649233 | AG98: =OFFSET(G98, -5, 0) -> 0.019302895 | AH98: =OFFSET(H98, -1, 0) -> -0.043097256 | AI98: =OFFSET(H98, -2, 0) -> -0.022519141 | AJ98: =OFFSET(H98, -3, 0) -> -0.007064967 | AK98: =OFFSET(H98, -4, 0) -> 0.0092807425 | AL98: =OFFSET(H98, -5, 0) -> 0.021149425 | AP98: 0.0625 | AQ98: 2384.2 | AR98: 6.961
A99: 45047 | B99: 0.042182945 | C99: -0.12011383 | E99: 0.01174743 | F99: =(AP99-AP100)/AP100 -> 0 | G99: =(AQ99-AQ100)/AQ100 -> -0.00038923017 | H99: =(AR99-AR100)/AR100 -> -0.030858806 | I99: =OFFSET(C99, -1, 0) -> 0.014562409 | J99: =OFFSET(C99, -2, 0) -> -0.018072781 | K99: =OFFSET(C99, -3, 0) -> -0.038946128 | L99: =OFFSET(C99, -4, 0) -> -0.0044837539 | M99: =OFFSET(C101, -5, 0) -> -0.038946128 | N99: =OFFSET(D99, -1, 0) -> 0 | O99: =OFFSET(D99, -2, 0) -> -0.060064935 | P99: =OFFSET(D99, -3, 0) -> 0.0016260163 | Q99: =OFFSET(D99, -4, 0) -> 0.11818182 | R99: =OFFSET(D99, -5, 0) -> 0.01663586 | S99: =OFFSET(E99, -1, 0) -> -0.0053554041 | T99: =OFFSET(E99, -2, 0) -> -0.0058083253 | U99: =OFFSET(E99, -2, 0) -> -0.0058083253 | V99: =OFFSET(E99, -4, 0) -> -0.011823446 | W99: =OFFSET(E99, -5, 0) -> 0.016691454 | X99: =OFFSET(F99, -1, 0) -> 0 | Y99: =OFFSET(F99, -2, 0) -> 0 | Z99: =OFFSET(F99, -3, 0) -> 0 | AA99: =OFFSET(F99, -4, 0) -> 0 | AB99: =OFFSET(F99, -5, 0) -> -0.04 | AC99: =OFFSET(G99, -1, 0) -> 0.0090912169 | AD99: =OFFSET(G99, -2, 0) -> 0.01157621 | AE99: =OFFSET(G99, -3, 0) -> 0.004813832 | AF99: =OFFSET(G99, -4, 0) -> 0.019348769 | AG99: =OFFSET(G99, -5, 0) -> 0.00054649233 | AH99: =OFFSET(H99, -1, 0) -> 0.045509162 | AI99: =OFFSET(H99, -2, 0) -> -0.043097256 | AJ99: =OFFSET(H99, -3, 0) -> -0.022519141 | AK99: =OFFSET(H99, -4, 0) -> -0.007064967 | AL99: =OFFSET(H99, -5, 0) -> 0.0092807425 | AP99: 0.0625 | AQ99: 2362.72 | AR99: 6.658
A100: 45078 | B100: 0.018567275 | C100: 0.036766197 | E100: -0.007123851 | F100: =(AP100-AP101)/AP101 -> 0 | G100: =(AQ100-AQ101)/AQ101 -> 0.037198261 | H100: =(AR100-AR101)/AR101 -> 0.07226471 | I100: =OFFSET(C100, -1, 0) -> -0.12011383 | J100: =OFFSET(C100, -2, 0) -> 0.014562409 | K100: =OFFSET(C100, -3, 0) -> -0.018072781 | L100: =OFFSET(C100, -4, 0) -> -0.038946128 | M100: =OFFSET(C102, -5, 0) -> -0.018072781 | N100: =OFFSET(D100, -1, 0) -> 0 | O100: =OFFSET(D100, -2, 0) -> 0 | P100: =OFFSET(D100, -3, 0) -> -0.060064935 | Q100: =OFFSET(D100, -4, 0) -> 0.0016260163 | R100: =OFFSET(D100, -5, 0) -> 0.11818182 | S100: =OFFSET(E100, -1, 0) -> 0.01174743 | T100: =OFFSET(E100, -2, 0) -> -0.0053554041 | U100: =OFFSET(E100, -2, 0) -> -0.0053554041 | V100: =OFFSET(E100, -4, 0) -> 0.01102289 | W100: =OFFSET(E100, -5, 0) -> -0.011823446 | X100: =OFFSET(F100, -1, 0) -> 0 | Y100: =OFFSET(F100, -2, 0) -> 0 | Z100: =OFFSET(F100, -3, 0) -> 0 | AA100: =OFFSET(F100, -4, 0) -> 0 | AB100: =OFFSET(F100, -5, 0) -> 0 | AC100: =OFFSET(G100, -1, 0) -> -0.00038923017 | AD100: =OFFSET(G100, -2, 0) -> 0.0090912169 | AE100: =OFFSET(G100, -3, 0) -> 0.01157621 | AF100: =OFFSET(G100, -4, 0) -> 0.004813832 | AG100: =OFFSET(G100, -5, 0) -> 0.019348769 | AH100: =OFFSET(H100, -1, 0) -> -0.030858806 | AI100: =OFFSET(H100, -2, 0) -> 0.045509162 | AJ100: =OFFSET(H100, -3, 0) -> -0.043097256 | AK100: =OFFSET(H100, -4, 0) -> -0.022519141 | AL100: =OFFSET(H100, -5, 0) -> -0.007064967 | AP100: 0.0625 | AQ100: 2363.64 | AR100: 6.87
A101: 45108 | B101: 0.044164457 | C101: 0.14668069 | E101: 0.0018150589 | F101: =(AP101-AP102)/AP102 -> 0 | G101: =(AQ101-AQ102)/AQ102 -> 0.017884341 | H101: =(AR101-AR102)/AR102 -> -0.016124079 | I101: =OFFSET(C101, -1, 0) -> 0.036766197 | J101: =OFFSET(C101, -2, 0) -> -0.12011383 | K101: =OFFSET(C101, -3, 0) -> 0.014562409 | L101: =OFFSET(C101, -4, 0) -> -0.018072781 | M101: =OFFSET(C103, -5, 0) -> 0.014562409 | N101: =OFFSET(D101, -1, 0) -> 0 | O101: =OFFSET(D101, -2, 0) -> 0 | P101: =OFFSET(D101, -3, 0) -> 0 | Q101: =OFFSET(D101, -4, 0) -> -0.060064935 | R101: =OFFSET(D101, -5, 0) -> 0.0016260163 | S101: =OFFSET(E101, -1, 0) -> -0.007123851 | T101: =OFFSET(E101, -2, 0) -> 0.01174743 | U101: =OFFSET(E101, -2, 0) -> 0.01174743 | V101: =OFFSET(E101, -4, 0) -> -0.0058083253 | W101: =OFFSET(E101, -5, 0) -> 0.01102289 | X101: =OFFSET(F101, -1, 0) -> 0 | Y101: =OFFSET(F101, -2, 0) -> 0 | Z101: =OFFSET(F101, -3, 0) -> 0 | AA101: =OFFSET(F101, -4, 0) -> 0 | AB101: =OFFSET(F101, -5, 0) -> 0 | AC101: =OFFSET(G101, -1, 0) -> 0.037198261 | AD101: =OFFSET(G101, -2, 0) -> -0.00038923017 | AE101: =OFFSET(G101, -3, 0) -> 0.0090912169 | AF101: =OFFSET(G101, -4, 0) -> 0.01157621 | AG101: =OFFSET(G101, -5, 0) -> 0.004813832 | AH101: =OFFSET(H101, -1, 0) -> 0.07226471 | AI101: =OFFSET(H101, -2, 0) -> -0.030858806 | AJ101: =OFFSET(H101, -3, 0) -> 0.045509162 | AK101: =OFFSET(H101, -4, 0) -> -0.043097256 | AL101: =OFFSET(H101, -5, 0) -> -0.022519141 | AP101: 0.0625 | AQ101: 2278.87 | AR101: 6.407
A102: 45139 | B102: 0.021047425 | C102: 0.022125064 | E102: 0.0056177043 | F102: =(AP102-AP103)/AP103 -> 0 | G102: =(AQ102-AQ103)/AQ103 -> 0.018200754 | H102: =(AR102-AR103)/AR103 -> 0.043088259 | I102: =OFFSET(C102, -1, 0) -> 0.14668069 | J102: =OFFSET(C102, -2, 0) -> 0.036766197 | K102: =OFFSET(C102, -3, 0) -> -0.12011383 | L102: =OFFSET(C102, -4, 0) -> 0.014562409 | M102: =OFFSET(C104, -5, 0) -> -0.12011383 | N102: =OFFSET(D102, -1, 0) -> 0 | O102: =OFFSET(D102, -2, 0) -> 0 | P102: =OFFSET(D102, -3, 0) -> 0 | Q102: =OFFSET(D102, -4, 0) -> 0 | R102: =OFFSET(D102, -5, 0) -> -0.060064935 | S102: =OFFSET(E102, -1, 0) -> 0.0018150589 | T102: =OFFSET(E102, -2, 0) -> -0.007123851 | U102: =OFFSET(E102, -2, 0) -> -0.007123851 | V102: =OFFSET(E102, -4, 0) -> -0.0053554041 | W102: =OFFSET(E102, -5, 0) -> -0.0058083253 | X102: =OFFSET(F102, -1, 0) -> 0 | Y102: =OFFSET(F102, -2, 0) -> 0 | Z102: =OFFSET(F102, -3, 0) -> 0 | AA102: =OFFSET(F102, -4, 0) -> 0 | AB102: =OFFSET(F102, -5, 0) -> 0 | AC102: =OFFSET(G102, -1, 0) -> 0.017884341 | AD102: =OFFSET(G102, -2, 0) -> 0.037198261 | AE102: =OFFSET(G102, -3, 0) -> -0.00038923017 | AF102: =OFFSET(G102, -4, 0) -> 0.0090912169 | AG102: =OFFSET(G102, -5, 0) -> 0.01157621 | AH102: =OFFSET(H102, -1, 0) -> -0.016124079 | AI102: =OFFSET(H102, -2, 0) -> 0.07226471 | AJ102: =OFFSET(H102, -3, 0) -> -0.030858806 | AK102: =OFFSET(H102, -4, 0) -> 0.045509162 | AL102: =OFFSET(H102, -5, 0) -> -0.043097256 | AP102: 0.0625 | AQ102: 2238.83 | AR102: 6.512
A103: 45170 | B103: -0.015229233 | C103: 0.08214684 | E103: 0.0039660468 | F103: =(AP103-AP104)/AP104 -> 0 | G103: =(AQ103-AQ104)/AQ104 -> 0.034174447 | H103: =(AR103-AR104)/AR104 -> -0.093246187 | I103: =OFFSET(C103, -1, 0) -> 0.022125064 | J103: =OFFSET(C103, -2, 0) -> 0.14668069 | K103: =OFFSET(C103, -3, 0) -> 0.036766197 | L103: =OFFSET(C103, -4, 0) -> -0.12011383 | M103: =OFFSET(C105, -5, 0) -> 0.036766197 | N103: =OFFSET(D103, -1, 0) -> 0 | O103: =OFFSET(D103, -2, 0) -> 0 | P103: =OFFSET(D103, -3, 0) -> 0 | Q103: =OFFSET(D103, -4, 0) -> 0 | R103: =OFFSET(D103, -5, 0) -> 0 | S103: =OFFSET(E103, -1, 0) -> 0.0056177043 | T103: =OFFSET(E103, -2, 0) -> 0.0018150589 | U103: =OFFSET(E103, -2, 0) -> 0.0018150589 | V103: =OFFSET(E103, -4, 0) -> 0.01174743 | W103: =OFFSET(E103, -5, 0) -> -0.0053554041 | X103: =OFFSET(F103, -1, 0) -> 0 | Y103: =OFFSET(F103, -2, 0) -> 0 | Z103: =OFFSET(F103, -3, 0) -> 0 | AA103: =OFFSET(F103, -4, 0) -> 0 | AB103: =OFFSET(F103, -5, 0) -> 0 | AC103: =OFFSET(G103, -1, 0) -> 0.018200754 | AD103: =OFFSET(G103, -2, 0) -> 0.017884341 | AE103: =OFFSET(G103, -3, 0) -> 0.037198261 | AF103: =OFFSET(G103, -4, 0) -> -0.00038923017 | AG103: =OFFSET(G103, -5, 0) -> 0.0090912169 | AH103: =OFFSET(H103, -1, 0) -> 0.043088259 | AI103: =OFFSET(H103, -2, 0) -> -0.016124079 | AJ103: =OFFSET(H103, -3, 0) -> 0.07226471 | AK103: =OFFSET(H103, -4, 0) -> -0.030858806 | AL103: =OFFSET(H103, -5, 0) -> 0.045509162 | AP103: 0.0625 | AQ103: 2198.81 | AR103: 6.243
A104: 45200 | B104: 0.0047967385 | C104: -0.11385311 | E104: 0.0027219077 | F104: =(AP104-AP105)/AP105 -> -0.038461538 | G104: =(AQ104-AQ105)/AQ105 -> -0.019425625 | H104: =(AR104-AR105)/AR105 -> -0.010491521 | I104: =OFFSET(C104, -1, 0) -> 0.08214684 | J104: =OFFSET(C104, -2, 0) -> 0.022125064 | K104: =OFFSET(C104, -3, 0) -> 0.14668069 | L104: =OFFSET(C104, -4, 0) -> 0.036766197 | M104: =OFFSET(C106, -5, 0) -> 0.14668069 | N104: =OFFSET(D104, -1, 0) -> 0 | O104: =OFFSET(D104, -2, 0) -> 0 | P104: =OFFSET(D104, -3, 0) -> 0 | Q104: =OFFSET(D104, -4, 0) -> 0 | R104: =OFFSET(D104, -5, 0) -> 0 | S104: =OFFSET(E104, -1, 0) -> 0.0039660468 | T104: =OFFSET(E104, -2, 0) -> 0.0056177043 | U104: =OFFSET(E104, -2, 0) -> 0.0056177043 | V104: =OFFSET(E104, -4, 0) -> -0.007123851 | W104: =OFFSET(E104, -5, 0) -> 0.01174743 | X104: =OFFSET(F104, -1, 0) -> 0 | Y104: =OFFSET(F104, -2, 0) -> 0 | Z104: =OFFSET(F104, -3, 0) -> 0 | AA104: =OFFSET(F104, -4, 0) -> 0 | AB104: =OFFSET(F104, -5, 0) -> 0 | AC104: =OFFSET(G104, -1, 0) -> 0.034174447 | AD104: =OFFSET(G104, -2, 0) -> 0.018200754 | AE104: =OFFSET(G104, -3, 0) -> 0.017884341 | AF104: =OFFSET(G104, -4, 0) -> 0.037198261 | AG104: =OFFSET(G104, -5, 0) -> -0.00038923017 | AH104: =OFFSET(H104, -1, 0) -> -0.093246187 | AI104: =OFFSET(H104, -2, 0) -> 0.043088259 | AJ104: =OFFSET(H104, -3, 0) -> -0.016124079 | AK104: =OFFSET(H104, -4, 0) -> 0.07226471 | AL104: =OFFSET(H104, -5, 0) -> -0.030858806 | AP104: 0.0625 | AQ104: 2126.15 | AR104: 6.885
A105: 45231 | B105: -0.028019975 | C105: -0.064489152 | E105: 0.0012131258 | F105: =(AP105-AP106)/AP106 -> 0 | G105: =(AQ105-AQ106)/AQ106 -> -0.0012344826 | H105: =(AR105-AR106)/AR106 -> -0.02137834 | I105: =OFFSET(C105, -1, 0) -> -0.11385311 | J105: =OFFSET(C105, -2, 0) -> 0.08214684 | K105: =OFFSET(C105, -3, 0) -> 0.022125064 | L105: =OFFSET(C105, -4, 0) -> 0.14668069 | M105: =OFFSET(C107, -5, 0) -> 0.022125064 | N105: =OFFSET(D105, -1, 0) -> 0 | O105: =OFFSET(D105, -2, 0) -> 0 | P105: =OFFSET(D105, -3, 0) -> 0 | Q105: =OFFSET(D105, -4, 0) -> 0 | R105: =OFFSET(D105, -5, 0) -> 0 | S105: =OFFSET(E105, -1, 0) -> 0.0027219077 | T105: =OFFSET(E105, -2, 0) -> 0.0039660468 | U105: =OFFSET(E105, -2, 0) -> 0.0039660468 | V105: =OFFSET(E105, -4, 0) -> 0.0018150589 | W105: =OFFSET(E105, -5, 0) -> -0.007123851 | X105: =OFFSET(F105, -1, 0) -> -0.038461538 | Y105: =OFFSET(F105, -2, 0) -> 0 | Z105: =OFFSET(F105, -3, 0) -> 0 | AA105: =OFFSET(F105, -4, 0) -> 0 | AB105: =OFFSET(F105, -5, 0) -> 0 | AC105: =OFFSET(G105, -1, 0) -> -0.019425625 | AD105: =OFFSET(G105, -2, 0) -> 0.034174447 | AE105: =OFFSET(G105, -3, 0) -> 0.018200754 | AF105: =OFFSET(G105, -4, 0) -> 0.017884341 | AG105: =OFFSET(G105, -5, 0) -> 0.037198261 | AH105: =OFFSET(H105, -1, 0) -> -0.010491521 | AI105: =OFFSET(H105, -2, 0) -> -0.093246187 | AJ105: =OFFSET(H105, -3, 0) -> 0.043088259 | AK105: =OFFSET(H105, -4, 0) -> -0.016124079 | AL105: =OFFSET(H105, -5, 0) -> 0.07226471 | AP105: 0.065 | AQ105: 2168.27 | AR105: 6.958
A106: 45261 | B106: 0.06517059 | C106: -0.058413732 | E106: -0.002003431 | F106: =(AP106-AP107)/AP107 -> 0 | G106: =(AQ106-AQ107)/AQ107 -> -0.0012191756 | H106: =(AR106-AR107)/AR107 -> -0.0073991344 | I106: =OFFSET(C106, -1, 0) -> -0.064489152 | J106: =OFFSET(C106, -2, 0) -> -0.11385311 | K106: =OFFSET(C106, -3, 0) -> 0.08214684 | L106: =OFFSET(C106, -4, 0) -> 0.022125064 | M106: =OFFSET(C108, -5, 0) -> 0.08214684 | N106: =OFFSET(D106, -1, 0) -> 0 | O106: =OFFSET(D106, -2, 0) -> 0 | P106: =OFFSET(D106, -3, 0) -> 0 | Q106: =OFFSET(D106, -4, 0) -> 0 | R106: =OFFSET(D106, -5, 0) -> 0 | S106: =OFFSET(E106, -1, 0) -> 0.0012131258 | T106: =OFFSET(E106, -2, 0) -> 0.0027219077 | U106: =OFFSET(E106, -2, 0) -> 0.0027219077 | V106: =OFFSET(E106, -4, 0) -> 0.0056177043 | W106: =OFFSET(E106, -5, 0) -> 0.0018150589 | X106: =OFFSET(F106, -1, 0) -> 0 | Y106: =OFFSET(F106, -2, 0) -> -0.038461538 | Z106: =OFFSET(F106, -3, 0) -> 0 | AA106: =OFFSET(F106, -4, 0) -> 0 | AB106: =OFFSET(F106, -5, 0) -> 0 | AC106: =OFFSET(G106, -1, 0) -> -0.0012344826 | AD106: =OFFSET(G106, -2, 0) -> -0.019425625 | AE106: =OFFSET(G106, -3, 0) -> 0.034174447 | AF106: =OFFSET(G106, -4, 0) -> 0.018200754 | AG106: =OFFSET(G106, -5, 0) -> 0.017884341 | AH106: =OFFSET(H106, -1, 0) -> -0.02137834 | AI106: =OFFSET(H106, -2, 0) -> -0.010491521 | AJ106: =OFFSET(H106, -3, 0) -> -0.093246187 | AK106: =OFFSET(H106, -4, 0) -> 0.043088259 | AL106: =OFFSET(H106, -5, 0) -> -0.016124079 | AP106: 0.065 | AQ106: 2170.95 | AR106: 7.11
A107: 45292 | B107: 0.070202921 | C107: 0.056964552 | E107: -0.0011419642 | F107: =(AP107-AP108)/AP108 -> 0 | G107: =(AQ107-AQ108)/AQ108 -> 0.035609807 | H107: =(AR107-AR108)/AR108 -> -0.038265306 | I107: =OFFSET(C107, -1, 0) -> -0.058413732 | J107: =OFFSET(C107, -2, 0) -> -0.064489152 | K107: =OFFSET(C107, -3, 0) -> -0.11385311 | L107: =OFFSET(C107, -4, 0) -> 0.08214684 | M107: =OFFSET(C109, -5, 0) -> -0.11385311 | N107: =OFFSET(D107, -1, 0) -> 0 | O107: =OFFSET(D107, -2, 0) -> 0 | P107: =OFFSET(D107, -3, 0) -> 0 | Q107: =OFFSET(D107, -4, 0) -> 0 | R107: =OFFSET(D107, -5, 0) -> 0 | S107: =OFFSET(E107, -1, 0) -> -0.002003431 | T107: =OFFSET(E107, -2, 0) -> 0.0012131258 | U107: =OFFSET(E107, -2, 0) -> 0.0012131258 | V107: =OFFSET(E107, -4, 0) -> 0.0039660468 | W107: =OFFSET(E107, -5, 0) -> 0.0056177043 | X107: =OFFSET(F107, -1, 0) -> 0 | Y107: =OFFSET(F107, -2, 0) -> 0 | Z107: =OFFSET(F107, -3, 0) -> -0.038461538 | AA107: =OFFSET(F107, -4, 0) -> 0 | AB107: =OFFSET(F107, -5, 0) -> 0 | AC107: =OFFSET(G107, -1, 0) -> -0.0012191756 | AD107: =OFFSET(G107, -2, 0) -> -0.0012344826 | AE107: =OFFSET(G107, -3, 0) -> -0.019425625 | AF107: =OFFSET(G107, -4, 0) -> 0.034174447 | AG107: =OFFSET(G107, -5, 0) -> 0.018200754 | AH107: =OFFSET(H107, -1, 0) -> -0.0073991344 | AI107: =OFFSET(H107, -2, 0) -> -0.02137834 | AJ107: =OFFSET(H107, -3, 0) -> -0.010491521 | AK107: =OFFSET(H107, -4, 0) -> -0.093246187 | AL107: =OFFSET(H107, -5, 0) -> 0.043088259 | AP107: 0.065 | AQ107: 2173.6 | AR107: 7.163
A108: 45323 | B108: -0.0020465323 | C108: 0.031278911 | E108: -0.0023467116 | F108: =(AP108-AP109)/AP109 -> 0 | G108: =(AQ108-AQ109)/AQ109 -> 0.00091084671 | H108: =(AR108-AR109)/AR109 -> -0.0030785705 | I108: =OFFSET(C108, -1, 0) -> 0.056964552 | J108: =OFFSET(C108, -2, 0) -> -0.058413732 | K108: =OFFSET(C108, -3, 0) -> -0.064489152 | L108: =OFFSET(C108, -4, 0) -> -0.11385311 | M108: =OFFSET(C110, -5, 0) -> -0.064489152 | N108: =OFFSET(D108, -1, 0) -> 0 | O108: =OFFSET(D108, -2, 0) -> 0 | P108: =OFFSET(D108, -3, 0) -> 0 | Q108: =OFFSET(D108, -4, 0) -> 0 | R108: =OFFSET(D108, -5, 0) -> 0 | S108: =OFFSET(E108, -1, 0) -> -0.0011419642 | T108: =OFFSET(E108, -2, 0) -> -0.002003431 | U108: =OFFSET(E108, -2, 0) -> -0.002003431 | V108: =OFFSET(E108, -4, 0) -> 0.0027219077 | W108: =OFFSET(E108, -5, 0) -> 0.0039660468 | X108: =OFFSET(F108, -1, 0) -> 0 | Y108: =OFFSET(F108, -2, 0) -> 0 | Z108: =OFFSET(F108, -3, 0) -> 0 | AA108: =OFFSET(F108, -4, 0) -> -0.038461538 | AB108: =OFFSET(F108, -5, 0) -> 0 | AC108: =OFFSET(G108, -1, 0) -> 0.035609807 | AD108: =OFFSET(G108, -2, 0) -> -0.0012191756 | AE108: =OFFSET(G108, -3, 0) -> -0.0012344826 | AF108: =OFFSET(G108, -4, 0) -> -0.019425625 | AG108: =OFFSET(G108, -5, 0) -> 0.034174447 | AH108: =OFFSET(H108, -1, 0) -> -0.038265306 | AI108: =OFFSET(H108, -2, 0) -> -0.0073991344 | AJ108: =OFFSET(H108, -3, 0) -> -0.02137834 | AK108: =OFFSET(H108, -4, 0) -> -0.010491521 | AL108: =OFFSET(H108, -5, 0) -> -0.093246187 | AP108: 0.065 | AQ108: 2098.86 | AR108: 7.448
A109: 45352 | B109: 0.029128097 | C109: 0.060850089 | E109: 0.0054282268 | F109: =(AP109-AP110)/AP110 -> 0 | G109: =(AQ109-AQ110)/AQ110 -> 0.01532465 | H109: =(AR109-AR110)/AR110 -> 0.0048419637 | I109: =OFFSET(C109, -1, 0) -> 0.031278911 | J109: =OFFSET(C109, -2, 0) -> 0.056964552 | K109: =OFFSET(C109, -3, 0) -> -0.058413732 | L109: =OFFSET(C109, -4, 0) -> -0.064489152 | M109: =OFFSET(C111, -5, 0) -> -0.058413732 | N109: =OFFSET(D109, -1, 0) -> 0 | O109: =OFFSET(D109, -2, 0) -> 0 | P109: =OFFSET(D109, -3, 0) -> 0 | Q109: =OFFSET(D109, -4, 0) -> 0 | R109: =OFFSET(D109, -5, 0) -> 0 | S109: =OFFSET(E109, -1, 0) -> -0.0023467116 | T109: =OFFSET(E109, -2, 0) -> -0.0011419642 | U109: =OFFSET(E109, -2, 0) -> -0.0011419642 | V109: =OFFSET(E109, -4, 0) -> 0.0012131258 | W109: =OFFSET(E109, -5, 0) -> 0.0027219077 | X109: =OFFSET(F109, -1, 0) -> 0 | Y109: =OFFSET(F109, -2, 0) -> 0 | Z109: =OFFSET(F109, -3, 0) -> 0 | AA109: =OFFSET(F109, -4, 0) -> 0 | AB109: =OFFSET(F109, -5, 0) -> -0.038461538 | AC109: =OFFSET(G109, -1, 0) -> 0.00091084671 | AD109: =OFFSET(G109, -2, 0) -> 0.035609807 | AE109: =OFFSET(G109, -3, 0) -> -0.0012191756 | AF109: =OFFSET(G109, -4, 0) -> -0.0012344826 | AG109: =OFFSET(G109, -5, 0) -> -0.019425625 | AH109: =OFFSET(H109, -1, 0) -> -0.0030785705 | AI109: =OFFSET(H109, -2, 0) -> -0.038265306 | AJ109: =OFFSET(H109, -3, 0) -> -0.0073991344 | AK109: =OFFSET(H109, -4, 0) -> -0.02137834 | AL109: =OFFSET(H109, -5, 0) -> -0.010491521 | AP109: 0.065 | AQ109: 2096.95 | AR109: 7.471
... A121: 45717 | B121: -0.059790027 | C121: 0.024356911 | E121: -0.022990477 | F121: =(AP121-AP122)/AP122 -> #DIV/0! | G121: =(AQ121-AQ122)/AQ122 -> 0.010491439 | H121: =(AR121-AR122)/AR122 -> -0.0057251908 | I121: =OFFSET(C121, -1, 0) -> -0.03893949 | J121: =OFFSET(C121, -2, 0) -> 0.011230621 | K121: =OFFSET(C121, -3, 0) -> 0.053261944 | L121: =OFFSET(C121, -4, 0) -> -0.018359834 | M121: =OFFSET(C123, -5, 0) -> 0.053261944 | N121: =OFFSET(D121, -1, 0) -> 0 | O121: =OFFSET(D121, -2, 0) -> 0 | P121: =OFFSET(D121, -3, 0) -> 0 | Q121: =OFFSET(D121, -4, 0) -> 0 | R121: =OFFSET(D121, -5, 0) -> 0 | S121: =OFFSET(E121, -1, 0) -> 0.010512818 | T121: =OFFSET(E121, -2, 0) -> 0.011770344 | U121: =OFFSET(E121, -2, 0) -> 0.011770344 | V121: =OFFSET(E121, -4, 0) -> 0.0059242693 | W121: =OFFSET(E121, -5, 0) -> 0.0036535132 | X121: =OFFSET(F121, -1, 0) -> 0 | Y121: =OFFSET(F121, -2, 0) -> 0 | Z121: =OFFSET(F121, -3, 0) -> -0.033333333 | AA121: =OFFSET(F121, -4, 0) -> -0.068965517 | AB121: =OFFSET(F121, -5, 0) -> 0 | AC121: =OFFSET(G121, -1, 0) -> -0.021011773 | AD121: =OFFSET(G121, -2, 0) -> 0.01974204 | AE121: =OFFSET(G121, -3, 0) -> -0.062580805 | AF121: =OFFSET(G121, -4, 0) -> -0.02644282 | AG121: =OFFSET(G121, -5, 0) -> 0.082983078 | AH121: =OFFSET(H121, -1, 0) -> 0.0058861164 | AI121: =OFFSET(H121, -2, 0) -> -0.0069965653 | AJ121: =OFFSET(H121, -3, 0) -> -0.0028183449 | AK121: =OFFSET(H121, -4, 0) -> -0.03147482 | AL121: =OFFSET(H121, -5, 0) -> 0.013397002 | AP121: 0.075 | AQ121: 2107.39 | AR121: 7.815
A122: 45748 | B122: 0.046222206 | C122: -0.20536053 | E122: -0.010074889 | F122: =(AP122-AP123)/AP123 -> #DIV/0! | G122: =(AQ122-AQ123)/AQ123 -> #DIV/0! | H122: =(AR122-AR123)/AR123 -> #DIV/0! | I122: =OFFSET(C122, -1, 0) -> 0.024356911 | J122: =OFFSET(C122, -2, 0) -> -0.03893949 | K122: =OFFSET(C122, -3, 0) -> 0.011230621 | L122: =OFFSET(C122, -4, 0) -> 0.053261944 | M122: =OFFSET(C124, -5, 0) -> 0.011230621 | N122: =OFFSET(D122, -1, 0) -> 0 | O122: =OFFSET(D122, -2, 0) -> 0 | P122: =OFFSET(D122, -3, 0) -> 0 | Q122: =OFFSET(D122, -4, 0) -> 0 | R122: =OFFSET(D122, -5, 0) -> 0 | S122: =OFFSET(E122, -1, 0) -> -0.022990477 | T122: =OFFSET(E122, -2, 0) -> 0.010512818 | U122: =OFFSET(E122, -2, 0) -> 0.010512818 | V122: =OFFSET(E122, -4, 0) -> 0.011766932 | W122: =OFFSET(E122, -5, 0) -> 0.0059242693 | X122: =OFFSET(F122, -1, 0) -> #DIV/0! | Y122: =OFFSET(F122, -2, 0) -> 0 | Z122: =OFFSET(F122, -3, 0) -> 0 | AA122: =OFFSET(F122, -4, 0) -> -0.033333333 | AB122: =OFFSET(F122, -5, 0) -> -0.068965517 | AC122: =OFFSET(G122, -1, 0) -> 0.010491439 | AD122: =OFFSET(G122, -2, 0) -> -0.021011773 | AE122: =OFFSET(G122, -3, 0) -> 0.01974204 | AF122: =OFFSET(G122, -4, 0) -> -0.062580805 | AG122: =OFFSET(G122, -5, 0) -> -0.02644282 | AH122: =OFFSET(H122, -1, 0) -> -0.0057251908 | AI122: =OFFSET(H122, -2, 0) -> 0.0058861164 | AJ122: =OFFSET(H122, -3, 0) -> -0.0069965653 | AK122: =OFFSET(H122, -4, 0) -> -0.0028183449 | AL122: =OFFSET(H122, -5, 0) -> -0.03147482 | AQ122: 2085.51 | AR122: 7.86

Sheet Lag Study
A2: Crude Lag Study | K2: Inflation Lag Study | Z2: Currency Lag Study | AO2: Repo Lag Study | BC2: S&P Lag Study | BN2: Bond Lag Study
A3: SUMMARY OUTPUT | K3: SUMMARY OUTPUT | Z3: SUMMARY OUTPUT | AO3: SUMMARY OUTPUT | BC3: SUMMARY OUTPUT | BN3: SUMMARY OUTPUT
A5: Regression Statistics | K5: Regression Statistics | Z5: Regression Statistics | AO5: Regression Statistics | BC5: Regression Statistics | BN5: Regression Statistics
A6: Multiple R | B6: 0.53428159 | K6: Multiple R | L6: 0.32551884 | Z6: Multiple R | AA6: 0.47919177 | AO6: Multiple R | AP6: 0.27514502 | BC6: Multiple R | BD6: 0.24813035 | BN6: Multiple R | BO6: 0.24891016
A7: R Square | B7: 0.28545682 | K7: R Square | L7: 0.10596252 | Z7: R Square | AA7: 0.22962476 | AO7: R Square | AP7: 0.075704782 | BC7: R Square | BD7: 0.061568669 | BN7: R Square | BO7: 0.061956265
A8: Adjusted R Square | B8: 0.24210656 | K8: Adjusted R Square | L8: 0.055164932 | Z8: Adjusted R Square | AA8: 0.18376519 | AO8: Adjusted R Square | AP8: 0.023188009 | BC8: Adjusted R Square | BD8: 0.008248707 | BN8: Adjusted R Square | BO8: 0.008658326
A9: Standard Error | B9: 0.044435858 | K9: Standard Error | L9: 0.049986285 | Z9: Standard Error | AA9: 0.046139246 | AO9: Standard Error | AP9: 0.050825113 | BC9: Standard Error | BD9: 0.051212296 | BN9: Standard Error | BO9: 0.051201719
A10: Observations | B10: 94 | K10: Observations | L10: 94 | Z10: Observations | AA10: 94 | AO10: Observations | AP10: 94 | BC10: Observations | BD10: 94 | BN10: Observations | BO10: 94
A12: ANOVA | K12: ANOVA | Z12: ANOVA | AO12: ANOVA | BC12: ANOVA | BN12: ANOVA
B13: df | C13: SS | D13: MS | E13: F | F13: Significance F | L13: df | M13: SS | N13: MS | O13: F | P13: Significance F | AA13: df | AB13: SS | AC13: MS | AD13: F | AE13: Significance F | AP13: df | AQ13: SS | AR13: MS | AS13: F | AT13: Significance F | BD13: df | BE13: SS | BF13: MS | BG13: F | BH13: Significance F | BO13: df | BP13: SS | BQ13: MS | BR13: F | BS13: Significance F
A14: Regression | B14: 5 | C14: 0.070205169 | D14: 0.014041034 | E14: 8.8887759 | F14: 7.3215641e-07 | K14: Regression | L14: 5 | M14: 0.026060391 | N14: 0.0052120783 | O14: 2.0859755 | P14: 0.074613855 | Z14: Regression | AA14: 5 | AB14: 0.056473848 | AC14: 0.01129477 | AD14: 6.6320288 | AE14: 2.7724895e-05 | AO14: Regression | AP14: 5 | AQ14: 0.018618813 | AR14: 0.0037237626 | AS14: 1.4415353 | AT14: 0.21737144 | BC14: Regression | BD14: 5 | BE14: 0.015142181 | BF14: 0.0030284362 | BG14: 1.154702 | BH14: 0.33795944 | BN14: Regression | BO14: 5 | BP14: 0.015237506 | BQ14: 0.0030475013 | BR14: 1.1624514 | BS14: 0.33409448
